Workbook
Name AdhesiveList: #REF!
Name amount: #REF!
Name BagTypeList: #REF!
Name Barier: #REF!
Name Clear: #REF!
Name Config_302FG: #REF!
Name Config_302FGW: #REF!
Name Config_306: #REF!
Name Config_308: #REF!
Name Config_312FG: #REF!
Name Config_312W: #REF!
Name Config_NKR: #REF!
Name Config_PL2021: "'Film Pricing- New'!$AF$10:$AF$20"
Name Config_PL2022: "'Film Pricing- New'!$AG$10:$AG$20"
Name Config_PL2023: "'Film Pricing- New'!$AH$10:$AH$20"
Name Family: #REF!
Name Film_type: '[1]List of names'!$Y$15:$Y$16
Name Film_type: #REF!
Name FilmList: #REF!
Name GF048.1: #REF!
Name Grouped: #REF!
Name HardenerList: #REF!
Name JOB: OFFSET('[2]GEF063 WP Sales'!B6,0,0,COUNTA('[2]GEF063 WP Sales'!$AS$11:$AS$200),COUNTA('[2]GEF063 WP Sales'!$AS$11:$AT$11))
Name JOB: OFFSET(#REF!,0,0,COUNTA(#REF!),COUNTA(#REF!))
Name Jobs: '[2]GEF063 WP Sales'!$AS$10:$AS$210+'[2]GEF063 WP Sales'!$AU$10-2
Name Jobs: #REF!+#REF!-2
Name Jobss: '[2]GEF063 WP Sales'!XFC2:XFC2+VALUE('[2]GEF063 WP Sales'!$AU$10)
Name Jobss: #REF!+VALUE(#REF!)
Name Laminate: '[1]List of names'!$P$15:$P$22
Name Laminate: #REF!
Name Laminate_Thickness: #REF!
Name Laminate_type: '[1]List of names'!$P$14:$X$14
Name Laminate_type: #REF!
Name Laminate106: [3]!Table2[Laminate106]
Name Laminate106: [3]!Table2[Laminate106]
Name Laminate106: #REF!
Name Laminate604: [3]!Table4[Laminate618]
Name Laminate604: [1]!Table4[Laminate618]
Name Laminate604: [3]!Table4[Laminate618]
Name Laminate604: #REF!
Name Laminate607: [3]!Table6[Laminate607]
Name Laminate607: [3]!Table6[Laminate607]
Name Laminate607: #REF!
Name Laminate607\: [3]!Table6[Laminate607]
Name Laminate607\: [1]!Table6[Laminate607]
Name Laminate607\: [3]!Table6[Laminate607]
Name Laminate607\: #REF!
Name Laminate608W: [3]!Table3[Laminate608W]
Name Laminate608W: [1]!Table3[Laminate608W]
Name Laminate608W: [3]!Table3[Laminate608W]
Name Laminate608W: #REF!
Name LaminateList: #REF!
Name MATERIAL: '[4]Raw materials prices'!$L$51:$L$61
Name MATERIAL: #REF!
Name Materials: '[5]list for drop down menu'!$A$1:$A$20
Name Materials: #REF!
Name Metalize: #REF!
Name NKR: #REF!
Name Paper: #REF!
Name pirce: #REF!

Sheet Sheet1
A3: Film | B3: Grade | C3: Sum of Price Calculated(€) Thickness & QTY related
A4: TIPA 302FG | B4: S723 | C4: 0.2424
B5: S724 | C5: 0.02352
A6: TIPA 302FG W | B6: S723 | C6: 0.2424
B7: S724 | C7: 0.09408
A8: TIPA 306M | B8: S723 | C8: 0.2424
B9: S724 | C9: 0.0588
A10: TIPA 306W | B10: S723 | C10: 0.2424
B11: S724 | C11: 0.1176
A12: TIPA 312 MFG | B12: S723 | C12: 0.2424
B13: S724 | C13: 0.06762
A14: TIPA 312MFGW | B14: S723 | C14: 0.2424
B15: S724 | C15: 0.06762
A16: Grand Total | C16: 1.88364
A20: Film | B20: Price (€/kg) | C20: Price ($/kg)
A21: PL202.1 | B21: 8.995784 | C21: 10.435109
A22: PL202.2 | B22: 6.73178 | C22: 7.8088648
A23: PL202.3 | B23: 5.74578 | C23: 6.6651048
A24: TIPA 302FG | B24: 3.599712 | C24: 4.1756659
A25: TIPA 302FG W | B25: 3.916872 | C25: 4.5435715
A26: TIPA 306M | B26: 3.520798 | C26: 4.0841257
A27: TIPA 306W | B27: 3.805774 | C27: 4.4146978
A28: TIPA 312 MFG | B28: 2.899978 | C28: 3.3639745
A29: TIPA 312MFGW | B29: 3.178978 | C29: 3.6876145
A32: FILM | B32: Material | C32: % from Total
A33: TIPA 302FG | B33: S723 | C33: =C4/$B$24 -> 0.06733872
B34: S724 | C34: =C5/$B$24 -> 0.006533856
A35: TIPA 302FG W | B35: S723 | C35: =C6/$B$25 -> 0.061886117
B36: S724 | C36: =C7/$B$25 -> 0.024019166
A37: TIPA 306M | B37: S723 | C37: =C8/$B$26 -> 0.068848028
B38: S724 | C38: =C9/$B$26 -> 0.016700759
A39: TIPA 306W | B39: S723 | C39: =C10/$B$27 -> 0.063692694
B40: S724 | C40: =C11/$B$27 -> 0.030900416
A41: TIPA 312 MFG | B41: S723 | C41: =C12/$B$28 -> 0.083586841
B42: S724 | C42: =C13/$B$28 -> 0.023317418
A43: TIPA 312MFGW | B43: S723 | C43: =C14/$B$29 -> 0.076250921
B44: S724 | C44: =C15/$B$29 -> 0.021270987

Sheet Laminated bags - Sales
Q1: ה NF יותר יקר מה FG בגלל אחוזי הרווחיות השונים בין הסיגמנטים
C3: Dimenssions
C4: Height (mm) | D4: Width(mm) | E4: Base (mm) | F4: Flap (mm) | G4: Web Width (mm) | M4: מ"א נפולת ל - SET UP | P4: Euro
C5: =C20 -> 254 | D5: =C21 -> 254 | E5: =C22 -> 76.2 | F5: =C23 -> 0 | G5: =2*C20+C22*2+C23 -> 660.4 | M5: =500+100 -> 600 | P5: 3.9
A8: Laminate cost | G8: Zipper cost | I8: Adhisive Tape | K8: Pouch production cost | Q8: 0.25
A9: Product | B9: Laminate | C9: Thickness (µ) | D9: Cost for ml | E9: Width (mm) | F9: Total laminate cost | G9: Zipper cost | H9: Total zipper cost | I9: Tape cost | J9: Total tape cost | K9: Set up | L9: Quantity | M9: Set up fall out | N9: Set up cost per pouch | O9: Pouch production cost | P9: Total cost per pouch | Q9: Price for customer | S9: SDR Cost per bag
A10: =+C18 -> Zipper pouch | B10: ='Laminate for Bags - Sales'!A3 -> 608W | C10: =C27 -> 100 | D10: =IF(C25="PR",'Laminate for Bags - Sales'!I26,'Laminate for Bags - Sales'!I33) -> 1.3964766 | E10: =$D5/1000 -> 0.254 | F10: =E10*D10 -> 0.35470507 | G10: =IF(ISNUMBER(SEARCH("zipper",A10))=TRUE,'[3]List of names'!T3,"") -> 0.169 | H10: =IF(ISNUMBER(SEARCH("zipper",A10))=TRUE,G10*E10,"") -> 0.042926 | L10: =C24 -> 100000 | M10: =IF(H10="",M5*(D10),M5*(D10+H10)) -> 863.64159 | N10: =M10/L10 -> 0.0086364159 | O10: =0.41/1.16 -> 0.35344828 | P10: =IF(AND(H10="",J10=""),O10+N10+F10,IF(AND(H10="",J10<>""),O10+N10+J10+F10,IF(AND(H10<>"",J10=""),O10+N10+H10+F10,O10+N10+J10+H10+F10))) -> 0.75971576 | Q10: =$P10/(1-$Q$8) -> 1.0129543 | S10: =O10+SUM('Laminate for Bags - Sales'!Q9:Q11)*D5/1000 -> 0.39253785
E11: =D10*E10 -> 0.35470507
B15: Laminate Pouch
B17: Laminate type | C17: Laminate608W | D17: For Side gusset pouch
B18: Bag Type | C18: Zipper pouch
B19: Food grade | C19: FG
B20: Height of bag | C20: =10*25.4 -> 254 | D20: Width
B21: Width of bag | C21: =10*25.4 -> 254 | D21: Height
B22: Base Gusset/2 | C22: =3*25.4 -> 76.2 | D22: Side gusset*2 | E22: MOQ | F22: =IF(C17="Laminate608W",2000/'Laminate for Bags - Sales'!Q28, IF(C17="Laminate608",750/'Laminate for Bags - Sales'!Q28,500/'Laminate for Bags - Sales'!Q28)) -> 87818.63
B23: Flap | C23: 0 | E23: Total Weight | F23: =C24*'Laminate for Bags - Sales'!Q28 -> 2277.4211
B24: Amount | C24: 100000
B25: Printed | C25: PR
B26: Number of Colurs | C26: 5 to 8
B27: Thickness (µ) | C27: 100
B29: Check amount | C29: =IF(C24>=F22,1,"X") -> 1
B30: Price per bag EXW Italy | C30: =IF(C31*C24>50000,"Higher than 50K",C31) -> Higher than 50K
B31: Price per bag € | C31: =Q10 -> 1.0129543
B32: Total order price | C32: =C30*C29*C24 -> #VALUE!
B34: Cost per bag | C34: =P10 -> 0.75971576
B36: Price per bag $ | C36: =+C31*1.17 -> 1.1851566 | D36: =P10*1.17 -> 0.88886744
B37: Total order price | C37: =+C36*C24 -> 118515.66
C41: MOQ - KG
B42: Laminate106 | C42: 500
B43: Laminate607 | C43: 500
B44: Laminate608 | C44: 750
B45: Laminate608W | C45: 2000
B56: Open Bag | C56: Open Pouch
B57: Open SUP | C57: SUP
B58: Open bag with Flap | C58: Resealable Pouch
B59: SUP with zipper | C59: SUP | D59: If the closure is with Zipper
B60: Gusset bag | C60: Side gusset pouch
B61: Open bag with Zipper | C61: Zipper pouch

Sheet Laminate for Bags  - Sales
E1: Quote in | G1: Units | H1: ='Laminated bags - Sales'!C24 -> 100000
A2: Laminate | B2: Layer | C2: Laminate structure | D2: Width of reel asked | E2: Width Used | G2: FG/NF | H2: Laminate length | I2: PR/ NonPR | J2: No of paints | K2: Lemination Width (mm) | L2: Thickness (µ) | M2: Density | N2: Weight (kg) | O2: Raw material Cost | P2: TRANSPORTATION | Q2: Cost (€) | R2: Cost ($) | T2: Cost Per KG | V2: Film weight per bag | W2: מחיר הדפסה למ"א | X2: מ"א מודפס
A3: =IF('Laminated bags - Sales'!C17="Laminate607",607,IF('Laminated bags - Sales'!C17="Laminate608",608,IF('Laminated bags - Sales'!C17="Laminate418",418,IF('Laminated bags - Sales'!C17="Laminate608W","608W",IF('Laminated bags - Sales'!C17="Laminate106",106,IF('Laminated bags - Sales'!C17="Laminate428",428,IF('Laminated bags - Sales'!C17="Laminate819",819,IF('Laminated bags - Sales'!C17="Laminate823",823,IF('Laminated bags - Sales'!C17="Laminate618",618,"Check"))))))))) -> 608W | B3: =IF(C3<>"","A","") -> A | C3: =IF(A3=W608,"Tipa302WFG",IF(A3=418,"Tipa312Met",IF(A3=428,"Tipa312Met",IF(A3=823,"Tipa312Met","Tipa302FG")))) -> Tipa302FG | D3: ='Laminated bags - Sales'!G5 -> 660.4 | E3: =IF(OR(A3<>"608W",A3<>608),IF((K4-29)/D3>6,D3*6,IF((K4-29)/D3>5,D3*5,IF((K4-29)/D3>4,D3*4,IF((K4-29)/D3>3,D3*3,IF((K4-29)/D3>2,D3*2,D3))))),MAX(750,IF((K4-29)/D3>6,D3*6,IF((K4-29)/D3>5,D3*5,IF((K4-29)/D3>4,D3*4,IF((K4-29)/D3>3,D3*3,IF((K4-29)/D3>2,D3*2,D3))))))) -> 660.4 | G3: ='Laminated bags - Sales'!C19 -> FG | H3: =H1*'Laminated bags - Sales'!C21/1000 -> 25400 | I3: ='Laminated bags - Sales'!C25 -> PR | J3: ='Laminated bags - Sales'!C26 -> 5 to 8 | K3: 790 | L3: =IF(C5<>"",L8-SUM(L4:L5,6),L8-SUM(L4:L5,3)) -> 71 | M3: =VLOOKUP(C3,'[3]List of names'!L:N,3,0) -> 1.25 | N3: =IF(C3="PAPER",42/1000*$K3/1000,M3*1000*(L3/1000000)*($K3/1000)) -> 0.0701125 | O3: =IF(E3>950,'[3]Film -Summary'!Q25*1.25,'[3]Film -Summary'!Q25) -> 6.1893378 | P3: =VLOOKUP(C3,'[3]List of names'!$L$2:$M$10,2,FALSE)+$Q$31 -> 4.45 | Q3: =N3*(O3+P3) -> 0.74595057 | R3: =Q3*USD -> #REF! | T3: =(O3+P3)*N3/$N$8 -> 7.2706648 | V3: =1.25*(L3/1000)*(E3/1000)*'Laminated bags - Sales'!C21/1000 -> 0.014887067 | W3: =Y3/X3 -> 0.0915768 | X3: =IF(A3=608,1/N8,1/N4) -> 38.219287 | Y3: =IF(A3=608,Y11*Y10,IF(J3="1 to 4",Y7,Y8)) -> 3.5 | Z3: הדפסה לק"ג | AA3: כמות שכבות | AB3: מחיר לק"ג
B4: =IF(C4<>"","B","") -> B | C4: =VLOOKUP(A3,'[3]List of names'!$F$2:$G$11,2,0) -> NKR | K4: 790 | L4: =HLOOKUP(C4,'[3]List of names'!B15:E16,2,0) -> 23 | M4: =VLOOKUP(C4,'[3]List of names'!L:N,3,0) -> 1.44 | N4: =IF(C4="PAPER",42/1000*$K4/1000,M4*1000*(L4/1000000)*($K4/1000)) -> 0.0261648 | O4: =VLOOKUP(C4,'[3]Raw material summary'!$I$11:$J$17,2,0) -> 7.95 | P4: =VLOOKUP(C4,'[3]List of names'!$L$2:$M$10,2,FALSE)+$Q$31 -> 4.6 | Q4: =N4*(O4+P4) -> 0.32836824 | R4: =Q4*USD -> #REF! | T4: =(O4+P4)*N4/$N$8 -> 3.2005544 | W4: =Y4/X4 -> 0.15389595 | X4: =1/N8 -> 9.7468452 | Y4: 1.5 | Z4: למינציה לק"ג | AA4: =IF(OR(A3="608W",A3=608,A3=618,A3=418,A3=607),1,2) -> 1 | AB4: 2.5
B5: =IF(C5<>"","C","") -> C | C5: =IF(VLOOKUP(A3,'[3]List of names'!F2:H11,3,FALSE)=0,"",VLOOKUP(A3,'[3]List of names'!F2:H11,3,FALSE)) -> PBAT | K5: 790 | L5: =_xlfn.IFNA(HLOOKUP(C5,'[3]List of names'!B15:E16,2,0),0) -> 0 | M5: =IF(C5="",0,VLOOKUP(C5,'[3]List of names'!L2:N7,3,0)) -> 1.25 | N5: =IF(C5="","",IF(C5="PAPER",50/1000*$K5/1000,M5*1000*(L5/1000000)*($K5/1000))) -> 0 | O5: =VLOOKUP(C5,'[3]Raw material summary'!$I$11:$J$17,2,0) -> 5.5 | P5: =VLOOKUP(C5,'[3]List of names'!$L$2:$M$10,2,FALSE)+$Q$31 -> 4.45 | Q5: =IF(C5="","",N5*(O5+P5)) -> 0 | R5: =IF(C5="","",Q5*USD) -> #REF! | T5: =IF(C5="","",(O5+P5)*N5/$N$8) -> 0 | W5: =Y5/X5 -> 0 | X5: =1/N8 -> 9.7468452 | Y5: =IF('Laminated bags - Sales'!C25="PR",0,0.4)*Y10 -> 0 | Z5: חיתוך לק"ג
C6: ADHISIVE | N6: =IF(A3=608,0,(K3/1000*0.004*IF(B5="C",2,1))) -> 0.00632 | O6: 4.5 | P6: =Q31 -> 4.25 | Q6: =N6*(O6+P6) -> 0.0553 | R6: =Q6*USD -> #REF! | T6: =(O6+P6)*N6/$N$8 -> 0.53900054
C7: HARDENER | Q7: =N7*(O7+P7) -> 0 | R7: =Q7*USD -> #REF! | T7: =(O7+P7)*N7/$N$8 -> 0 | W7: =W4*X4 -> 1.5 | Y7: =IF(L18>1000,2.5,IF(L18>500,3,3.5))*Y10 -> 3 | Z7: מחיר הדפסה 1-4
A8: =A3 -> 608W | C8: =COUNTA(C3:C5) -> 3 | E8: =COUNTIF(C3:C5,"") -> 0 | G8: Lemingth length width used | H8: =H3/(ROUNDDOWN(K3/D3,0)) -> 25400 | K8: =SUMPRODUCT(K3:K5,L3:L5)/(L8-IF(AA4=2,6,3)) -> 765.56701 | L8: ='Laminated bags - Sales'!C27 -> 100 | N8: =SUM(N3:N7) -> 0.1025973 | P8: Total materials cost | Q8: =SUM(Q3:Q7) -> 1.1296188 | R8: =Q8*USD -> #REF! | T8: =SUM(T3:T7) -> 11.01022 | Y8: =IF(L18>1000,3,IF(L18>500,3.5,4))*Y10 -> 3.5 | Z8: מחיר הדפסה 5-8
E9: =IF(OR((680-D3*1)<120,AND((680-D3*2)<120,(680-D3*2)>0),AND((680-D3*3)<120,(680-D3*3)>0)),680,0) -> 680 | P9: Lamination | Q9: =+W4 -> 0.15389595 | R9: =Q9*USD -> #REF! | T9: =Y4 -> 1.5
B10: 4 | C10: EURO | E10: =IF(680-D3*1<120,680,0) -> 680 | M10: =+N3/N8 -> 0.68337568 | P10: Slitting | R10: =Q10*USD -> #REF! | T10: =Y5 -> 0 | Y10: =IF(L19<100,2,IF(L19<200,1.75,IF(L19<250,1.5,1))) -> 1 | Z10: מקדם מתחת ל300 ק"ג
B11: 3.6 | C11: $ | M11: =+M10*L19 -> 1780.8575 | P11: Printing | R11: =Q11*USD -> #REF! | T11: =Y3*N4/N8 -> 0.89258489 | Y11: 2.5 | Z11: מחיר הדפסה DP | AA11: DP Price
N12: =100*N8 -> 10.25973 | P12: Total | Q12: =SUM(Q8:Q11) -> 1.2835148 | R12: =SUM(R8:R11) -> #REF! | T12: =SUM(T8:T11) -> 13.402805 | Y12: 1.275 | Z12: למינציה DP
A13: Impression details | H13: Gross profit | I13: COST | K13: Cost per ml | L13: =$Q13/ROUNDDOWN((K8-30)/D3,0) -> 1.3964766 | M13: =L13*USD -> #REF! | P13: Total + 10% | Q13: =Q8*(1+Q17)+SUM(Q9:Q11) -> 1.3964766 | R13: =R12*1.1 -> #REF! | T13: =T12*1.1 -> 14.743085
A14: Width | B14: 300 | C14: This is the height of the bag | H14: =IF(C32="NF",30%,25%) -> 0.25 | K14: Cost per kg | L14: =$L13*$L22 -> 13.611242 | M14: =L14*USD -> #REF! | T14: =T13*(K3/E3) -> 17.636337
A15: Length | B15: 250 | C15: This is the width of the bag | I15: SELL | K15: Price per ml | L15: =$L13/(1-$H14) -> 1.8619689 | M15: =L15*USD -> #REF!
K16: Price per kg | L16: =L14/(1-H14) -> 18.148322 | M16: =L16*USD -> #REF! | N16: =L16/L15 -> 9.7468452 | AB16: "680,900,1100"
A17: Reel details | L17: =(L16-L14)/L16 -> 0.25 | P17: Waste assumption Printed | Q17: 0.1
A18: Width | B18: =C35 -> 0 | C18: This is the height of the bag*2 | K18: Printed KG | L18: =L19*L4/L8 -> 599.37343 | P18: Waste assumption Non Printed | Q18: 0.1
A19: Length | B19: =C37 -> 0 | C19: to check if there is any length limitation - Must be filled!!! | K19: Total KG | L19: =N8/ROUNDDOWN((K3-29)/D3,0)*H3 -> 2605.9714 | M19: =+L19*N3/N8 -> 1780.8575
A21: Waste assumptions | C21: Number of works | D21: Waste per work | K21: Ml & Lem used width of reel in kg | L21: =1/N8 -> 9.7468452
A22: 1st laminate | B22: 1000 | C22: 4 | D22: =B22/C22 -> 250 | K22: Ml & Lem Asked width of reel in kg | L22: =1/N8*ROUNDDOWN(E3/D3,0) -> 9.7468452 | P22: Number of impression | Q22: =IF(G1="impression",ROUNDDOWN(K3/D3,0)*1000/B15,"NA") -> NA
A23: 2nd laminate | B23: 1000 | C23: 4 | D23: =B23/C23 -> 250 | H23: Printed Waste Assumption | P23: Cost per impressiom | Q23: =IF(G1="Impression",Q13/Q22,"NA") -> NA
A24: Prining | B24: 1000 | C24: 1 | D24: =B24/C24 -> 1000 | I24: Eur | K24: USD | P24: Price Per impression | Q24: =Q23*1.25 -> #VALUE!
A25: Reel change | B25: 50 | C25: evrey 3K Meter | I25: Cost | J25: Sale price | K25: Cost | L25: Sale price
A26: Converting | B26: 500 | C26: Set up | H26: ML | I26: =L13 -> 1.3964766 | J26: =L15 -> 1.8619689 | K26: =I26*USD -> #REF! | L26: =J26*USD -> #REF!
A27: Converting process | B27: 0.1 | C27: Based on the run length | D27: =5%+3% -> 0.08 | E27: =7%+3% -> 0.1 | G27: =6%+3% -> 0.09 | H27: KG | I27: =L14 -> 13.611242 | J27: =L16 -> 18.148322 | K27: =I27*USD -> #REF! | L27: =J27*USD -> #REF!
P28: Weight of bag | Q28: =N8*D3/E3*((E3+30)/K3)*'Laminated bags - Sales'!C21/1000 -> 0.022774211
H29: Non Printed waste Assumption
I31: Eur | K31: USD | P31: Shipment addition | Q31: =IF(L19<1000,2,IF(L19<3000,2,1.5))+15*0.15 -> 4.25
G32: =H14 -> 0.25 | I32: Cost | J32: Sale price | K32: Cost | L32: Sale price
H33: ML | I33: =(Q8*(1+Q18)+SUM(Q9:Q11))/ROUNDDOWN((K3-30)/D3,0) -> 1.3964766 | J33: =I33*(1+$G$32) -> 1.7455958 | K33: =I33*USD -> #REF! | L33: =J33*USD -> #REF!
H34: KG | I34: =$I33*$L22 -> 13.611242 | J34: =I34*(1+$G$32) -> 17.014052 | K34: =I34*USD -> #REF! | L34: =J34*USD -> #REF!

Sheet Laminate for reels  - Sales (2)
B1: Laminate608 W | C1: Tipa302WFG | E1: Quote in | G1: =C38 -> Ml | H1: =C39 -> 5000
A2: Laminate | B2: Layer | C2: Laminate structure | D2: Width of reel asked | E2: Width Used | F2: length of impression | G2: FG/NF | H2: Laminate length (m) width asked | I2: PR/ NonPR | J2: No of paints | K2: Lemination Width (mm) | L2: Thickness (µ) | M2: Density | N2: Weight (kg) | O2: Raw material Cost | P2: TRANSPORTATION | Q2: Cost (€) | R2: Cost ($) | T2: Cost Per KG | W2: מחיר הדפסה למ"א | X2: מ"א מודפס | AB2: SDR Price
A3: =IF(C36="Laminate607",607,IF(C36="Laminate608",608,IF(C36="Laminate418",418,IF(C36="Laminate608W","608W",IF(C36="Laminate106",106,IF(C36="Laminate428",428,IF(C36="Laminate819",819,IF(C36="Laminate823",823,IF(C36="Laminate618",618,"Check"))))))))) -> 819 | B3: =IF(C3<>"","A","") -> A | C3: =IF(C36="Laminate608W","Tipa302WFG",IF(C36="Laminate418","Tipa312Met",IF(C36="Laminate428","Tipa312Met",IF(C36="Laminate823","Tipa312Met","Tipa302FG")))) -> Tipa302FG | D3: =IF(G1="Impression",B14,B18) -> 760 | E3: =IF(OR(A3<>"608W",A3<>608),IF((K4-29)/D3>6,D3*6,IF((K4-29)/D3>5,D3*5,IF((K4-29)/D3>4,D3*4,IF((K4-29)/D3>3,D3*3,IF((K4-29)/D3>2,D3*2,D3))))),MAX(750,IF((K4-29)/D3>6,D3*6,IF((K4-29)/D3>5,D3*5,IF((K4-29)/D3>4,D3*4,IF((K4-29)/D3>3,D3*3,IF((K4-29)/D3>2,D3*2,D3))))))) -> 760 | F3: =IF(G1="Impression",B15,"") | G3: =C37 -> FG | H3: =IF(G1="Ml",H1,IF(G1="KG",(1/N8*ROUNDDOWN((K8-30)/D3,0))*H1,H1*F3/1000)) -> 5000 | I3: =C43 -> Non PR | J3: =C44 -> 0 | K3: =IF(OR(A3="608W",A3=608),E3+40*2,E3+50) -> 810 | L3: =IF($AA$4=1,L8-SUM(L4:L5,3),L8-SUM(L4:L5,6)) -> 4 | M3: =VLOOKUP(C3,'[1]List of names'!L:N,3,0) -> 1.25 | N3: =IF(C3="PAPER",42/1000*$K3/1000,M3*1000*(L3/1000000)*($K3/1000)) -> 0.00405 | O3: =IF(E3<950,'[1]Film -Summary'!Q35,'[1]Film -Summary'!Q35*1.25) -> #N/A | P3: =VLOOKUP(C3,'[1]List of names'!$L$2:$M$10,2,FALSE)+Q32 -> 4.95 | Q3: =N3*(O3+P3) -> #N/A | R3: =Q3*USD -> #N/A | T3: =(O3+P3)*N3/$N$8 -> #N/A | W3: =Y3/X3 -> 0.1073088 | X3: =IF(OR(A3="608W",A3=608),1/N8,1/N4) -> 37.275601 | Y3: =IF(OR(A3="608W",A3=608),Y11*Y10,IF(J3="1 to 4",Y7,Y8)) -> 4 | Z3: הדפסה לק"ג | AA3: כמות שכבות | AB3: מחיר לק"ג
B4: =IF(C4<>"","B","") -> B | C4: =VLOOKUP(A3,'[1]List of names'!$F$2:$G$11,2,0) -> NKR | K4: =IF(D3<300,D3*4+50,IF(D3<400,D3*3+50,IF(D3<600,D3*2+50,D3+50))) -> 810 | L4: {=IF(C4="NKR",23,IF(C4="NKME",20,IF(C4="Tipa312Met",25,NA)))} -> 23 | M4: =VLOOKUP(C4,'[1]List of names'!L:N,3,0) -> 1.44 | N4: =IF(C4="PAPER",42/1000*$K4/1000,M4*1000*(L4/1000000)*($K4/1000)) -> 0.0268272 | O4: =VLOOKUP(C4,'[1]Raw material summary'!$I$10:$K$16,IF($K$3<900,2,3),0) -> 7.95 | P4: =VLOOKUP(C4,'[1]List of names'!$L$2:$M$7,2,FALSE)+Q32 -> 5.1 | Q4: =N4*(O4+P4) -> 0.35009496 | R4: =Q4*USD -> 0.38510446 | T4: =(O4+P4)*N4/$N$8 -> 5.0777256 | W4: =Y4/X4 -> 0.28957824 | X4: =1/N8 -> 14.503852 | Y4: =IF(OR(A3=608,A3="608W"),AA4*Y12*Y10,Y12*AA4*Y10) -> 4.2 | Z4: למינציה לק"ג | AA4: =IF(OR(A3="608W",A3=608,A3=618,A3=418),1,2) -> 2 | AB4: 2.5
B5: =IF(C5<>"","C","") -> C | C5: =IF(VLOOKUP(A3,'[1]List of names'!F2:H11,3,FALSE)=0,"",VLOOKUP(A3,'[1]List of names'!F2:H11,3,FALSE)) -> Paper | K5: =IF(D3<300,D3*4+50,IF(D3<400,D3*3+50,IF(D3<600,D3*2+50,D3+50))) -> 810 | L5: =IF(C5="","",IF(C5="NKR",23,IF(C5="NKME",20,IF(C5="Paper",67,IF(C5="PBAT",INDEX('[1]List of names'!$F$34:$F$40,MATCH($L$8,'[1]List of names'!$D$34:$D$40,0)),IF(C5="",0,"NA")))))) -> 67 | M5: =IF(C5="",0,VLOOKUP(C5,'[1]List of names'!L2:N7,3,0)) -> 1 | N5: =IF(C5="","",IF(C5="PAPER",42/1000*$K5/1000,M5*1000*(L5/1000000)*($K5/1000))) -> 0.03402 | O5: =IF(C5="",0,VLOOKUP(C5,'[1]Raw material summary'!$I$10:$K$16,IF($K$3<900,2,3),0)) -> 1.31 | P5: =IF(C5="",0,VLOOKUP(C5,'[1]List of names'!$L$2:$M$7,2,FALSE)) -> 0.3 | Q5: =IF(C5="","",N5*(O5+P5)) -> 0.0547722 | R5: =IF(C5="","",Q5*USD) -> 0.06024942 | T5: =IF(C5="","",(O5+P5)*N5/$N$8) -> 0.79440789 | W5: =Y5/X5 -> 0.0517104 | X5: =1/N8 -> 14.503852 | Y5: 0.75 | Z5: חיתוך לק"ג
C6: ADHISIVE | N6: =IF(A3=608,0,(K3/1000*0.0025*IF(B5="C",2,1))) -> 0.00405 | O6: 4.5 | P6: =0.2+Q32 -> 4.95 | Q6: =N6*(O6+P6) -> 0.0382725 | R6: =Q6*USD -> 0.04209975 | T6: =(O6+P6)*N6/$N$8 -> 0.55509868
C7: HARDENER | Q7: =N7*(O7+P7) -> 0 | R7: =Q7*USD -> 0 | T7: =(O7+P7)*N7/$N$8 -> 0 | Y7: 3.5 | Z7: מחיר הדפסה 1-4
A8: =A3 -> 819 | C8: =COUNTA(C3:C5) -> 3 | E8: =COUNTIF(C3:C5,"") -> 0 | G8: Lemingth length width used | H8: =H3/(ROUNDDOWN(K3/D3,0)) -> 5000 | K8: =SUMPRODUCT(K3:K5,L3:L5)/IF(AA4=1,($L$8-3),($L$8-6)) -> 810 | L8: =C45 -> 100 | N8: =SUM(N3:N7) -> 0.0689472 | P8: Total materials cost | Q8: =SUM(Q3:Q7) -> #N/A | R8: =Q8*USD -> #N/A | T8: =SUM(T3:T7) -> #N/A | Y8: 4 | Z8: מחיר הדפסה 5-8
E9: =IF(OR((680-D3*1)<120,AND((680-D3*2)<120,(680-D3*2)>0),AND((680-D3*3)<120,(680-D3*3)>0)),680,0) -> 680 | L9: =K3*L3+K4*L4 -> 21870 | P9: Lamination | Q9: =0.06 -> 0.06 | R9: =Q9*USD -> 0.066 | T9: =+Y4 -> 4.2
B10: 4 | C10: EURO | E10: =IF(680-D3*1<120,680,0) -> 680 | F10: =IF(C5="NKR",19,IF(C5="NKME",20,IF(C5="",0,"NA"))) -> NA | K10: =IF(OR(A3=607,A3=608),'[1]SDR price list'!Y5,'[1]SDR price list'!Y21) -> 910 | P10: Slitting | Q10: =W5 -> 0.0517104 | R10: =Q10*USD -> 0.05688144 | T10: =Y5 -> 0.75 | Y10: =IF(L19<300,2,IF(L19<750,1.75,IF(L19<1500,1.5,1))) -> 1.75 | Z10: מקדם מתחת ל300 ק"ג
B11: 3.6 | C11: $ | P11: Printing | Q11: =87.8/1000 -> 0.0878 | R11: =Q11*USD -> 0.09658 | T11: =IF(I3="PR",Y3*N4/N8,0) -> 0 | Y11: 2.5 | Z11: מחיר הדפסה DP | AA11: DP Price
D12: =IF(C36=OR("Laminate418","Laminate428","Laminate823"),"Tipa312Met") -> #VALUE! | N12: =100*N8 -> 6.89472 | P12: Total | Q12: =SUM(Q8:Q11) -> #N/A | R12: =SUM(R8:R11) -> #N/A | T12: =SUM(T8:T11) -> #N/A | Y12: 1.2 | Z12: למינציה DP
A13: Impression details | H13: Gross profit | I13: COST | K13: Cost per ml | L13: =$Q13/ROUNDDOWN((K8-30)/D3,0) -> #N/A | M13: =L13*$B$10/$B$11 -> #N/A | P13: Total + 10% | Q13: =Q8*(1+Q17)+SUM(Q9:Q11) -> #N/A | R13: =R12*(1.1) -> #N/A | T13: =T8*(1+Q17)+SUM(T9:T11) -> #N/A
A14: Width | B14: =C40 -> 760 | C14: This is the height of the bag | H14: 0.2 | K14: Cost per kg | L14: =$L13*$L22*K8/E3 -> #N/A | M14: =L14*$B$10/$B$11 -> #N/A | T14: =T13*(K8/E3) -> #N/A
A15: Length | B15: 110 | C15: This is the width of the bag | I15: SELL | K15: Price per ml | L15: =$L13/(1-$H14) -> #N/A | M15: =L15*$B$10/$B$11 -> #N/A | X15: Total Weight | Y15: Total Cost
K16: Price per kg | L16: =L14/(1-H14) -> #N/A | M16: =L16*$B$10/$B$11 -> #N/A | T16: =T8/T12 -> #N/A | X16: =$H$8*N3 -> 20.25 | Y16: =X16*(O3+P3) -> #N/A | AB16: "680,900,1100"
A17: Reel details | P17: Waste assumption Printed | Q17: =IF(A3=607,(D24*L4/L8+D23+D27*H8)/H8,(D24*L4/L8+D23+D22*0.8+D27*H8)/H8) -> 0.186 | X17: =$H$8*N4 -> 134.136 | Y17: =X17*(O4+P4) -> 1750.4748
A18: Width | B18: =C40 -> 760 | C18: This is the height of the bag*2 | K18: Printed KG | L18: =L19*L4/L8 -> 79.28928 | P18: Waste assumption Non Printed | Q18: =IF(C5="",(D23+D27*H8)/H8,(D23+D22*0.8+D27*H8)/H8) -> 0.14 | X18: =$H$8*N5 -> 170.1 | Y18: =X18*(O5+P5) -> 273.861
A19: Length | B19: =C42 -> 0 | C19: to check if there is any length limitation - Must be filled!!! | K19: Total KG | L19: =N8/ROUNDDOWN((K8-29)/D3,0)*H3 -> 344.736 | M19: =+L19*N3/N8 -> 20.25 | X19: =$H$8*N6 -> 20.25 | Y19: =X19*(O6+P6) -> 191.3625
K20: Net KG | L20: =N8/ROUNDDOWN(K8/D3,0)*(E3/K8)*H1 -> 323.456 | X20: =$H$8*N7 -> 0 | Y20: =X20*O7 -> 0
A21: Waste assumptions | C21: Number of works | D21: Waste per work | K21: Ml & Lem used width of reel in kg | L21: =1/N8 -> 14.503852 | X21: =SUM(X16:X20) -> 344.736 | Y21: =SUM(Y16:Y20) -> #N/A
A22: 1st laminate | B22: 1000 | C22: 4 | D22: =B22/C22 -> 250 | K22: Ml & Lem Asked width of reel in kg | L22: =1/N8*ROUNDDOWN(K8/D3,0) -> 14.503852 | P22: Number of impression | Q22: =ROUNDDOWN(K3/D3,0)*1000/B15 -> 9.0909091 | X22: Waste of width | Y22: =+(K3/E3*T13-T13)*L19 -> #N/A
A23: 2nd laminate | B23: 1000 | C23: 4 | D23: =B23/C23 -> 250 | H23: Printed Waste Assumption | P23: Cost per impressiom | Q23: =Q13/Q22 -> #N/A | X23: SDR | Y23: =X21*SUM(T9:T11) -> 1706.4432
A24: Prining | B24: 1000 | C24: 1 | D24: =B24/C24 -> 1000 | I24: Eur | K24: USD | P24: Price Per impression | Q24: =Q23*1.25 -> #N/A | R24: =Q24*1.16 -> #N/A | X24: Waste | Y24: =IF(C43="PR",Y21*Q17,Y21*Q18) -> #N/A
A25: Reel change | B25: 50 | C25: evrey 3K Meter | I25: Cost | J25: Sale price | K25: Cost | L25: Sale price | X25: Total Cost | Y25: =SUM(Y21:Y24) -> #N/A
A26: Converting | B26: 500 | C26: Set up | H26: ML | I26: =L13 -> #N/A | J26: =L15 -> #N/A | K26: =I26*$O$29 -> #N/A | L26: =J26*$O$29 -> #N/A | P26: Meter MOQ | Q26: =IF(C36="Laminate608",750/N8*(E3/D3),500/N8*(E3/D3)) -> 7251.9261 | X26: Total Price | Y26: =C50 -> #N/A
A27: Converting process | B27: 0.1 | C27: Based on the run length | D27: 0.05 | H27: KG | I27: =L14 -> #N/A | J27: =L16 -> #N/A | K27: =I27*$O$29 -> #N/A | L27: =J27*$O$29 -> #N/A | X27: Profit | Y27: =Y26-Y25 -> #N/A
O28: Euro to dollar rate | Y28: =Y27/Y26 -> #N/A
H29: Non Printed waste Assumption | O29: 1.17
I31: Eur | K31: USD
B32: Laminat Reel 607, 106 | C32: MOQ = 500KG | G32: =H14 -> 0.2 | I32: Cost | J32: Sale price | K32: Cost | L32: Sale price | P32: Shipment addition | Q32: =IF(L20<1000,2.5,IF(L20<3000,2,1.5))+15*0.15 -> 4.75
B33: Laminat Reel 608 | C33: MOQ = 750KG | H33: ML | I33: =(Q8*(1+Q18)+SUM(Q9:Q11))/ROUNDDOWN((K3-30)/D3,0) -> #N/A | J33: =I33/(1-$G$32) -> #N/A | K33: =I33*$O$29 -> #N/A | L33: =J33*$O$29 -> #N/A
B34: Laminat Reel 608W | C34: MOQ = 2000KG | H34: KG | I34: =$I33*$L22*K8/E3 -> #N/A | J34: =I34/(1-$G$32) -> #N/A | K34: =I34*$O$29 -> #N/A | L34: =J34*$O$29 -> #N/A
B36: Laminate type | C36: Laminate819 | I36: =I33*800 -> #N/A
B37: Food grade | C37: FG
B38: Quote by | C38: Ml | D38: Meter MOQ | E38: =IF(C36="Laminate608w",2000/N8*(E3/D3),IF(C36="Laminate608",750/N8*(E3/D3),500/N8*(E3/D3))) -> 7251.9261
B39: Amount | C39: 5000 | D39: KG MOQ | E39: =IF(C36="Laminate608W",2000,IF(C36="Laminate608",750,500)) -> 500 | I39: QTY | J39: Cost | K39: Price
B40: Width of reel | C40: 760 | D40: Total KG | E40: =+L19 -> 344.736 | H40: Z10771.00023-000 | I40: 5000 | J40: 11.485134 | K40: 14.356417 | L40: =K40*I40 -> 71782.087
B41: Length limitation <50Kg (Y/N) | C41: Y | D41: (*) Min is 500 Meter | H41: Z10771.00023-000 | I41: =I40*2 -> 10000 | J41: =$I$34 -> #N/A | K41: =$J$34 -> #N/A | L41: =K41*I41 -> #N/A | M41: =K41/K40-1 -> #N/A
B42: Length Limit | D42: (*) Up to 1,150 width | H42: Z10771.00023-000 | I42: =I40*3 -> 15000 | J42: =$I$34 -> #N/A | K42: =$J$34 -> #N/A | L42: =K42*I42 -> #N/A | M42: =K42/K41-1 -> #N/A
B43: Printed | C43: Non PR
B44: Number of Colurs | C44: 0 | I44: Imp | J44: Meters | K44: Kg | L44: Cost | M44: Price | N44: Deal amount
B45: Thickness (µ) | C45: 100 | I45: 500000 | J45: =I45/(1000/$B$15) -> 55000 | K45: =$N$8/ROUNDDOWN(($K$3-29)/$D$3,0)*$H$3 -> 344.736 | M45: 0.0437 | N45: =M45*I45 -> 21850
I46: 1000000 | J46: =I46/(1000/$B$15) -> 110000 | K46: =$N$8/ROUNDDOWN(($K$3-29)/$D$3,0)*$H$3 -> 344.736 | M46: 0.0396 | N46: =M46*I46 -> 39600
B47: Check amount | C47: =IF(AND(C38="KG",J34*H1>150000),"X",IF(AND(C38="Ml",J33*H1>150000),"X",1)) -> #N/A | I47: 2000000 | J47: =I47/(1000/$B$15) -> 220000 | K47: =$N$8/ROUNDDOWN(($K$3-29)/$D$3,0)*$H$3 -> 344.736 | M47: 0.0375 | N47: =M47*I47 -> 75000
B48: Price per unit EXW Italy | C48: =IF(C49*C39>150000,"Higher than 40K",C49) -> #N/A | H48: MOQ | I48: 3000000 | J48: =I48/(1000/$B$15) -> 330000 | K48: 532.025 | L48: =$Q$23 -> #N/A | M48: 0.037 | N48: =M48*I48 -> 111000
B49: Price per unit | C49: =IF(AND(C43="PR",C38="Ml"),J26,IF(AND(C43="PR",C38="KG"),J27,IF(AND(C43="Non PR",C38="Ml"),J33,J34))) -> #N/A | I49: 4000000 | J49: =I49/(1000/$B$15) -> 440000 | K49: =$N$8/ROUNDDOWN(($K$3-29)/$D$3,0)*$H$3 -> 344.736 | L49: =$Q$23 -> #N/A | M49: 0.0365 | N49: =M49*I49 -> 146000 | O49: =N49/$L$20 -> 451.37515
B50: Total order price | C50: =C48*C47*C39 -> #N/A
N51: =M51*I51 -> 0
B52: Lam Cost | C52: =IF(AND(C43="PR",C38="Ml"),I26,IF(AND(C43="PR",C38="KG"),I27,IF(AND(C43="Non PR",C38="Ml"),I33,I34)))*C47 -> #N/A | N52: =M52*I52 -> 0
K53: Per day | L53: per month | N53: per hour | O53: Set up time
B54: Price per unit $ | C54: =+C49*USD -> #N/A | I54: Laminate production | K54: =120*60*12 -> 86400 | L54: =K54*25 -> 2160000 | M54: Meters | N54: =350/(120*60) -> 0.048611111 | O54: 3 hours | P54: Flexo
B55: Total order price | C55: =+C54*C39 -> #N/A | I55: Pouch production | K55: =200*60*12 -> 144000 | L55: =K55*25 -> 3600000 | M55: Minute | O55: 2 hours
I56: Printing per minute | K56: =300*60*12 -> 216000 | L56: =K56*25 -> 5400000 | M56: Meters | N56: =700/(120*60) -> 0.097222222 | O56: 1.5 hours
C57: EXW Italy or Poland
C59: 1000, 3000, 5000 | I59: סוג תהליך | J59: ארה"ב (USD) | K59: אירופה (EUR) | L59: מרכיבי עלות מרכזיים
C60: 1500ת 3000ת 5000 | I60: הדפסה דיגיטלית (Indigo 25K) | J60: $450 - $600 | K60: €400 - €550 | L60: פחת גבוה ($1.5M+ מכונה), חוזי שירות יקרים, מפעיל מומחה.
B61: 608 | C61: 14.7 | I61: הדפסת פלקסו (Wide Web) | J61: $650 - $950 | K61: €600 - €850 | L61: השקעה הונית אדירה, 2 מפעילים, צריכת אנרגיה גבוהה לייבוש.
I62: למינציה / ורניש | J62: $280 - $420 | K62: €250 - €380 | L62: עלויות דבק/לקה, אנרגיה (חימום), פחת מכונה בינוני.
I63: קונברטינג (Totani) | J63: $200 - $320 | K63: €180 - €290 | L63: עבודה אינטנסיבית (בדיקות איכות), פחת מכונה נמוך יותר.

Sheet Step by Step
B2: 📋 FILM PRICING LIST - STEP BY STEP GUIDE
B3: How to use the Film Pricing calculator
B5: 🔄 PRICING WORKFLOW
B7: STEP 1 | C7: → | D7: STEP 2 | E7: → | F7: STEP 3 | G7: → | H7: STEP 4 | I7: → | J7: STEP 5
B8: 📝 INPUT | D8: ⚙️ SPECS | F8: 💰 COSTS | H8: 📦 SHIP | J8: 💵 PRICE
B11: 📝 DETAILED STEPS
B13: Step | C13: Action | D13: Column | E13: Example | F13: Notes
B14: 1️⃣ | C14: Select Film Type | D14: A | E14: TIPA 302FG | F14: Dropdown list
B15: 2️⃣ | C15: Enter Width | D15: B | E15: 406 mm | F15: Width in mm
B16: 3️⃣ | C16: Enter Thickness | D16: C | E16: 20 µ | F16: Dropdown list
B17: 4️⃣ | C17: Enter Weight | D17: E | E17: 500 Kg | F17: Order qty (Kg)
B18: 5️⃣ | C18: Weight Override | D18: F | E18: 500 Kg | F18: Optional
B19: 6️⃣ | C19: Shipping Dest. | D19: S | E19: EU/USA | F19: Dropdown list
B20: 7️⃣ | C20: Review Price | D20: W | E20: Auto | F20: Final price/Kg
B21: 8️⃣ | C21: Compare Margins | D21: X+ | E21: 25%, 30% | F21: Multiple options
B24: ⚡ AUTO-CALCULATIONS
B26: Calculation | C26: Formula Logic
B27: Length (Mr) | C27: Weight ÷ (Width × Thickness × Density)
B28: Production Cost | C28: Hourly Rate × Production Time
B29: Total Cost | C29: RM + Production + Depreciation + Waste + Ship
B30: Sell Price | C30: Total Cost × (1 + Margin %)
B33: 💡 QUICK TIPS
B35: ✓ Use dropdowns to avoid typos
B36: ✓ Higher weight = lower cost/Kg (economies of scale)
B37: ✓ Compare margin columns for pricing options
B38: ✓ Density auto-fills based on Film Type

Sheet BOM
A1: Film | B1: Ext | C1: Material | D1: Grade | E1: Serial Number | F1: Resin | G1: Thickness (µ) | H1: QTY | I1: Price (€/kg) | J1: Price Calculated(€) Thickness & QTY related | L1: Film | M1: Grade | N1: Serial Number | O1: Price Calculated(€) Thickness & QTY related | Q1: Film | R1: Price (€/kg) | S1: Price ($/kg) | U1: Film | V1: Material | W1: Grade | X1: Serial Number | Y1: Resin | Z1: Weighted QTY % | AA1: Film Total Check
A2: TIPA 302FG | B2: Ext. A (Out - Chillroll) | C2: PBSA | D2: =IF(C2="","",IFERROR(_xlfn.XLOOKUP(C2,HELPER!$A$2:$A$81,HELPER!$B$2:$B$81,""),D2)) -> FD92PM | E2: =IFERROR(_xlfn.XLOOKUP(D2,HELPER!$B:$B,HELPER!$C:$C,""),"") -> RMPM2 | F2: =IFERROR(_xlfn.XLOOKUP(D2,HELPER!$B:$B,HELPER!$D:$D,""),"") -> Resin 9C | G2: 8 | H2: 0.826 | I2: =IF(AND(H2<>"",IFERROR(_xlfn.XLOOKUP(D2,HELPER!$B:$B,HELPER!$E:$E,""),"")=""),"Missing price",IFERROR(_xlfn.XLOOKUP(D2,HELPER!$B:$B,HELPER!$E:$E,"")," ")) -> 6.75 | J2: =IFERROR(H2*(IF(G2=8,I2*HELPER!$G$2,BOM!I2*HELPER!$G$3))," ") -> 1.1151 | L2: {=IFERROR(_xlfn.LET(_xlpm.films,Table4[Film],_xlpm.grades,Table4[Grade],_xlpm.pairs,_xlfn._xlws.FILTER(_xlfn.HSTACK(_xlpm.films,_xlpm.grades),(_xlpm.films<>"")*(TRIM(_xlpm.grades)<>"")),_xlpm.uniquePairs,_xlfn.UNIQUE(_xlpm.pairs),_xlpm.sortedPairs,_xlfn._xlws.SORT(_xlpm.uniquePairs,1,1),INDEX(_xlpm.sortedPairs,ROWS($L$2:L2),1)),"")} -> PL202.1 | M2: {=IFERROR(_xlfn.LET(_xlpm.films,Table4[Film],_xlpm.grades,Table4[Grade],_xlpm.pairs,_xlfn._xlws.FILTER(_xlfn.HSTACK(_xlpm.films,_xlpm.grades),(_xlpm.films<>"")*(TRIM(_xlpm.grades)<>"")),_xlpm.uniquePairs,_xlfn.UNIQUE(_xlpm.pairs),_xlpm.sortedPairs,_xlfn._xlws.SORT(_xlpm.uniquePairs,1,1),INDEX(_xlpm.sortedPairs,ROWS($M$2:M2),2)),"")} -> FD92PM | N2: {=IF(OR(Table2[[#This Row],[Film]]="",Table2[[#This Row],[Grade]]=""),"",IFERROR(INDEX(Table4[Serial Number],MATCH(1,(Table4[Film]=Table2[[#This Row],[Film]])*(Table4[Grade]=Table2[[#This Row],[Grade]]),0)),""))} -> RMPM2 | O2: =IF(OR(Table2[[#This Row],[Film]]="",Table2[[#This Row],[Grade]]=""),"",SUMIFS(Table4[Price Calculated(€) Thickness & QTY related],Table4[Film],Table2[[#This Row],[Film]],Table4[Grade],Table2[[#This Row],[Grade]])) -> 3.25215 | Q2: {=IFERROR(INDEX(Table2[Film],MATCH(0,COUNTIF($Q$1:Q1,Table2[Film])+IF(Table2[Film]="",1,0),0)),"")} -> PL202.1 | R2: =SUMIF(Table2[Film],"TIPA 312 MFG",Table2[Price Calculated(€) Thickness & QTY related])+_xlfn.XLOOKUP("MET LUX ",HELPER!$A:$A,HELPER!$E:$E,0) -> 5.380588 | S2: =IFERROR(R2*HELPER!$AK$2," ") -> 6.2414821 | U2: PL202.1 | V2: PVOH | W2: BVE8049P | X2: BVE8049P | Y2: BVE8049P | Z2: {=SUMPRODUCT((BOM!$A$2:$A$391=U2)*(BOM!$F$2:$F$391=Y2)*BOM!$H$2:$H$391*BOM!$G$2:$G$391)/SUMPRODUCT((BOM!$A$2:$A$391=U2)*BOM!$H$2:$H$391*BOM!$G$2:$G$391)} -> 0.254 | AA2: =SUMIF(tblResinWeightedQty12[Film],tblResinWeightedQty12[[#This Row],[Film]],tblResinWeightedQty12[Weighted QTY %]) -> 1
A3: TIPA 302FG | B3: Ext. A (Out - Chillroll) | C3: PLA | D3: =IF(C3="","",IFERROR(_xlfn.XLOOKUP(C3,HELPER!$A$2:$A$81,HELPER!$B$2:$B$81,""),D3)) -> LX175 | E3: =IFERROR(_xlfn.XLOOKUP(D3,HELPER!$B:$B,HELPER!$C:$C,""),"") -> RMLX175 | F3: =IFERROR(_xlfn.XLOOKUP(D3,HELPER!$B:$B,HELPER!$D:$D,""),"") -> Resin 1A | G3: 8 | H3: 0.144 | I3: =IF(AND(H3<>"",IFERROR(_xlfn.XLOOKUP(D3,HELPER!$B:$B,HELPER!$E:$E,""),"")=""),"Missing price",IFERROR(_xlfn.XLOOKUP(D3,HELPER!$B:$B,HELPER!$E:$E,"")," ")) -> 3.17 | J3: =IFERROR(H3*(IF(G3=8,I3*HELPER!$G$2,BOM!I3*HELPER!$G$3))," ") -> 0.091296 | L3: {=IFERROR(_xlfn.LET(_xlpm.films,Table4[Film],_xlpm.grades,Table4[Grade],_xlpm.pairs,_xlfn._xlws.FILTER(_xlfn.HSTACK(_xlpm.films,_xlpm.grades),(_xlpm.films<>"")*(TRIM(_xlpm.grades)<>"")),_xlpm.uniquePairs,_xlfn.UNIQUE(_xlpm.pairs),_xlpm.sortedPairs,_xlfn._xlws.SORT(_xlpm.uniquePairs,1,1),INDEX(_xlpm.sortedPairs,ROWS($L$2:L3),1)),"")} -> PL202.1 | M3: {=IFERROR(_xlfn.LET(_xlpm.films,Table4[Film],_xlpm.grades,Table4[Grade],_xlpm.pairs,_xlfn._xlws.FILTER(_xlfn.HSTACK(_xlpm.films,_xlpm.grades),(_xlpm.films<>"")*(TRIM(_xlpm.grades)<>"")),_xlpm.uniquePairs,_xlfn.UNIQUE(_xlpm.pairs),_xlpm.sortedPairs,_xlfn._xlws.SORT(_xlpm.uniquePairs,1,1),INDEX(_xlpm.sortedPairs,ROWS($M$2:M3),2)),"")} -> LX175 | N3: {=IF(OR(Table2[[#This Row],[Film]]="",Table2[[#This Row],[Grade]]=""),"",IFERROR(INDEX(Table4[Serial Number],MATCH(1,(Table4[Film]=Table2[[#This Row],[Film]])*(Table4[Grade]=Table2[[#This Row],[Grade]]),0)),""))} -> RMLX175 | O3: =IF(OR(Table2[[#This Row],[Film]]="",Table2[[#This Row],[Grade]]=""),"",SUMIFS(Table4[Price Calculated(€) Thickness & QTY related],Table4[Film],Table2[[#This Row],[Film]],Table4[Grade],Table2[[#This Row],[Grade]])) -> 0.270084 | Q3: {=IFERROR(INDEX(Table2[Film],MATCH(0,COUNTIF($Q$1:Q2,Table2[Film])+IF(Table2[Film]="",1,0),0)),"")} -> PL202.2 | R3: =SUMIF(Table2[Film],"TIPA 312 MFG",Table2[Price Calculated(€) Thickness & QTY related])+_xlfn.XLOOKUP("MET LUX ",HELPER!$A:$A,HELPER!$E:$E,0) -> 5.380588 | S3: =IFERROR(R3*HELPER!$AK$2," ") -> 6.2414821 | U3: PL202.1 | V3: PLA | W3: LX175 | X3: RMLX175 | Y3: Resin 1A | Z3: {=SUMPRODUCT((BOM!$A$2:$A$391=U3)*(BOM!$F$2:$F$391=Y3)*BOM!$H$2:$H$391*BOM!$G$2:$G$391)/SUMPRODUCT((BOM!$A$2:$A$391=U3)*BOM!$H$2:$H$391*BOM!$G$2:$G$391)} -> 0.0852 | AA3: =SUMIF(tblResinWeightedQty12[Film],tblResinWeightedQty12[[#This Row],[Film]],tblResinWeightedQty12[Weighted QTY %]) -> 1
A4: TIPA 302FG | B4: Ext. A (Out - Chillroll) | C4: AB-PLA | D4: =IF(C4="","",IFERROR(_xlfn.XLOOKUP(C4,HELPER!$A$2:$A$81,HELPER!$B$2:$B$81,""),D4)) -> KAB59A | E4: =IFERROR(_xlfn.XLOOKUP(D4,HELPER!$B:$B,HELPER!$C:$C,""),"") -> RM A KAB59A | F4: =IFERROR(_xlfn.XLOOKUP(D4,HELPER!$B:$B,HELPER!$D:$D,""),"") -> Resin 8 | G4: 8 | H4: 0.015 | I4: =IF(AND(H4<>"",IFERROR(_xlfn.XLOOKUP(D4,HELPER!$B:$B,HELPER!$E:$E,""),"")=""),"Missing price",IFERROR(_xlfn.XLOOKUP(D4,HELPER!$B:$B,HELPER!$E:$E,"")," ")) -> 7.55 | J4: =IFERROR(H4*(IF(G4=8,I4*HELPER!$G$2,BOM!I4*HELPER!$G$3))," ") -> 0.02265 | L4: {=IFERROR(_xlfn.LET(_xlpm.films,Table4[Film],_xlpm.grades,Table4[Grade],_xlpm.pairs,_xlfn._xlws.FILTER(_xlfn.HSTACK(_xlpm.films,_xlpm.grades),(_xlpm.films<>"")*(TRIM(_xlpm.grades)<>"")),_xlpm.uniquePairs,_xlfn.UNIQUE(_xlpm.pairs),_xlpm.sortedPairs,_xlfn._xlws.SORT(_xlpm.uniquePairs,1,1),INDEX(_xlpm.sortedPairs,ROWS($L$2:L4),1)),"")} -> PL202.1 | M4: {=IFERROR(_xlfn.LET(_xlpm.films,Table4[Film],_xlpm.grades,Table4[Grade],_xlpm.pairs,_xlfn._xlws.FILTER(_xlfn.HSTACK(_xlpm.films,_xlpm.grades),(_xlpm.films<>"")*(TRIM(_xlpm.grades)<>"")),_xlpm.uniquePairs,_xlfn.UNIQUE(_xlpm.pairs),_xlpm.sortedPairs,_xlfn._xlws.SORT(_xlpm.uniquePairs,1,1),INDEX(_xlpm.sortedPairs,ROWS($M$2:M4),2)),"")} -> S723 | N4: {=IF(OR(Table2[[#This Row],[Film]]="",Table2[[#This Row],[Grade]]=""),"",IFERROR(INDEX(Table4[Serial Number],MATCH(1,(Table4[Film]=Table2[[#This Row],[Film]])*(Table4[Grade]=Table2[[#This Row],[Grade]]),0)),""))} -> RM TA45-08 S723 | O4: =IF(OR(Table2[[#This Row],[Film]]="",Table2[[#This Row],[Grade]]=""),"",SUMIFS(Table4[Price Calculated(€) Thickness & QTY related],Table4[Film],Table2[[#This Row],[Film]],Table4[Grade],Table2[[#This Row],[Grade]])) -> 0.3232 | Q4: {=IFERROR(INDEX(Table2[Film],MATCH(0,COUNTIF($Q$1:Q3,Table2[Film])+IF(Table2[Film]="",1,0),0)),"")} -> PL202.3 | R4: =SUMIF(Table2[Film],"TIPA 312 MFG",Table2[Price Calculated(€) Thickness & QTY related])+_xlfn.XLOOKUP("MET LUX ",HELPER!$A:$A,HELPER!$E:$E,0) -> 5.380588 | S4: =IFERROR(R4*HELPER!$AK$2," ") -> 6.2414821 | U4: PL202.1 | V4: PBAT | W4: B12 | X4: RMB12 | Y4: Resin 2A | Z4: {=SUMPRODUCT((BOM!$A$2:$A$391=U4)*(BOM!$F$2:$F$391=Y4)*BOM!$H$2:$H$391*BOM!$G$2:$G$391)/SUMPRODUCT((BOM!$A$2:$A$391=U4)*BOM!$H$2:$H$391*BOM!$G$2:$G$391)} -> 0.138 | AA4: =SUMIF(tblResinWeightedQty12[Film],tblResinWeightedQty12[[#This Row],[Film]],tblResinWeightedQty12[Weighted QTY %]) -> 1
A5: TIPA 302FG | B5: Ext. A (Out - Chillroll) | C5: AO-PBS | D5: =IF(C5="","",IFERROR(_xlfn.XLOOKUP(C5,HELPER!$A$2:$A$81,HELPER!$B$2:$B$81,""),D5)) -> S723 | E5: =IFERROR(_xlfn.XLOOKUP(D5,HELPER!$B:$B,HELPER!$C:$C,""),"") -> RM TA45-08 S723 | F5: =IFERROR(_xlfn.XLOOKUP(D5,HELPER!$B:$B,HELPER!$D:$D,""),"") -> Resin 6 | G5: 8 | H5: 0.015 | I5: =IF(AND(H5<>"",IFERROR(_xlfn.XLOOKUP(D5,HELPER!$B:$B,HELPER!$E:$E,""),"")=""),"Missing price",IFERROR(_xlfn.XLOOKUP(D5,HELPER!$B:$B,HELPER!$E:$E,"")," ")) -> 16.16 | J5: =IFERROR(H5*(IF(G5=8,I5*HELPER!$G$2,BOM!I5*HELPER!$G$3))," ") -> 0.04848 | L5: {=IFERROR(_xlfn.LET(_xlpm.films,Table4[Film],_xlpm.grades,Table4[Grade],_xlpm.pairs,_xlfn._xlws.FILTER(_xlfn.HSTACK(_xlpm.films,_xlpm.grades),(_xlpm.films<>"")*(TRIM(_xlpm.grades)<>"")),_xlpm.uniquePairs,_xlfn.UNIQUE(_xlpm.pairs),_xlpm.sortedPairs,_xlfn._xlws.SORT(_xlpm.uniquePairs,1,1),INDEX(_xlpm.sortedPairs,ROWS($L$2:L5),1)),"")} -> PL202.1 | M5: {=IFERROR(_xlfn.LET(_xlpm.films,Table4[Film],_xlpm.grades,Table4[Grade],_xlpm.pairs,_xlfn._xlws.FILTER(_xlfn.HSTACK(_xlpm.films,_xlpm.grades),(_xlpm.films<>"")*(TRIM(_xlpm.grades)<>"")),_xlpm.uniquePairs,_xlfn.UNIQUE(_xlpm.pairs),_xlpm.sortedPairs,_xlfn._xlws.SORT(_xlpm.uniquePairs,1,1),INDEX(_xlpm.sortedPairs,ROWS($M$2:M5),2)),"")} -> S724 | N5: {=IF(OR(Table2[[#This Row],[Film]]="",Table2[[#This Row],[Grade]]=""),"",IFERROR(INDEX(Table4[Serial Number],MATCH(1,(Table4[Film]=Table2[[#This Row],[Film]])*(Table4[Grade]=Table2[[#This Row],[Grade]]),0)),""))} -> RM TA45-08 S724 | O5: =IF(OR(Table2[[#This Row],[Film]]="",Table2[[#This Row],[Grade]]=""),"",SUMIFS(Table4[Price Calculated(€) Thickness & QTY related],Table4[Film],Table2[[#This Row],[Film]],Table4[Grade],Table2[[#This Row],[Grade]])) -> 0.1764 | Q5: {=IFERROR(INDEX(Table2[Film],MATCH(0,COUNTIF($Q$1:Q4,Table2[Film])+IF(Table2[Film]="",1,0),0)),"")} -> TIPA 302FG | R5: =SUMIF(Table2[Film],"TIPA 312 MFG",Table2[Price Calculated(€) Thickness & QTY related])+_xlfn.XLOOKUP("MET LUX ",HELPER!$A:$A,HELPER!$E:$E,0) -> 5.380588 | S5: =IFERROR(R5*HELPER!$AK$2," ") -> 6.2414821 | U5: PL202.1 | V5: AO-PBS | W5: S723 | X5: RM TA45-08 S723 | Y5: Resin 6 | Z5: {=SUMPRODUCT((BOM!$A$2:$A$391=U5)*(BOM!$F$2:$F$391=Y5)*BOM!$H$2:$H$391*BOM!$G$2:$G$391)/SUMPRODUCT((BOM!$A$2:$A$391=U5)*BOM!$H$2:$H$391*BOM!$G$2:$G$391)} -> 0.02 | AA5: =SUMIF(tblResinWeightedQty12[Film],tblResinWeightedQty12[[#This Row],[Film]],tblResinWeightedQty12[Weighted QTY %]) -> 1
A6: TIPA 302FG | B6: Ext. A (Out - Chillroll) | D6: =IF(C6="","",IFERROR(_xlfn.XLOOKUP(C6,HELPER!$A$2:$A$81,HELPER!$B$2:$B$81,""),D6)) | E6: =IFERROR(_xlfn.XLOOKUP(D6,HELPER!$B:$B,HELPER!$C:$C,""),"") | F6: =IFERROR(_xlfn.XLOOKUP(D6,HELPER!$B:$B,HELPER!$D:$D,""),"") | G6: 8 | I6: =IF(AND(H6<>"",IFERROR(_xlfn.XLOOKUP(D6,HELPER!$B:$B,HELPER!$E:$E,""),"")=""),"Missing price",IFERROR(_xlfn.XLOOKUP(D6,HELPER!$B:$B,HELPER!$E:$E,"")," ")) | J6: =IFERROR(H6*(IF(G6=8,I6*HELPER!$G$2,BOM!I6*HELPER!$G$3))," ") | L6: {=IFERROR(_xlfn.LET(_xlpm.films,Table4[Film],_xlpm.grades,Table4[Grade],_xlpm.pairs,_xlfn._xlws.FILTER(_xlfn.HSTACK(_xlpm.films,_xlpm.grades),(_xlpm.films<>"")*(TRIM(_xlpm.grades)<>"")),_xlpm.uniquePairs,_xlfn.UNIQUE(_xlpm.pairs),_xlpm.sortedPairs,_xlfn._xlws.SORT(_xlpm.uniquePairs,1,1),INDEX(_xlpm.sortedPairs,ROWS($L$2:L6),1)),"")} -> PL202.1 | M6: {=IFERROR(_xlfn.LET(_xlpm.films,Table4[Film],_xlpm.grades,Table4[Grade],_xlpm.pairs,_xlfn._xlws.FILTER(_xlfn.HSTACK(_xlpm.films,_xlpm.grades),(_xlpm.films<>"")*(TRIM(_xlpm.grades)<>"")),_xlpm.uniquePairs,_xlfn.UNIQUE(_xlpm.pairs),_xlpm.sortedPairs,_xlfn._xlws.SORT(_xlpm.uniquePairs,1,1),INDEX(_xlpm.sortedPairs,ROWS($M$2:M6),2)),"")} -> KAB59A | N6: {=IF(OR(Table2[[#This Row],[Film]]="",Table2[[#This Row],[Grade]]=""),"",IFERROR(INDEX(Table4[Serial Number],MATCH(1,(Table4[Film]=Table2[[#This Row],[Film]])*(Table4[Grade]=Table2[[#This Row],[Grade]]),0)),""))} -> RM A KAB59A | O6: =IF(OR(Table2[[#This Row],[Film]]="",Table2[[#This Row],[Grade]]=""),"",SUMIFS(Table4[Price Calculated(€) Thickness & QTY related],Table4[Film],Table2[[#This Row],[Film]],Table4[Grade],Table2[[#This Row],[Grade]])) -> 0.06795 | Q6: {=IFERROR(INDEX(Table2[Film],MATCH(0,COUNTIF($Q$1:Q5,Table2[Film])+IF(Table2[Film]="",1,0),0)),"")} -> TIPA 302FG W | R6: =SUMIF(Table2[Film],"TIPA 312 MFG",Table2[Price Calculated(€) Thickness & QTY related])+_xlfn.XLOOKUP("MET LUX ",HELPER!$A:$A,HELPER!$E:$E,0) -> 5.380588 | S6: =IFERROR(R6*HELPER!$AK$2," ") -> 6.2414821 | U6: PL202.1 | V6: SLAB-PBSA | W6: S724 | X6: RM TA45-08 S724 | Y6: Resin 7 | Z6: {=SUMPRODUCT((BOM!$A$2:$A$391=U6)*(BOM!$F$2:$F$391=Y6)*BOM!$H$2:$H$391*BOM!$G$2:$G$391)/SUMPRODUCT((BOM!$A$2:$A$391=U6)*BOM!$H$2:$H$391*BOM!$G$2:$G$391)} -> 0.012 | AA6: =SUMIF(tblResinWeightedQty12[Film],tblResinWeightedQty12[[#This Row],[Film]],tblResinWeightedQty12[Weighted QTY %]) -> 1
A7: TIPA 302FG | B7: Ext. A (Out - Chillroll) | D7: =IF(C7="","",IFERROR(_xlfn.XLOOKUP(C7,HELPER!$A$2:$A$81,HELPER!$B$2:$B$81,""),D7)) | E7: =IFERROR(_xlfn.XLOOKUP(D7,HELPER!$B:$B,HELPER!$C:$C,""),"") | F7: =IFERROR(_xlfn.XLOOKUP(D7,HELPER!$B:$B,HELPER!$D:$D,""),"") | G7: 8 | I7: =IF(AND(H7<>"",IFERROR(_xlfn.XLOOKUP(D7,HELPER!$B:$B,HELPER!$E:$E,""),"")=""),"Missing price",IFERROR(_xlfn.XLOOKUP(D7,HELPER!$B:$B,HELPER!$E:$E,"")," ")) | J7: =IFERROR(H7*(IF(G7=8,I7*HELPER!$G$2,BOM!I7*HELPER!$G$3))," ") | L7: {=IFERROR(_xlfn.LET(_xlpm.films,Table4[Film],_xlpm.grades,Table4[Grade],_xlpm.pairs,_xlfn._xlws.FILTER(_xlfn.HSTACK(_xlpm.films,_xlpm.grades),(_xlpm.films<>"")*(TRIM(_xlpm.grades)<>"")),_xlpm.uniquePairs,_xlfn.UNIQUE(_xlpm.pairs),_xlpm.sortedPairs,_xlfn._xlws.SORT(_xlpm.uniquePairs,1,1),INDEX(_xlpm.sortedPairs,ROWS($L$2:L7),1)),"")} -> PL202.1 | M7: {=IFERROR(_xlfn.LET(_xlpm.films,Table4[Film],_xlpm.grades,Table4[Grade],_xlpm.pairs,_xlfn._xlws.FILTER(_xlfn.HSTACK(_xlpm.films,_xlpm.grades),(_xlpm.films<>"")*(TRIM(_xlpm.grades)<>"")),_xlpm.uniquePairs,_xlfn.UNIQUE(_xlpm.pairs),_xlpm.sortedPairs,_xlfn._xlws.SORT(_xlpm.uniquePairs,1,1),INDEX(_xlpm.sortedPairs,ROWS($M$2:M7),2)),"")} -> BVE8049P | N7: {=IF(OR(Table2[[#This Row],[Film]]="",Table2[[#This Row],[Grade]]=""),"",IFERROR(INDEX(Table4[Serial Number],MATCH(1,(Table4[Film]=Table2[[#This Row],[Film]])*(Table4[Grade]=Table2[[#This Row],[Grade]]),0)),""))} -> BVE8049P | O7: =IF(OR(Table2[[#This Row],[Film]]="",Table2[[#This Row],[Grade]]=""),"",SUMIFS(Table4[Price Calculated(€) Thickness & QTY related],Table4[Film],Table2[[#This Row],[Film]],Table4[Grade],Table2[[#This Row],[Grade]])) -> 4.699 | Q7: {=IFERROR(INDEX(Table2[Film],MATCH(0,COUNTIF($Q$1:Q6,Table2[Film])+IF(Table2[Film]="",1,0),0)),"")} -> TIPA 306M | R7: =SUMIF(Table2[Film],"TIPA 312 MFG",Table2[Price Calculated(€) Thickness & QTY related])+_xlfn.XLOOKUP("MET LUX ",HELPER!$A:$A,HELPER!$E:$E,0) -> 5.380588 | S7: =IFERROR(R7*HELPER!$AK$2," ") -> 6.2414821 | U7: PL202.1 | V7: AB-PLA | W7: KAB59A | X7: RM A KAB59A | Y7: Resin 8 | Z7: {=SUMPRODUCT((BOM!$A$2:$A$391=U7)*(BOM!$F$2:$F$391=Y7)*BOM!$H$2:$H$391*BOM!$G$2:$G$391)/SUMPRODUCT((BOM!$A$2:$A$391=U7)*BOM!$H$2:$H$391*BOM!$G$2:$G$391)} -> 0.009 | AA7: =SUMIF(tblResinWeightedQty12[Film],tblResinWeightedQty12[[#This Row],[Film]],tblResinWeightedQty12[Weighted QTY %]) -> 1
A8: TIPA 302FG | B8: Ext. A (Out - Chillroll) | D8: =IF(C8="","",IFERROR(_xlfn.XLOOKUP(C8,HELPER!$A$2:$A$81,HELPER!$B$2:$B$81,""),D8)) | E8: =IFERROR(_xlfn.XLOOKUP(D8,HELPER!$B:$B,HELPER!$C:$C,""),"") | F8: =IFERROR(_xlfn.XLOOKUP(D8,HELPER!$B:$B,HELPER!$D:$D,""),"") | G8: 8 | I8: =IF(AND(H8<>"",IFERROR(_xlfn.XLOOKUP(D8,HELPER!$B:$B,HELPER!$E:$E,""),"")=""),"Missing price",IFERROR(_xlfn.XLOOKUP(D8,HELPER!$B:$B,HELPER!$E:$E,"")," ")) | J8: =IFERROR(H8*(IF(G8=8,I8*HELPER!$G$2,BOM!I8*HELPER!$G$3))," ") | L8: {=IFERROR(_xlfn.LET(_xlpm.films,Table4[Film],_xlpm.grades,Table4[Grade],_xlpm.pairs,_xlfn._xlws.FILTER(_xlfn.HSTACK(_xlpm.films,_xlpm.grades),(_xlpm.films<>"")*(TRIM(_xlpm.grades)<>"")),_xlpm.uniquePairs,_xlfn.UNIQUE(_xlpm.pairs),_xlpm.sortedPairs,_xlfn._xlws.SORT(_xlpm.uniquePairs,1,1),INDEX(_xlpm.sortedPairs,ROWS($L$2:L8),1)),"")} -> PL202.1 | M8: {=IFERROR(_xlfn.LET(_xlpm.films,Table4[Film],_xlpm.grades,Table4[Grade],_xlpm.pairs,_xlfn._xlws.FILTER(_xlfn.HSTACK(_xlpm.films,_xlpm.grades),(_xlpm.films<>"")*(TRIM(_xlpm.grades)<>"")),_xlpm.uniquePairs,_xlfn.UNIQUE(_xlpm.pairs),_xlpm.sortedPairs,_xlfn._xlws.SORT(_xlpm.uniquePairs,1,1),INDEX(_xlpm.sortedPairs,ROWS($M$2:M8),2)),"")} -> B12 | N8: {=IF(OR(Table2[[#This Row],[Film]]="",Table2[[#This Row],[Grade]]=""),"",IFERROR(INDEX(Table4[Serial Number],MATCH(1,(Table4[Film]=Table2[[#This Row],[Film]])*(Table4[Grade]=Table2[[#This Row],[Grade]]),0)),""))} -> RMB12 | O8: =IF(OR(Table2[[#This Row],[Film]]="",Table2[[#This Row],[Grade]]=""),"",SUMIFS(Table4[Price Calculated(€) Thickness & QTY related],Table4[Film],Table2[[#This Row],[Film]],Table4[Grade],Table2[[#This Row],[Grade]])) -> 0.24978 | Q8: {=IFERROR(INDEX(Table2[Film],MATCH(0,COUNTIF($Q$1:Q7,Table2[Film])+IF(Table2[Film]="",1,0),0)),"")} -> TIPA 306W | R8: =SUMIF(Table2[Film],"TIPA 312 MFG",Table2[Price Calculated(€) Thickness & QTY related])+_xlfn.XLOOKUP("MET LUX ",HELPER!$A:$A,HELPER!$E:$E,0) -> 5.380588 | S8: =IFERROR(R8*HELPER!$AK$2," ") -> 6.2414821 | U8: PL202.1 | V8: PBSA | W8: FD92PM | X8: RMPM2 | Y8: Resin 9C | Z8: {=SUMPRODUCT((BOM!$A$2:$A$391=U8)*(BOM!$F$2:$F$391=Y8)*BOM!$H$2:$H$391*BOM!$G$2:$G$391)/SUMPRODUCT((BOM!$A$2:$A$391=U8)*BOM!$H$2:$H$391*BOM!$G$2:$G$391)} -> 0.4818 | AA8: =SUMIF(tblResinWeightedQty12[Film],tblResinWeightedQty12[[#This Row],[Film]],tblResinWeightedQty12[Weighted QTY %]) -> 1
A9: TIPA 302FG | B9: Ext. A (Out - Chillroll) | D9: =IF(C9="","",IFERROR(_xlfn.XLOOKUP(C9,HELPER!$A$2:$A$81,HELPER!$B$2:$B$81,""),D9)) | E9: =IFERROR(_xlfn.XLOOKUP(D9,HELPER!$B:$B,HELPER!$C:$C,""),"") | F9: =IFERROR(_xlfn.XLOOKUP(D9,HELPER!$B:$B,HELPER!$D:$D,""),"") | G9: 8 | I9: =IF(AND(H9<>"",IFERROR(_xlfn.XLOOKUP(D9,HELPER!$B:$B,HELPER!$E:$E,""),"")=""),"Missing price",IFERROR(_xlfn.XLOOKUP(D9,HELPER!$B:$B,HELPER!$E:$E,"")," ")) | J9: =IFERROR(H9*(IF(G9=8,I9*HELPER!$G$2,BOM!I9*HELPER!$G$3))," ") | L9: {=IFERROR(_xlfn.LET(_xlpm.films,Table4[Film],_xlpm.grades,Table4[Grade],_xlpm.pairs,_xlfn._xlws.FILTER(_xlfn.HSTACK(_xlpm.films,_xlpm.grades),(_xlpm.films<>"")*(TRIM(_xlpm.grades)<>"")),_xlpm.uniquePairs,_xlfn.UNIQUE(_xlpm.pairs),_xlpm.sortedPairs,_xlfn._xlws.SORT(_xlpm.uniquePairs,1,1),INDEX(_xlpm.sortedPairs,ROWS($L$2:L9),1)),"")} -> PL202.2 | M9: {=IFERROR(_xlfn.LET(_xlpm.films,Table4[Film],_xlpm.grades,Table4[Grade],_xlpm.pairs,_xlfn._xlws.FILTER(_xlfn.HSTACK(_xlpm.films,_xlpm.grades),(_xlpm.films<>"")*(TRIM(_xlpm.grades)<>"")),_xlpm.uniquePairs,_xlfn.UNIQUE(_xlpm.pairs),_xlpm.sortedPairs,_xlfn._xlws.SORT(_xlpm.uniquePairs,1,1),INDEX(_xlpm.sortedPairs,ROWS($M$2:M9),2)),"")} -> LX175 | N9: {=IF(OR(Table2[[#This Row],[Film]]="",Table2[[#This Row],[Grade]]=""),"",IFERROR(INDEX(Table4[Serial Number],MATCH(1,(Table4[Film]=Table2[[#This Row],[Film]])*(Table4[Grade]=Table2[[#This Row],[Grade]]),0)),""))} -> RMLX175 | O9: =IF(OR(Table2[[#This Row],[Film]]="",Table2[[#This Row],[Grade]]=""),"",SUMIFS(Table4[Price Calculated(€) Thickness & QTY related],Table4[Film],Table2[[#This Row],[Film]],Table4[Grade],Table2[[#This Row],[Grade]])) -> 1.50258 | Q9: {=IFERROR(INDEX(Table2[Film],MATCH(0,COUNTIF($Q$1:Q8,Table2[Film])+IF(Table2[Film]="",1,0),0)),"")} -> TIPA 312 MFG | R9: =SUMIF(Table2[Film],"TIPA 312 MFG",Table2[Price Calculated(€) Thickness & QTY related])+_xlfn.XLOOKUP("MET LUX ",HELPER!$A:$A,HELPER!$E:$E,0) -> 5.380588 | S9: =IFERROR(R9*HELPER!$AK$2," ") -> 6.2414821 | U9: PL202.2 | V9: PVOH | W9: BVE8049P | X9: BVE8049P | Y9: BVE8049P | Z9: {=SUMPRODUCT((BOM!$A$2:$A$391=U9)*(BOM!$F$2:$F$391=Y9)*BOM!$H$2:$H$391*BOM!$G$2:$G$391)/SUMPRODUCT((BOM!$A$2:$A$391=U9)*BOM!$H$2:$H$391*BOM!$G$2:$G$391)} -> 0.254 | AA9: =SUMIF(tblResinWeightedQty12[Film],tblResinWeightedQty12[[#This Row],[Film]],tblResinWeightedQty12[Weighted QTY %]) -> 1
A10: TIPA 302FG | B10: Ext. A (Out - Chillroll) | D10: =IF(C10="","",IFERROR(_xlfn.XLOOKUP(C10,HELPER!$A$2:$A$81,HELPER!$B$2:$B$81,""),D10)) | E10: =IFERROR(_xlfn.XLOOKUP(D10,HELPER!$B:$B,HELPER!$C:$C,""),"") | F10: =IFERROR(_xlfn.XLOOKUP(D10,HELPER!$B:$B,HELPER!$D:$D,""),"") | G10: 8 | I10: =IF(AND(H10<>"",IFERROR(_xlfn.XLOOKUP(D10,HELPER!$B:$B,HELPER!$E:$E,""),"")=""),"Missing price",IFERROR(_xlfn.XLOOKUP(D10,HELPER!$B:$B,HELPER!$E:$E,"")," ")) | J10: =IFERROR(H10*(IF(G10=8,I10*HELPER!$G$2,BOM!I10*HELPER!$G$3))," ") | L10: {=IFERROR(_xlfn.LET(_xlpm.films,Table4[Film],_xlpm.grades,Table4[Grade],_xlpm.pairs,_xlfn._xlws.FILTER(_xlfn.HSTACK(_xlpm.films,_xlpm.grades),(_xlpm.films<>"")*(TRIM(_xlpm.grades)<>"")),_xlpm.uniquePairs,_xlfn.UNIQUE(_xlpm.pairs),_xlpm.sortedPairs,_xlfn._xlws.SORT(_xlpm.uniquePairs,1,1),INDEX(_xlpm.sortedPairs,ROWS($L$2:L10),1)),"")} -> PL202.2 | M10: {=IFERROR(_xlfn.LET(_xlpm.films,Table4[Film],_xlpm.grades,Table4[Grade],_xlpm.pairs,_xlfn._xlws.FILTER(_xlfn.HSTACK(_xlpm.films,_xlpm.grades),(_xlpm.films<>"")*(TRIM(_xlpm.grades)<>"")),_xlpm.uniquePairs,_xlfn.UNIQUE(_xlpm.pairs),_xlpm.sortedPairs,_xlfn._xlws.SORT(_xlpm.uniquePairs,1,1),INDEX(_xlpm.sortedPairs,ROWS($M$2:M10),2)),"")} -> P65D | N10: {=IF(OR(Table2[[#This Row],[Film]]="",Table2[[#This Row],[Grade]]=""),"",IFERROR(INDEX(Table4[Serial Number],MATCH(1,(Table4[Film]=Table2[[#This Row],[Film]])*(Table4[Grade]=Table2[[#This Row],[Grade]]),0)),""))} -> RMP65D | O10: =IF(OR(Table2[[#This Row],[Film]]="",Table2[[#This Row],[Grade]]=""),"",SUMIFS(Table4[Price Calculated(€) Thickness & QTY related],Table4[Film],Table2[[#This Row],[Film]],Table4[Grade],Table2[[#This Row],[Grade]])) -> 0.8322 | Q10: {=IFERROR(INDEX(Table2[Film],MATCH(0,COUNTIF($Q$1:Q9,Table2[Film])+IF(Table2[Film]="",1,0),0)),"")} -> TIPA 312MFGW | R10: =SUMIF(Table2[Film],"TIPA 312 MFG",Table2[Price Calculated(€) Thickness & QTY related])+_xlfn.XLOOKUP("MET LUX ",HELPER!$A:$A,HELPER!$E:$E,0) -> 5.380588 | S10: =IFERROR(R10*HELPER!$AK$2," ") -> 6.2414821 | U10: PL202.2 | V10: PLA | W10: LX175 | X10: RMLX175 | Y10: Resin 1A | Z10: {=SUMPRODUCT((BOM!$A$2:$A$391=U10)*(BOM!$F$2:$F$391=Y10)*BOM!$H$2:$H$391*BOM!$G$2:$G$391)/SUMPRODUCT((BOM!$A$2:$A$391=U10)*BOM!$H$2:$H$391*BOM!$G$2:$G$391)} -> 0.474 | AA10: =SUMIF(tblResinWeightedQty12[Film],tblResinWeightedQty12[[#This Row],[Film]],tblResinWeightedQty12[Weighted QTY %]) -> 1
A11: TIPA 302FG | B11: Ext. A (Out - Chillroll) | D11: =IF(C11="","",IFERROR(_xlfn.XLOOKUP(C11,HELPER!$A$2:$A$81,HELPER!$B$2:$B$81,""),D11)) | E11: =IFERROR(_xlfn.XLOOKUP(D11,HELPER!$B:$B,HELPER!$C:$C,""),"") | F11: =IFERROR(_xlfn.XLOOKUP(D11,HELPER!$B:$B,HELPER!$D:$D,""),"") | G11: 8 | I11: =IF(AND(H11<>"",IFERROR(_xlfn.XLOOKUP(D11,HELPER!$B:$B,HELPER!$E:$E,""),"")=""),"Missing price",IFERROR(_xlfn.XLOOKUP(D11,HELPER!$B:$B,HELPER!$E:$E,"")," ")) | J11: =IFERROR(H11*(IF(G11=8,I11*HELPER!$G$2,BOM!I11*HELPER!$G$3))," ") | L11: {=IFERROR(_xlfn.LET(_xlpm.films,Table4[Film],_xlpm.grades,Table4[Grade],_xlpm.pairs,_xlfn._xlws.FILTER(_xlfn.HSTACK(_xlpm.films,_xlpm.grades),(_xlpm.films<>"")*(TRIM(_xlpm.grades)<>"")),_xlpm.uniquePairs,_xlfn.UNIQUE(_xlpm.pairs),_xlpm.sortedPairs,_xlfn._xlws.SORT(_xlpm.uniquePairs,1,1),INDEX(_xlpm.sortedPairs,ROWS($L$2:L11),1)),"")} -> PL202.2 | M11: {=IFERROR(_xlfn.LET(_xlpm.films,Table4[Film],_xlpm.grades,Table4[Grade],_xlpm.pairs,_xlfn._xlws.FILTER(_xlfn.HSTACK(_xlpm.films,_xlpm.grades),(_xlpm.films<>"")*(TRIM(_xlpm.grades)<>"")),_xlpm.uniquePairs,_xlfn.UNIQUE(_xlpm.pairs),_xlpm.sortedPairs,_xlfn._xlws.SORT(_xlpm.uniquePairs,1,1),INDEX(_xlpm.sortedPairs,ROWS($M$2:M11),2)),"")} -> S723 | N11: {=IF(OR(Table2[[#This Row],[Film]]="",Table2[[#This Row],[Grade]]=""),"",IFERROR(INDEX(Table4[Serial Number],MATCH(1,(Table4[Film]=Table2[[#This Row],[Film]])*(Table4[Grade]=Table2[[#This Row],[Grade]]),0)),""))} -> RM TA45-08 S723 | O11: =IF(OR(Table2[[#This Row],[Film]]="",Table2[[#This Row],[Grade]]=""),"",SUMIFS(Table4[Price Calculated(€) Thickness & QTY related],Table4[Film],Table2[[#This Row],[Film]],Table4[Grade],Table2[[#This Row],[Grade]])) -> 0.3232 | Q11: TIPA 312 MET | R11: =SUMIF(Table2[Film],"TIPA 312 MFG",Table2[Price Calculated(€) Thickness & QTY related])+_xlfn.XLOOKUP("MET LUX ",HELPER!$A:$A,HELPER!$E:$E,0) -> 5.380588 | S11: =IFERROR(R11*HELPER!$AK$2," ") -> 6.2414821 | U11: PL202.2 | V11: PBAT | W11: B12 | X11: RMB12 | Y11: Resin 2A | Z11: {=SUMPRODUCT((BOM!$A$2:$A$391=U11)*(BOM!$F$2:$F$391=Y11)*BOM!$H$2:$H$391*BOM!$G$2:$G$391)/SUMPRODUCT((BOM!$A$2:$A$391=U11)*BOM!$H$2:$H$391*BOM!$G$2:$G$391)} -> 0.138 | AA11: =SUMIF(tblResinWeightedQty12[Film],tblResinWeightedQty12[[#This Row],[Film]],tblResinWeightedQty12[Weighted QTY %]) -> 1
A12: TIPA 302FG | B12: Ext. B | D12: =IF(C12="","",IFERROR(_xlfn.XLOOKUP(C12,HELPER!$A$2:$A$81,HELPER!$B$2:$B$81,""),D12)) | E12: =IFERROR(_xlfn.XLOOKUP(D12,HELPER!$B:$B,HELPER!$C:$C,""),"") | F12: =IFERROR(_xlfn.XLOOKUP(D12,HELPER!$B:$B,HELPER!$D:$D,""),"") | G12: 8 | I12: =IF(AND(H12<>"",IFERROR(_xlfn.XLOOKUP(D12,HELPER!$B:$B,HELPER!$E:$E,""),"")=""),"Missing price",IFERROR(_xlfn.XLOOKUP(D12,HELPER!$B:$B,HELPER!$E:$E,"")," ")) | J12: =IFERROR(H12*(IF(G12=8,I12*HELPER!$G$2,BOM!I12*HELPER!$G$3))," ") | L12: {=IFERROR(_xlfn.LET(_xlpm.films,Table4[Film],_xlpm.grades,Table4[Grade],_xlpm.pairs,_xlfn._xlws.FILTER(_xlfn.HSTACK(_xlpm.films,_xlpm.grades),(_xlpm.films<>"")*(TRIM(_xlpm.grades)<>"")),_xlpm.uniquePairs,_xlfn.UNIQUE(_xlpm.pairs),_xlpm.sortedPairs,_xlfn._xlws.SORT(_xlpm.uniquePairs,1,1),INDEX(_xlpm.sortedPairs,ROWS($L$2:L12),1)),"")} -> PL202.2 | M12: {=IFERROR(_xlfn.LET(_xlpm.films,Table4[Film],_xlpm.grades,Table4[Grade],_xlpm.pairs,_xlfn._xlws.FILTER(_xlfn.HSTACK(_xlpm.films,_xlpm.grades),(_xlpm.films<>"")*(TRIM(_xlpm.grades)<>"")),_xlpm.uniquePairs,_xlfn.UNIQUE(_xlpm.pairs),_xlpm.sortedPairs,_xlfn._xlws.SORT(_xlpm.uniquePairs,1,1),INDEX(_xlpm.sortedPairs,ROWS($M$2:M12),2)),"")} -> BVE8049P | N12: {=IF(OR(Table2[[#This Row],[Film]]="",Table2[[#This Row],[Grade]]=""),"",IFERROR(INDEX(Table4[Serial Number],MATCH(1,(Table4[Film]=Table2[[#This Row],[Film]])*(Table4[Grade]=Table2[[#This Row],[Grade]]),0)),""))} -> BVE8049P | O12: =IF(OR(Table2[[#This Row],[Film]]="",Table2[[#This Row],[Grade]]=""),"",SUMIFS(Table4[Price Calculated(€) Thickness & QTY related],Table4[Film],Table2[[#This Row],[Film]],Table4[Grade],Table2[[#This Row],[Grade]])) -> 4.699 | Q12: {=IFERROR(INDEX(Table2[Film],MATCH(0,COUNTIF($Q$1:Q11,Table2[Film])+IF(Table2[Film]="",1,0),0)),"")} | R12: =SUMIF(Table2[Film],"TIPA 312 MFG",Table2[Price Calculated(€) Thickness & QTY related])+_xlfn.XLOOKUP("MET LUX ",HELPER!$A:$A,HELPER!$E:$E,0) -> 5.380588 | S12: =IFERROR(R12*HELPER!$AK$2," ") -> 6.2414821 | U12: PL202.2 | V12: PCL | W12: P65D | X12: RMP65D | Y12: Resin 4A | Z12: {=SUMPRODUCT((BOM!$A$2:$A$391=U12)*(BOM!$F$2:$F$391=Y12)*BOM!$H$2:$H$391*BOM!$G$2:$G$391)/SUMPRODUCT((BOM!$A$2:$A$391=U12)*BOM!$H$2:$H$391*BOM!$G$2:$G$391)} -> 0.114 | AA12: =SUMIF(tblResinWeightedQty12[Film],tblResinWeightedQty12[[#This Row],[Film]],tblResinWeightedQty12[Weighted QTY %]) -> 1
A13: TIPA 302FG | B13: Ext. B | D13: =IF(C13="","",IFERROR(_xlfn.XLOOKUP(C13,HELPER!$A$2:$A$81,HELPER!$B$2:$B$81,""),D13)) | E13: =IFERROR(_xlfn.XLOOKUP(D13,HELPER!$B:$B,HELPER!$C:$C,""),"") | F13: =IFERROR(_xlfn.XLOOKUP(D13,HELPER!$B:$B,HELPER!$D:$D,""),"") | G13: 24 | I13: =IF(AND(H13<>"",IFERROR(_xlfn.XLOOKUP(D13,HELPER!$B:$B,HELPER!$E:$E,""),"")=""),"Missing price",IFERROR(_xlfn.XLOOKUP(D13,HELPER!$B:$B,HELPER!$E:$E,"")," ")) | J13: =IFERROR(H13*(IF(G13=8,I13*HELPER!$G$2,BOM!I13*HELPER!$G$3))," ") | L13: {=IFERROR(_xlfn.LET(_xlpm.films,Table4[Film],_xlpm.grades,Table4[Grade],_xlpm.pairs,_xlfn._xlws.FILTER(_xlfn.HSTACK(_xlpm.films,_xlpm.grades),(_xlpm.films<>"")*(TRIM(_xlpm.grades)<>"")),_xlpm.uniquePairs,_xlfn.UNIQUE(_xlpm.pairs),_xlpm.sortedPairs,_xlfn._xlws.SORT(_xlpm.uniquePairs,1,1),INDEX(_xlpm.sortedPairs,ROWS($L$2:L13),1)),"")} -> PL202.2 | M13: {=IFERROR(_xlfn.LET(_xlpm.films,Table4[Film],_xlpm.grades,Table4[Grade],_xlpm.pairs,_xlfn._xlws.FILTER(_xlfn.HSTACK(_xlpm.films,_xlpm.grades),(_xlpm.films<>"")*(TRIM(_xlpm.grades)<>"")),_xlpm.uniquePairs,_xlfn.UNIQUE(_xlpm.pairs),_xlpm.sortedPairs,_xlfn._xlws.SORT(_xlpm.uniquePairs,1,1),INDEX(_xlpm.sortedPairs,ROWS($M$2:M13),2)),"")} -> B12 | N13: {=IF(OR(Table2[[#This Row],[Film]]="",Table2[[#This Row],[Grade]]=""),"",IFERROR(INDEX(Table4[Serial Number],MATCH(1,(Table4[Film]=Table2[[#This Row],[Film]])*(Table4[Grade]=Table2[[#This Row],[Grade]]),0)),""))} -> RMB12 | O13: =IF(OR(Table2[[#This Row],[Film]]="",Table2[[#This Row],[Grade]]=""),"",SUMIFS(Table4[Price Calculated(€) Thickness & QTY related],Table4[Film],Table2[[#This Row],[Film]],Table4[Grade],Table2[[#This Row],[Grade]])) -> 0.24978 | Q13: {=IFERROR(INDEX(Table2[Film],MATCH(0,COUNTIF($Q$1:Q12,Table2[Film])+IF(Table2[Film]="",1,0),0)),"")} | R13: =SUMIF(Table2[Film],"TIPA 312 MFG",Table2[Price Calculated(€) Thickness & QTY related])+_xlfn.XLOOKUP("MET LUX ",HELPER!$A:$A,HELPER!$E:$E,0) -> 5.380588 | S13: =IFERROR(R13*HELPER!$AK$2," ") -> 6.2414821 | U13: PL202.2 | V13: AO-PBS | W13: S723 | X13: RM TA45-08 S723 | Y13: Resin 6 | Z13: {=SUMPRODUCT((BOM!$A$2:$A$391=U13)*(BOM!$F$2:$F$391=Y13)*BOM!$H$2:$H$391*BOM!$G$2:$G$391)/SUMPRODUCT((BOM!$A$2:$A$391=U13)*BOM!$H$2:$H$391*BOM!$G$2:$G$391)} -> 0.02 | AA13: =SUMIF(tblResinWeightedQty12[Film],tblResinWeightedQty12[[#This Row],[Film]],tblResinWeightedQty12[Weighted QTY %]) -> 1
A14: TIPA 302FG | B14: Ext. B | D14: =IF(C14="","",IFERROR(_xlfn.XLOOKUP(C14,HELPER!$A$2:$A$81,HELPER!$B$2:$B$81,""),D14)) | E14: =IFERROR(_xlfn.XLOOKUP(D14,HELPER!$B:$B,HELPER!$C:$C,""),"") | F14: =IFERROR(_xlfn.XLOOKUP(D14,HELPER!$B:$B,HELPER!$D:$D,""),"") | G14: 24 | I14: =IF(AND(H14<>"",IFERROR(_xlfn.XLOOKUP(D14,HELPER!$B:$B,HELPER!$E:$E,""),"")=""),"Missing price",IFERROR(_xlfn.XLOOKUP(D14,HELPER!$B:$B,HELPER!$E:$E,"")," ")) | J14: =IFERROR(H14*(IF(G14=8,I14*HELPER!$G$2,BOM!I14*HELPER!$G$3))," ") | L14: {=IFERROR(_xlfn.LET(_xlpm.films,Table4[Film],_xlpm.grades,Table4[Grade],_xlpm.pairs,_xlfn._xlws.FILTER(_xlfn.HSTACK(_xlpm.films,_xlpm.grades),(_xlpm.films<>"")*(TRIM(_xlpm.grades)<>"")),_xlpm.uniquePairs,_xlfn.UNIQUE(_xlpm.pairs),_xlpm.sortedPairs,_xlfn._xlws.SORT(_xlpm.uniquePairs,1,1),INDEX(_xlpm.sortedPairs,ROWS($L$2:L14),1)),"")} -> PL202.3 | M14: {=IFERROR(_xlfn.LET(_xlpm.films,Table4[Film],_xlpm.grades,Table4[Grade],_xlpm.pairs,_xlfn._xlws.FILTER(_xlfn.HSTACK(_xlpm.films,_xlpm.grades),(_xlpm.films<>"")*(TRIM(_xlpm.grades)<>"")),_xlpm.uniquePairs,_xlfn.UNIQUE(_xlpm.pairs),_xlpm.sortedPairs,_xlfn._xlws.SORT(_xlpm.uniquePairs,1,1),INDEX(_xlpm.sortedPairs,ROWS($M$2:M14),2)),"")} -> LX175 | N14: {=IF(OR(Table2[[#This Row],[Film]]="",Table2[[#This Row],[Grade]]=""),"",IFERROR(INDEX(Table4[Serial Number],MATCH(1,(Table4[Film]=Table2[[#This Row],[Film]])*(Table4[Grade]=Table2[[#This Row],[Grade]]),0)),""))} -> RMLX175 | O14: =IF(OR(Table2[[#This Row],[Film]]="",Table2[[#This Row],[Grade]]=""),"",SUMIFS(Table4[Price Calculated(€) Thickness & QTY related],Table4[Film],Table2[[#This Row],[Film]],Table4[Grade],Table2[[#This Row],[Grade]])) -> 1.50258 | Q14: {=IFERROR(INDEX(Table2[Film],MATCH(0,COUNTIF($Q$1:Q13,Table2[Film])+IF(Table2[Film]="",1,0),0)),"")} | R14: =SUMIF(Table2[Film],"TIPA 312 MFG",Table2[Price Calculated(€) Thickness & QTY related])+_xlfn.XLOOKUP("MET LUX ",HELPER!$A:$A,HELPER!$E:$E,0) -> 5.380588 | S14: =IFERROR(R14*HELPER!$AK$2," ") -> 6.2414821 | U14: PL202.3 | V14: PVOH | W14: BVE8049P | X14: BVE8049P | Y14: BVE8049P | Z14: {=SUMPRODUCT((BOM!$A$2:$A$391=U14)*(BOM!$F$2:$F$391=Y14)*BOM!$H$2:$H$391*BOM!$G$2:$G$391)/SUMPRODUCT((BOM!$A$2:$A$391=U14)*BOM!$H$2:$H$391*BOM!$G$2:$G$391)} -> 0.196 | AA14: =SUMIF(tblResinWeightedQty12[Film],tblResinWeightedQty12[[#This Row],[Film]],tblResinWeightedQty12[Weighted QTY %]) -> 1
A15: TIPA 302FG | B15: Ext. B | D15: =IF(C15="","",IFERROR(_xlfn.XLOOKUP(C15,HELPER!$A$2:$A$81,HELPER!$B$2:$B$81,""),D15)) | E15: =IFERROR(_xlfn.XLOOKUP(D15,HELPER!$B:$B,HELPER!$C:$C,""),"") | F15: =IFERROR(_xlfn.XLOOKUP(D15,HELPER!$B:$B,HELPER!$D:$D,""),"") | G15: 24 | I15: =IF(AND(H15<>"",IFERROR(_xlfn.XLOOKUP(D15,HELPER!$B:$B,HELPER!$E:$E,""),"")=""),"Missing price",IFERROR(_xlfn.XLOOKUP(D15,HELPER!$B:$B,HELPER!$E:$E,"")," ")) | J15: =IFERROR(H15*(IF(G15=8,I15*HELPER!$G$2,BOM!I15*HELPER!$G$3))," ") | L15: {=IFERROR(_xlfn.LET(_xlpm.films,Table4[Film],_xlpm.grades,Table4[Grade],_xlpm.pairs,_xlfn._xlws.FILTER(_xlfn.HSTACK(_xlpm.films,_xlpm.grades),(_xlpm.films<>"")*(TRIM(_xlpm.grades)<>"")),_xlpm.uniquePairs,_xlfn.UNIQUE(_xlpm.pairs),_xlpm.sortedPairs,_xlfn._xlws.SORT(_xlpm.uniquePairs,1,1),INDEX(_xlpm.sortedPairs,ROWS($L$2:L15),1)),"")} -> PL202.3 | M15: {=IFERROR(_xlfn.LET(_xlpm.films,Table4[Film],_xlpm.grades,Table4[Grade],_xlpm.pairs,_xlfn._xlws.FILTER(_xlfn.HSTACK(_xlpm.films,_xlpm.grades),(_xlpm.films<>"")*(TRIM(_xlpm.grades)<>"")),_xlpm.uniquePairs,_xlfn.UNIQUE(_xlpm.pairs),_xlpm.sortedPairs,_xlfn._xlws.SORT(_xlpm.uniquePairs,1,1),INDEX(_xlpm.sortedPairs,ROWS($M$2:M15),2)),"")} -> P65D | N15: {=IF(OR(Table2[[#This Row],[Film]]="",Table2[[#This Row],[Grade]]=""),"",IFERROR(INDEX(Table4[Serial Number],MATCH(1,(Table4[Film]=Table2[[#This Row],[Film]])*(Table4[Grade]=Table2[[#This Row],[Grade]]),0)),""))} -> RMP65D | O15: =IF(OR(Table2[[#This Row],[Film]]="",Table2[[#This Row],[Grade]]=""),"",SUMIFS(Table4[Price Calculated(€) Thickness & QTY related],Table4[Film],Table2[[#This Row],[Film]],Table4[Grade],Table2[[#This Row],[Grade]])) -> 0.8322 | Q15: {=IFERROR(INDEX(Table2[Film],MATCH(0,COUNTIF($Q$1:Q14,Table2[Film])+IF(Table2[Film]="",1,0),0)),"")} | R15: =SUMIF(Table2[Film],"TIPA 312 MFG",Table2[Price Calculated(€) Thickness & QTY related])+_xlfn.XLOOKUP("MET LUX ",HELPER!$A:$A,HELPER!$E:$E,0) -> 5.380588 | S15: =IFERROR(R15*HELPER!$AK$2," ") -> 6.2414821 | U15: PL202.3 | V15: PLA | W15: LX175 | X15: RMLX175 | Y15: Resin 1A | Z15: {=SUMPRODUCT((BOM!$A$2:$A$391=U15)*(BOM!$F$2:$F$391=Y15)*BOM!$H$2:$H$391*BOM!$G$2:$G$391)/SUMPRODUCT((BOM!$A$2:$A$391=U15)*BOM!$H$2:$H$391*BOM!$G$2:$G$391)} -> 0.474 | AA15: =SUMIF(tblResinWeightedQty12[Film],tblResinWeightedQty12[[#This Row],[Film]],tblResinWeightedQty12[Weighted QTY %]) -> 1
A16: TIPA 302FG | B16: Ext. B | C16: AO-PBS | D16: =IF(C16="","",IFERROR(_xlfn.XLOOKUP(C16,HELPER!$A$2:$A$81,HELPER!$B$2:$B$81,""),D16)) -> S723 | E16: =IFERROR(_xlfn.XLOOKUP(D16,HELPER!$B:$B,HELPER!$C:$C,""),"") -> RM TA45-08 S723 | F16: =IFERROR(_xlfn.XLOOKUP(D16,HELPER!$B:$B,HELPER!$D:$D,""),"") -> Resin 6 | G16: 24 | H16: 0.015 | I16: =IF(AND(H16<>"",IFERROR(_xlfn.XLOOKUP(D16,HELPER!$B:$B,HELPER!$E:$E,""),"")=""),"Missing price",IFERROR(_xlfn.XLOOKUP(D16,HELPER!$B:$B,HELPER!$E:$E,"")," ")) -> 16.16 | J16: =IFERROR(H16*(IF(G16=8,I16*HELPER!$G$2,BOM!I16*HELPER!$G$3))," ") -> 0.14544 | L16: {=IFERROR(_xlfn.LET(_xlpm.films,Table4[Film],_xlpm.grades,Table4[Grade],_xlpm.pairs,_xlfn._xlws.FILTER(_xlfn.HSTACK(_xlpm.films,_xlpm.grades),(_xlpm.films<>"")*(TRIM(_xlpm.grades)<>"")),_xlpm.uniquePairs,_xlfn.UNIQUE(_xlpm.pairs),_xlpm.sortedPairs,_xlfn._xlws.SORT(_xlpm.uniquePairs,1,1),INDEX(_xlpm.sortedPairs,ROWS($L$2:L16),1)),"")} -> PL202.3 | M16: {=IFERROR(_xlfn.LET(_xlpm.films,Table4[Film],_xlpm.grades,Table4[Grade],_xlpm.pairs,_xlfn._xlws.FILTER(_xlfn.HSTACK(_xlpm.films,_xlpm.grades),(_xlpm.films<>"")*(TRIM(_xlpm.grades)<>"")),_xlpm.uniquePairs,_xlfn.UNIQUE(_xlpm.pairs),_xlpm.sortedPairs,_xlfn._xlws.SORT(_xlpm.uniquePairs,1,1),INDEX(_xlpm.sortedPairs,ROWS($M$2:M16),2)),"")} -> S723 | N16: {=IF(OR(Table2[[#This Row],[Film]]="",Table2[[#This Row],[Grade]]=""),"",IFERROR(INDEX(Table4[Serial Number],MATCH(1,(Table4[Film]=Table2[[#This Row],[Film]])*(Table4[Grade]=Table2[[#This Row],[Grade]]),0)),""))} -> RM TA45-08 S723 | O16: =IF(OR(Table2[[#This Row],[Film]]="",Table2[[#This Row],[Grade]]=""),"",SUMIFS(Table4[Price Calculated(€) Thickness & QTY related],Table4[Film],Table2[[#This Row],[Film]],Table4[Grade],Table2[[#This Row],[Grade]])) -> 0.3232 | Q16: {=IFERROR(INDEX(Table2[Film],MATCH(0,COUNTIF($Q$1:Q15,Table2[Film])+IF(Table2[Film]="",1,0),0)),"")} | R16: =SUMIF(Table2[Film],"TIPA 312 MFG",Table2[Price Calculated(€) Thickness & QTY related])+_xlfn.XLOOKUP("MET LUX ",HELPER!$A:$A,HELPER!$E:$E,0) -> 5.380588 | S16: =IFERROR(R16*HELPER!$AK$2," ") -> 6.2414821 | U16: PL202.3 | V16: PBAT | W16: B12 | X16: RMB12 | Y16: Resin 2A | Z16: {=SUMPRODUCT((BOM!$A$2:$A$391=U16)*(BOM!$F$2:$F$391=Y16)*BOM!$H$2:$H$391*BOM!$G$2:$G$391)/SUMPRODUCT((BOM!$A$2:$A$391=U16)*BOM!$H$2:$H$391*BOM!$G$2:$G$391)} -> 0.196 | AA16: =SUMIF(tblResinWeightedQty12[Film],tblResinWeightedQty12[[#This Row],[Film]],tblResinWeightedQty12[Weighted QTY %]) -> 1
A17: TIPA 302FG | B17: Ext. B | D17: =IF(C17="","",IFERROR(_xlfn.XLOOKUP(C17,HELPER!$A$2:$A$81,HELPER!$B$2:$B$81,""),D17)) | E17: =IFERROR(_xlfn.XLOOKUP(D17,HELPER!$B:$B,HELPER!$C:$C,""),"") | F17: =IFERROR(_xlfn.XLOOKUP(D17,HELPER!$B:$B,HELPER!$D:$D,""),"") | G17: 24 | I17: =IF(AND(H17<>"",IFERROR(_xlfn.XLOOKUP(D17,HELPER!$B:$B,HELPER!$E:$E,""),"")=""),"Missing price",IFERROR(_xlfn.XLOOKUP(D17,HELPER!$B:$B,HELPER!$E:$E,"")," ")) | J17: =IFERROR(H17*(IF(G17=8,I17*HELPER!$G$2,BOM!I17*HELPER!$G$3))," ") | L17: {=IFERROR(_xlfn.LET(_xlpm.films,Table4[Film],_xlpm.grades,Table4[Grade],_xlpm.pairs,_xlfn._xlws.FILTER(_xlfn.HSTACK(_xlpm.films,_xlpm.grades),(_xlpm.films<>"")*(TRIM(_xlpm.grades)<>"")),_xlpm.uniquePairs,_xlfn.UNIQUE(_xlpm.pairs),_xlpm.sortedPairs,_xlfn._xlws.SORT(_xlpm.uniquePairs,1,1),INDEX(_xlpm.sortedPairs,ROWS($L$2:L17),1)),"")} -> PL202.3 | M17: {=IFERROR(_xlfn.LET(_xlpm.films,Table4[Film],_xlpm.grades,Table4[Grade],_xlpm.pairs,_xlfn._xlws.FILTER(_xlfn.HSTACK(_xlpm.films,_xlpm.grades),(_xlpm.films<>"")*(TRIM(_xlpm.grades)<>"")),_xlpm.uniquePairs,_xlfn.UNIQUE(_xlpm.pairs),_xlpm.sortedPairs,_xlfn._xlws.SORT(_xlpm.uniquePairs,1,1),INDEX(_xlpm.sortedPairs,ROWS($M$2:M17),2)),"")} -> BVE8049P | N17: {=IF(OR(Table2[[#This Row],[Film]]="",Table2[[#This Row],[Grade]]=""),"",IFERROR(INDEX(Table4[Serial Number],MATCH(1,(Table4[Film]=Table2[[#This Row],[Film]])*(Table4[Grade]=Table2[[#This Row],[Grade]]),0)),""))} -> BVE8049P | O17: =IF(OR(Table2[[#This Row],[Film]]="",Table2[[#This Row],[Grade]]=""),"",SUMIFS(Table4[Price Calculated(€) Thickness & QTY related],Table4[Film],Table2[[#This Row],[Film]],Table4[Grade],Table2[[#This Row],[Grade]])) -> 3.626 | Q17: {=IFERROR(INDEX(Table2[Film],MATCH(0,COUNTIF($Q$1:Q16,Table2[Film])+IF(Table2[Film]="",1,0),0)),"")} | R17: =SUMIF(Table2[Film],"TIPA 312 MFG",Table2[Price Calculated(€) Thickness & QTY related])+_xlfn.XLOOKUP("MET LUX ",HELPER!$A:$A,HELPER!$E:$E,0) -> 5.380588 | S17: =IFERROR(R17*HELPER!$AK$2," ") -> 6.2414821 | U17: PL202.3 | V17: PCL | W17: P65D | X17: RMP65D | Y17: Resin 4A | Z17: {=SUMPRODUCT((BOM!$A$2:$A$391=U17)*(BOM!$F$2:$F$391=Y17)*BOM!$H$2:$H$391*BOM!$G$2:$G$391)/SUMPRODUCT((BOM!$A$2:$A$391=U17)*BOM!$H$2:$H$391*BOM!$G$2:$G$391)} -> 0.114 | AA17: =SUMIF(tblResinWeightedQty12[Film],tblResinWeightedQty12[[#This Row],[Film]],tblResinWeightedQty12[Weighted QTY %]) -> 1
A18: TIPA 302FG | B18: Ext. B | C18: PBAT | D18: =IF(C18="","",IFERROR(_xlfn.XLOOKUP(C18,HELPER!$A$2:$A$81,HELPER!$B$2:$B$81,""),D18)) -> B12 | E18: =IFERROR(_xlfn.XLOOKUP(D18,HELPER!$B:$B,HELPER!$C:$C,""),"") -> RMB12 | F18: =IFERROR(_xlfn.XLOOKUP(D18,HELPER!$B:$B,HELPER!$D:$D,""),"") -> Resin 2A | G18: 24 | H18: 0.985 | I18: =IF(AND(H18<>"",IFERROR(_xlfn.XLOOKUP(D18,HELPER!$B:$B,HELPER!$E:$E,""),"")=""),"Missing price",IFERROR(_xlfn.XLOOKUP(D18,HELPER!$B:$B,HELPER!$E:$E,"")," ")) -> 1.81 | J18: =IFERROR(H18*(IF(G18=8,I18*HELPER!$G$2,BOM!I18*HELPER!$G$3))," ") -> 1.06971 | L18: {=IFERROR(_xlfn.LET(_xlpm.films,Table4[Film],_xlpm.grades,Table4[Grade],_xlpm.pairs,_xlfn._xlws.FILTER(_xlfn.HSTACK(_xlpm.films,_xlpm.grades),(_xlpm.films<>"")*(TRIM(_xlpm.grades)<>"")),_xlpm.uniquePairs,_xlfn.UNIQUE(_xlpm.pairs),_xlpm.sortedPairs,_xlfn._xlws.SORT(_xlpm.uniquePairs,1,1),INDEX(_xlpm.sortedPairs,ROWS($L$2:L18),1)),"")} -> PL202.3 | M18: {=IFERROR(_xlfn.LET(_xlpm.films,Table4[Film],_xlpm.grades,Table4[Grade],_xlpm.pairs,_xlfn._xlws.FILTER(_xlfn.HSTACK(_xlpm.films,_xlpm.grades),(_xlpm.films<>"")*(TRIM(_xlpm.grades)<>"")),_xlpm.uniquePairs,_xlfn.UNIQUE(_xlpm.pairs),_xlpm.sortedPairs,_xlfn._xlws.SORT(_xlpm.uniquePairs,1,1),INDEX(_xlpm.sortedPairs,ROWS($M$2:M18),2)),"")} -> B12 | N18: {=IF(OR(Table2[[#This Row],[Film]]="",Table2[[#This Row],[Grade]]=""),"",IFERROR(INDEX(Table4[Serial Number],MATCH(1,(Table4[Film]=Table2[[#This Row],[Film]])*(Table4[Grade]=Table2[[#This Row],[Grade]]),0)),""))} -> RMB12 | O18: =IF(OR(Table2[[#This Row],[Film]]="",Table2[[#This Row],[Grade]]=""),"",SUMIFS(Table4[Price Calculated(€) Thickness & QTY related],Table4[Film],Table2[[#This Row],[Film]],Table4[Grade],Table2[[#This Row],[Grade]])) -> 0.35476 | Q18: {=IFERROR(INDEX(Table2[Film],MATCH(0,COUNTIF($Q$1:Q17,Table2[Film])+IF(Table2[Film]="",1,0),0)),"")} | R18: =SUMIF(Table2[Film],"TIPA 312 MFG",Table2[Price Calculated(€) Thickness & QTY related])+_xlfn.XLOOKUP("MET LUX ",HELPER!$A:$A,HELPER!$E:$E,0) -> 5.380588 | S18: =IFERROR(R18*HELPER!$AK$2," ") -> 6.2414821 | U18: PL202.3 | V18: AO-PBS | W18: S723 | X18: RM TA45-08 S723 | Y18: Resin 6 | Z18: {=SUMPRODUCT((BOM!$A$2:$A$391=U18)*(BOM!$F$2:$F$391=Y18)*BOM!$H$2:$H$391*BOM!$G$2:$G$391)/SUMPRODUCT((BOM!$A$2:$A$391=U18)*BOM!$H$2:$H$391*BOM!$G$2:$G$391)} -> 0.02 | AA18: =SUMIF(tblResinWeightedQty12[Film],tblResinWeightedQty12[[#This Row],[Film]],tblResinWeightedQty12[Weighted QTY %]) -> 1
A19: TIPA 302FG | B19: Ext. B | D19: =IF(C19="","",IFERROR(_xlfn.XLOOKUP(C19,HELPER!$A$2:$A$81,HELPER!$B$2:$B$81,""),D19)) | E19: =IFERROR(_xlfn.XLOOKUP(D19,HELPER!$B:$B,HELPER!$C:$C,""),"") | F19: =IFERROR(_xlfn.XLOOKUP(D19,HELPER!$B:$B,HELPER!$D:$D,""),"") | G19: 24 | I19: =IF(AND(H19<>"",IFERROR(_xlfn.XLOOKUP(D19,HELPER!$B:$B,HELPER!$E:$E,""),"")=""),"Missing price",IFERROR(_xlfn.XLOOKUP(D19,HELPER!$B:$B,HELPER!$E:$E,"")," ")) | J19: =IFERROR(H19*(IF(G19=8,I19*HELPER!$G$2,BOM!I19*HELPER!$G$3))," ") | L19: {=IFERROR(_xlfn.LET(_xlpm.films,Table4[Film],_xlpm.grades,Table4[Grade],_xlpm.pairs,_xlfn._xlws.FILTER(_xlfn.HSTACK(_xlpm.films,_xlpm.grades),(_xlpm.films<>"")*(TRIM(_xlpm.grades)<>"")),_xlpm.uniquePairs,_xlfn.UNIQUE(_xlpm.pairs),_xlpm.sortedPairs,_xlfn._xlws.SORT(_xlpm.uniquePairs,1,1),INDEX(_xlpm.sortedPairs,ROWS($L$2:L19),1)),"")} -> TIPA 302FG | M19: {=IFERROR(_xlfn.LET(_xlpm.films,Table4[Film],_xlpm.grades,Table4[Grade],_xlpm.pairs,_xlfn._xlws.FILTER(_xlfn.HSTACK(_xlpm.films,_xlpm.grades),(_xlpm.films<>"")*(TRIM(_xlpm.grades)<>"")),_xlpm.uniquePairs,_xlfn.UNIQUE(_xlpm.pairs),_xlpm.sortedPairs,_xlfn._xlws.SORT(_xlpm.uniquePairs,1,1),INDEX(_xlpm.sortedPairs,ROWS($M$2:M19),2)),"")} -> FD92PM | N19: {=IF(OR(Table2[[#This Row],[Film]]="",Table2[[#This Row],[Grade]]=""),"",IFERROR(INDEX(Table4[Serial Number],MATCH(1,(Table4[Film]=Table2[[#This Row],[Film]])*(Table4[Grade]=Table2[[#This Row],[Grade]]),0)),""))} -> RMPM2 | O19: =IF(OR(Table2[[#This Row],[Film]]="",Table2[[#This Row],[Grade]]=""),"",SUMIFS(Table4[Price Calculated(€) Thickness & QTY related],Table4[Film],Table2[[#This Row],[Film]],Table4[Grade],Table2[[#This Row],[Grade]])) -> 2.2194 | Q19: {=IFERROR(INDEX(Table2[Film],MATCH(0,COUNTIF($Q$1:Q18,Table2[Film])+IF(Table2[Film]="",1,0),0)),"")} | R19: =SUMIF(Table2[Film],"TIPA 312 MFG",Table2[Price Calculated(€) Thickness & QTY related])+_xlfn.XLOOKUP("MET LUX ",HELPER!$A:$A,HELPER!$E:$E,0) -> 5.380588 | S19: =IFERROR(R19*HELPER!$AK$2," ") -> 6.2414821 | U19: TIPA 302FG | V19: PLA | W19: LX175 | X19: RMLX175 | Y19: Resin 1A | Z19: {=SUMPRODUCT((BOM!$A$2:$A$391=U19)*(BOM!$F$2:$F$391=Y19)*BOM!$H$2:$H$391*BOM!$G$2:$G$391)/SUMPRODUCT((BOM!$A$2:$A$391=U19)*BOM!$H$2:$H$391*BOM!$G$2:$G$391)} -> 0.0576 | AA19: =SUMIF(tblResinWeightedQty12[Film],tblResinWeightedQty12[[#This Row],[Film]],tblResinWeightedQty12[Weighted QTY %]) -> 1
A20: TIPA 302FG | B20: Ext. B | D20: =IF(C20="","",IFERROR(_xlfn.XLOOKUP(C20,HELPER!$A$2:$A$81,HELPER!$B$2:$B$81,""),D20)) | E20: =IFERROR(_xlfn.XLOOKUP(D20,HELPER!$B:$B,HELPER!$C:$C,""),"") | F20: =IFERROR(_xlfn.XLOOKUP(D20,HELPER!$B:$B,HELPER!$D:$D,""),"") | G20: 24 | I20: =IF(AND(H20<>"",IFERROR(_xlfn.XLOOKUP(D20,HELPER!$B:$B,HELPER!$E:$E,""),"")=""),"Missing price",IFERROR(_xlfn.XLOOKUP(D20,HELPER!$B:$B,HELPER!$E:$E,"")," ")) | J20: =IFERROR(H20*(IF(G20=8,I20*HELPER!$G$2,BOM!I20*HELPER!$G$3))," ") | L20: {=IFERROR(_xlfn.LET(_xlpm.films,Table4[Film],_xlpm.grades,Table4[Grade],_xlpm.pairs,_xlfn._xlws.FILTER(_xlfn.HSTACK(_xlpm.films,_xlpm.grades),(_xlpm.films<>"")*(TRIM(_xlpm.grades)<>"")),_xlpm.uniquePairs,_xlfn.UNIQUE(_xlpm.pairs),_xlpm.sortedPairs,_xlfn._xlws.SORT(_xlpm.uniquePairs,1,1),INDEX(_xlpm.sortedPairs,ROWS($L$2:L20),1)),"")} -> TIPA 302FG | M20: {=IFERROR(_xlfn.LET(_xlpm.films,Table4[Film],_xlpm.grades,Table4[Grade],_xlpm.pairs,_xlfn._xlws.FILTER(_xlfn.HSTACK(_xlpm.films,_xlpm.grades),(_xlpm.films<>"")*(TRIM(_xlpm.grades)<>"")),_xlpm.uniquePairs,_xlfn.UNIQUE(_xlpm.pairs),_xlpm.sortedPairs,_xlfn._xlws.SORT(_xlpm.uniquePairs,1,1),INDEX(_xlpm.sortedPairs,ROWS($M$2:M20),2)),"")} -> LX175 | N20: {=IF(OR(Table2[[#This Row],[Film]]="",Table2[[#This Row],[Grade]]=""),"",IFERROR(INDEX(Table4[Serial Number],MATCH(1,(Table4[Film]=Table2[[#This Row],[Film]])*(Table4[Grade]=Table2[[#This Row],[Grade]]),0)),""))} -> RMLX175 | O20: =IF(OR(Table2[[#This Row],[Film]]="",Table2[[#This Row],[Grade]]=""),"",SUMIFS(Table4[Price Calculated(€) Thickness & QTY related],Table4[Film],Table2[[#This Row],[Film]],Table4[Grade],Table2[[#This Row],[Grade]])) -> 0.182592 | Q20: {=IFERROR(INDEX(Table2[Film],MATCH(0,COUNTIF($Q$1:Q19,Table2[Film])+IF(Table2[Film]="",1,0),0)),"")} | R20: =SUMIF(Table2[Film],"TIPA 312 MFG",Table2[Price Calculated(€) Thickness & QTY related])+_xlfn.XLOOKUP("MET LUX ",HELPER!$A:$A,HELPER!$E:$E,0) -> 5.380588 | S20: =IFERROR(R20*HELPER!$AK$2," ") -> 6.2414821 | U20: TIPA 302FG | V20: PBAT | W20: B12 | X20: RMB12 | Y20: Resin 2A | Z20: {=SUMPRODUCT((BOM!$A$2:$A$391=U20)*(BOM!$F$2:$F$391=Y20)*BOM!$H$2:$H$391*BOM!$G$2:$G$391)/SUMPRODUCT((BOM!$A$2:$A$391=U20)*BOM!$H$2:$H$391*BOM!$G$2:$G$391)} -> 0.591 | AA20: =SUMIF(tblResinWeightedQty12[Film],tblResinWeightedQty12[[#This Row],[Film]],tblResinWeightedQty12[Weighted QTY %]) -> 1
A21: TIPA 302FG | B21: Ext. B | D21: =IF(C21="","",IFERROR(_xlfn.XLOOKUP(C21,HELPER!$A$2:$A$81,HELPER!$B$2:$B$81,""),D21)) | E21: =IFERROR(_xlfn.XLOOKUP(D21,HELPER!$B:$B,HELPER!$C:$C,""),"") | F21: =IFERROR(_xlfn.XLOOKUP(D21,HELPER!$B:$B,HELPER!$D:$D,""),"") | G21: 24 | I21: =IF(AND(H21<>"",IFERROR(_xlfn.XLOOKUP(D21,HELPER!$B:$B,HELPER!$E:$E,""),"")=""),"Missing price",IFERROR(_xlfn.XLOOKUP(D21,HELPER!$B:$B,HELPER!$E:$E,"")," ")) | J21: =IFERROR(H21*(IF(G21=8,I21*HELPER!$G$2,BOM!I21*HELPER!$G$3))," ") | L21: {=IFERROR(_xlfn.LET(_xlpm.films,Table4[Film],_xlpm.grades,Table4[Grade],_xlpm.pairs,_xlfn._xlws.FILTER(_xlfn.HSTACK(_xlpm.films,_xlpm.grades),(_xlpm.films<>"")*(TRIM(_xlpm.grades)<>"")),_xlpm.uniquePairs,_xlfn.UNIQUE(_xlpm.pairs),_xlpm.sortedPairs,_xlfn._xlws.SORT(_xlpm.uniquePairs,1,1),INDEX(_xlpm.sortedPairs,ROWS($L$2:L21),1)),"")} -> TIPA 302FG | M21: {=IFERROR(_xlfn.LET(_xlpm.films,Table4[Film],_xlpm.grades,Table4[Grade],_xlpm.pairs,_xlfn._xlws.FILTER(_xlfn.HSTACK(_xlpm.films,_xlpm.grades),(_xlpm.films<>"")*(TRIM(_xlpm.grades)<>"")),_xlpm.uniquePairs,_xlfn.UNIQUE(_xlpm.pairs),_xlpm.sortedPairs,_xlfn._xlws.SORT(_xlpm.uniquePairs,1,1),INDEX(_xlpm.sortedPairs,ROWS($M$2:M21),2)),"")} -> KAB59A | N21: {=IF(OR(Table2[[#This Row],[Film]]="",Table2[[#This Row],[Grade]]=""),"",IFERROR(INDEX(Table4[Serial Number],MATCH(1,(Table4[Film]=Table2[[#This Row],[Film]])*(Table4[Grade]=Table2[[#This Row],[Grade]]),0)),""))} -> RM A KAB59A | O21: =IF(OR(Table2[[#This Row],[Film]]="",Table2[[#This Row],[Grade]]=""),"",SUMIFS(Table4[Price Calculated(€) Thickness & QTY related],Table4[Film],Table2[[#This Row],[Film]],Table4[Grade],Table2[[#This Row],[Grade]])) -> 0.0453 | Q21: {=IFERROR(INDEX(Table2[Film],MATCH(0,COUNTIF($Q$1:Q20,Table2[Film])+IF(Table2[Film]="",1,0),0)),"")} | R21: =SUMIF(Table2[Film],"TIPA 312 MFG",Table2[Price Calculated(€) Thickness & QTY related])+_xlfn.XLOOKUP("MET LUX ",HELPER!$A:$A,HELPER!$E:$E,0) -> 5.380588 | S21: =IFERROR(R21*HELPER!$AK$2," ") -> 6.2414821 | U21: TIPA 302FG | V21: AO-PBS | W21: S723 | X21: RM TA45-08 S723 | Y21: Resin 6 | Z21: {=SUMPRODUCT((BOM!$A$2:$A$391=U21)*(BOM!$F$2:$F$391=Y21)*BOM!$H$2:$H$391*BOM!$G$2:$G$391)/SUMPRODUCT((BOM!$A$2:$A$391=U21)*BOM!$H$2:$H$391*BOM!$G$2:$G$391)} -> 0.015 | AA21: =SUMIF(tblResinWeightedQty12[Film],tblResinWeightedQty12[[#This Row],[Film]],tblResinWeightedQty12[Weighted QTY %]) -> 1
A22: TIPA 302FG | B22: Ext. C (In) | C22: PBSA | D22: =IF(C22="","",IFERROR(_xlfn.XLOOKUP(C22,HELPER!$A$2:$A$81,HELPER!$B$2:$B$81,""),D22)) -> FD92PM | E22: =IFERROR(_xlfn.XLOOKUP(D22,HELPER!$B:$B,HELPER!$C:$C,""),"") -> RMPM2 | F22: =IFERROR(_xlfn.XLOOKUP(D22,HELPER!$B:$B,HELPER!$D:$D,""),"") -> Resin 9C | G22: 8 | H22: 0.818 | I22: =IF(AND(H22<>"",IFERROR(_xlfn.XLOOKUP(D22,HELPER!$B:$B,HELPER!$E:$E,""),"")=""),"Missing price",IFERROR(_xlfn.XLOOKUP(D22,HELPER!$B:$B,HELPER!$E:$E,"")," ")) -> 6.75 | J22: =IFERROR(H22*(IF(G22=8,I22*HELPER!$G$2,BOM!I22*HELPER!$G$3))," ") -> 1.1043 | L22: {=IFERROR(_xlfn.LET(_xlpm.films,Table4[Film],_xlpm.grades,Table4[Grade],_xlpm.pairs,_xlfn._xlws.FILTER(_xlfn.HSTACK(_xlpm.films,_xlpm.grades),(_xlpm.films<>"")*(TRIM(_xlpm.grades)<>"")),_xlpm.uniquePairs,_xlfn.UNIQUE(_xlpm.pairs),_xlpm.sortedPairs,_xlfn._xlws.SORT(_xlpm.uniquePairs,1,1),INDEX(_xlpm.sortedPairs,ROWS($L$2:L22),1)),"")} -> TIPA 302FG | M22: {=IFERROR(_xlfn.LET(_xlpm.films,Table4[Film],_xlpm.grades,Table4[Grade],_xlpm.pairs,_xlfn._xlws.FILTER(_xlfn.HSTACK(_xlpm.films,_xlpm.grades),(_xlpm.films<>"")*(TRIM(_xlpm.grades)<>"")),_xlpm.uniquePairs,_xlfn.UNIQUE(_xlpm.pairs),_xlpm.sortedPairs,_xlfn._xlws.SORT(_xlpm.uniquePairs,1,1),INDEX(_xlpm.sortedPairs,ROWS($M$2:M22),2)),"")} -> S723 | N22: {=IF(OR(Table2[[#This Row],[Film]]="",Table2[[#This Row],[Grade]]=""),"",IFERROR(INDEX(Table4[Serial Number],MATCH(1,(Table4[Film]=Table2[[#This Row],[Film]])*(Table4[Grade]=Table2[[#This Row],[Grade]]),0)),""))} -> RM TA45-08 S723 | O22: =IF(OR(Table2[[#This Row],[Film]]="",Table2[[#This Row],[Grade]]=""),"",SUMIFS(Table4[Price Calculated(€) Thickness & QTY related],Table4[Film],Table2[[#This Row],[Film]],Table4[Grade],Table2[[#This Row],[Grade]])) -> 0.2424 | Q22: {=IFERROR(INDEX(Table2[Film],MATCH(0,COUNTIF($Q$1:Q21,Table2[Film])+IF(Table2[Film]="",1,0),0)),"")} | R22: =SUMIF(Table2[Film],"TIPA 312 MFG",Table2[Price Calculated(€) Thickness & QTY related])+_xlfn.XLOOKUP("MET LUX ",HELPER!$A:$A,HELPER!$E:$E,0) -> 5.380588 | S22: =IFERROR(R22*HELPER!$AK$2," ") -> 6.2414821 | U22: TIPA 302FG | V22: SLAB-PBSA | W22: S724 | X22: RM TA45-08 S724 | Y22: Resin 7 | Z22: {=SUMPRODUCT((BOM!$A$2:$A$391=U22)*(BOM!$F$2:$F$391=Y22)*BOM!$H$2:$H$391*BOM!$G$2:$G$391)/SUMPRODUCT((BOM!$A$2:$A$391=U22)*BOM!$H$2:$H$391*BOM!$G$2:$G$391)} -> 0.0016 | AA22: =SUMIF(tblResinWeightedQty12[Film],tblResinWeightedQty12[[#This Row],[Film]],tblResinWeightedQty12[Weighted QTY %]) -> 1
A23: TIPA 302FG | B23: Ext. C (In) | C23: PLA | D23: =IF(C23="","",IFERROR(_xlfn.XLOOKUP(C23,HELPER!$A$2:$A$81,HELPER!$B$2:$B$81,""),D23)) -> LX175 | E23: =IFERROR(_xlfn.XLOOKUP(D23,HELPER!$B:$B,HELPER!$C:$C,""),"") -> RMLX175 | F23: =IFERROR(_xlfn.XLOOKUP(D23,HELPER!$B:$B,HELPER!$D:$D,""),"") -> Resin 1A | G23: 8 | H23: 0.144 | I23: =IF(AND(H23<>"",IFERROR(_xlfn.XLOOKUP(D23,HELPER!$B:$B,HELPER!$E:$E,""),"")=""),"Missing price",IFERROR(_xlfn.XLOOKUP(D23,HELPER!$B:$B,HELPER!$E:$E,"")," ")) -> 3.17 | J23: =IFERROR(H23*(IF(G23=8,I23*HELPER!$G$2,BOM!I23*HELPER!$G$3))," ") -> 0.091296 | L23: {=IFERROR(_xlfn.LET(_xlpm.films,Table4[Film],_xlpm.grades,Table4[Grade],_xlpm.pairs,_xlfn._xlws.FILTER(_xlfn.HSTACK(_xlpm.films,_xlpm.grades),(_xlpm.films<>"")*(TRIM(_xlpm.grades)<>"")),_xlpm.uniquePairs,_xlfn.UNIQUE(_xlpm.pairs),_xlpm.sortedPairs,_xlfn._xlws.SORT(_xlpm.uniquePairs,1,1),INDEX(_xlpm.sortedPairs,ROWS($L$2:L23),1)),"")} -> TIPA 302FG | M23: {=IFERROR(_xlfn.LET(_xlpm.films,Table4[Film],_xlpm.grades,Table4[Grade],_xlpm.pairs,_xlfn._xlws.FILTER(_xlfn.HSTACK(_xlpm.films,_xlpm.grades),(_xlpm.films<>"")*(TRIM(_xlpm.grades)<>"")),_xlpm.uniquePairs,_xlfn.UNIQUE(_xlpm.pairs),_xlpm.sortedPairs,_xlfn._xlws.SORT(_xlpm.uniquePairs,1,1),INDEX(_xlpm.sortedPairs,ROWS($M$2:M23),2)),"")} -> B12 | N23: {=IF(OR(Table2[[#This Row],[Film]]="",Table2[[#This Row],[Grade]]=""),"",IFERROR(INDEX(Table4[Serial Number],MATCH(1,(Table4[Film]=Table2[[#This Row],[Film]])*(Table4[Grade]=Table2[[#This Row],[Grade]]),0)),""))} -> RMB12 | O23: =IF(OR(Table2[[#This Row],[Film]]="",Table2[[#This Row],[Grade]]=""),"",SUMIFS(Table4[Price Calculated(€) Thickness & QTY related],Table4[Film],Table2[[#This Row],[Film]],Table4[Grade],Table2[[#This Row],[Grade]])) -> 1.06971 | Q23: {=IFERROR(INDEX(Table2[Film],MATCH(0,COUNTIF($Q$1:Q22,Table2[Film])+IF(Table2[Film]="",1,0),0)),"")} | R23: =SUMIF(Table2[Film],"TIPA 312 MFG",Table2[Price Calculated(€) Thickness & QTY related])+_xlfn.XLOOKUP("MET LUX ",HELPER!$A:$A,HELPER!$E:$E,0) -> 5.380588 | S23: =IFERROR(R23*HELPER!$AK$2," ") -> 6.2414821 | U23: TIPA 302FG | V23: AB-PLA | W23: KAB59A | X23: RM A KAB59A | Y23: Resin 8 | Z23: {=SUMPRODUCT((BOM!$A$2:$A$391=U23)*(BOM!$F$2:$F$391=Y23)*BOM!$H$2:$H$391*BOM!$G$2:$G$391)/SUMPRODUCT((BOM!$A$2:$A$391=U23)*BOM!$H$2:$H$391*BOM!$G$2:$G$391)} -> 0.006 | AA23: =SUMIF(tblResinWeightedQty12[Film],tblResinWeightedQty12[[#This Row],[Film]],tblResinWeightedQty12[Weighted QTY %]) -> 1
A24: TIPA 302FG | B24: Ext. C (In) | C24: AB-PLA | D24: =IF(C24="","",IFERROR(_xlfn.XLOOKUP(C24,HELPER!$A$2:$A$81,HELPER!$B$2:$B$81,""),D24)) -> KAB59A | E24: =IFERROR(_xlfn.XLOOKUP(D24,HELPER!$B:$B,HELPER!$C:$C,""),"") -> RM A KAB59A | F24: =IFERROR(_xlfn.XLOOKUP(D24,HELPER!$B:$B,HELPER!$D:$D,""),"") -> Resin 8 | G24: 8 | H24: 0.015 | I24: =IF(AND(H24<>"",IFERROR(_xlfn.XLOOKUP(D24,HELPER!$B:$B,HELPER!$E:$E,""),"")=""),"Missing price",IFERROR(_xlfn.XLOOKUP(D24,HELPER!$B:$B,HELPER!$E:$E,"")," ")) -> 7.55 | J24: =IFERROR(H24*(IF(G24=8,I24*HELPER!$G$2,BOM!I24*HELPER!$G$3))," ") -> 0.02265 | L24: {=IFERROR(_xlfn.LET(_xlpm.films,Table4[Film],_xlpm.grades,Table4[Grade],_xlpm.pairs,_xlfn._xlws.FILTER(_xlfn.HSTACK(_xlpm.films,_xlpm.grades),(_xlpm.films<>"")*(TRIM(_xlpm.grades)<>"")),_xlpm.uniquePairs,_xlfn.UNIQUE(_xlpm.pairs),_xlpm.sortedPairs,_xlfn._xlws.SORT(_xlpm.uniquePairs,1,1),INDEX(_xlpm.sortedPairs,ROWS($L$2:L24),1)),"")} -> TIPA 302FG | M24: {=IFERROR(_xlfn.LET(_xlpm.films,Table4[Film],_xlpm.grades,Table4[Grade],_xlpm.pairs,_xlfn._xlws.FILTER(_xlfn.HSTACK(_xlpm.films,_xlpm.grades),(_xlpm.films<>"")*(TRIM(_xlpm.grades)<>"")),_xlpm.uniquePairs,_xlfn.UNIQUE(_xlpm.pairs),_xlpm.sortedPairs,_xlfn._xlws.SORT(_xlpm.uniquePairs,1,1),INDEX(_xlpm.sortedPairs,ROWS($M$2:M24),2)),"")} -> S724 | N24: {=IF(OR(Table2[[#This Row],[Film]]="",Table2[[#This Row],[Grade]]=""),"",IFERROR(INDEX(Table4[Serial Number],MATCH(1,(Table4[Film]=Table2[[#This Row],[Film]])*(Table4[Grade]=Table2[[#This Row],[Grade]]),0)),""))} -> RM TA45-08 S724 | O24: =IF(OR(Table2[[#This Row],[Film]]="",Table2[[#This Row],[Grade]]=""),"",SUMIFS(Table4[Price Calculated(€) Thickness & QTY related],Table4[Film],Table2[[#This Row],[Film]],Table4[Grade],Table2[[#This Row],[Grade]])) -> 0.02352 | Q24: {=IFERROR(INDEX(Table2[Film],MATCH(0,COUNTIF($Q$1:Q23,Table2[Film])+IF(Table2[Film]="",1,0),0)),"")} | R24: =SUMIF(Table2[Film],"TIPA 312 MFG",Table2[Price Calculated(€) Thickness & QTY related])+_xlfn.XLOOKUP("MET LUX ",HELPER!$A:$A,HELPER!$E:$E,0) -> 5.380588 | S24: =IFERROR(R24*HELPER!$AK$2," ") -> 6.2414821 | U24: TIPA 302FG | V24: PBSA | W24: FD92PM | X24: RMPM2 | Y24: Resin 9C | Z24: {=SUMPRODUCT((BOM!$A$2:$A$391=U24)*(BOM!$F$2:$F$391=Y24)*BOM!$H$2:$H$391*BOM!$G$2:$G$391)/SUMPRODUCT((BOM!$A$2:$A$391=U24)*BOM!$H$2:$H$391*BOM!$G$2:$G$391)} -> 0.3288 | AA24: =SUMIF(tblResinWeightedQty12[Film],tblResinWeightedQty12[[#This Row],[Film]],tblResinWeightedQty12[Weighted QTY %]) -> 1
A25: TIPA 302FG | B25: Ext. C (In) | C25: AO-PBS | D25: =IF(C25="","",IFERROR(_xlfn.XLOOKUP(C25,HELPER!$A$2:$A$81,HELPER!$B$2:$B$81,""),D25)) -> S723 | E25: =IFERROR(_xlfn.XLOOKUP(D25,HELPER!$B:$B,HELPER!$C:$C,""),"") -> RM TA45-08 S723 | F25: =IFERROR(_xlfn.XLOOKUP(D25,HELPER!$B:$B,HELPER!$D:$D,""),"") -> Resin 6 | G25: 8 | H25: 0.015 | I25: =IF(AND(H25<>"",IFERROR(_xlfn.XLOOKUP(D25,HELPER!$B:$B,HELPER!$E:$E,""),"")=""),"Missing price",IFERROR(_xlfn.XLOOKUP(D25,HELPER!$B:$B,HELPER!$E:$E,"")," ")) -> 16.16 | J25: =IFERROR(H25*(IF(G25=8,I25*HELPER!$G$2,BOM!I25*HELPER!$G$3))," ") -> 0.04848 | L25: {=IFERROR(_xlfn.LET(_xlpm.films,Table4[Film],_xlpm.grades,Table4[Grade],_xlpm.pairs,_xlfn._xlws.FILTER(_xlfn.HSTACK(_xlpm.films,_xlpm.grades),(_xlpm.films<>"")*(TRIM(_xlpm.grades)<>"")),_xlpm.uniquePairs,_xlfn.UNIQUE(_xlpm.pairs),_xlpm.sortedPairs,_xlfn._xlws.SORT(_xlpm.uniquePairs,1,1),INDEX(_xlpm.sortedPairs,ROWS($L$2:L25),1)),"")} -> TIPA 302FG W | M25: {=IFERROR(_xlfn.LET(_xlpm.films,Table4[Film],_xlpm.grades,Table4[Grade],_xlpm.pairs,_xlfn._xlws.FILTER(_xlfn.HSTACK(_xlpm.films,_xlpm.grades),(_xlpm.films<>"")*(TRIM(_xlpm.grades)<>"")),_xlpm.uniquePairs,_xlfn.UNIQUE(_xlpm.pairs),_xlpm.sortedPairs,_xlfn._xlws.SORT(_xlpm.uniquePairs,1,1),INDEX(_xlpm.sortedPairs,ROWS($M$2:M25),2)),"")} -> FD92PM | N25: {=IF(OR(Table2[[#This Row],[Film]]="",Table2[[#This Row],[Grade]]=""),"",IFERROR(INDEX(Table4[Serial Number],MATCH(1,(Table4[Film]=Table2[[#This Row],[Film]])*(Table4[Grade]=Table2[[#This Row],[Grade]]),0)),""))} -> RMPM2 | O25: =IF(OR(Table2[[#This Row],[Film]]="",Table2[[#This Row],[Grade]]=""),"",SUMIFS(Table4[Price Calculated(€) Thickness & QTY related],Table4[Film],Table2[[#This Row],[Film]],Table4[Grade],Table2[[#This Row],[Grade]])) -> 2.187 | Q25: {=IFERROR(INDEX(Table2[Film],MATCH(0,COUNTIF($Q$1:Q24,Table2[Film])+IF(Table2[Film]="",1,0),0)),"")} | R25: =SUMIF(Table2[Film],"TIPA 312 MFG",Table2[Price Calculated(€) Thickness & QTY related])+_xlfn.XLOOKUP("MET LUX ",HELPER!$A:$A,HELPER!$E:$E,0) -> 5.380588 | S25: =IFERROR(R25*HELPER!$AK$2," ") -> 6.2414821 | U25: TIPA 302FG W | V25: ECOMP WHITE | W25: RM WHITE BIO8153 | X25: RM WHITE BIO8153 | Y25: Resin 13B | Z25: {=SUMPRODUCT((BOM!$A$2:$A$391=U25)*(BOM!$F$2:$F$391=Y25)*BOM!$H$2:$H$391*BOM!$G$2:$G$391)/SUMPRODUCT((BOM!$A$2:$A$391=U25)*BOM!$H$2:$H$391*BOM!$G$2:$G$391)} -> 0.06 | AA25: =SUMIF(tblResinWeightedQty12[Film],tblResinWeightedQty12[[#This Row],[Film]],tblResinWeightedQty12[Weighted QTY %]) -> 1
A26: TIPA 302FG | B26: Ext. C (In) | C26: SLAB-PBSA | D26: =IF(C26="","",IFERROR(_xlfn.XLOOKUP(C26,HELPER!$A$2:$A$81,HELPER!$B$2:$B$81,""),D26)) -> S724 | E26: =IFERROR(_xlfn.XLOOKUP(D26,HELPER!$B:$B,HELPER!$C:$C,""),"") -> RM TA45-08 S724 | F26: =IFERROR(_xlfn.XLOOKUP(D26,HELPER!$B:$B,HELPER!$D:$D,""),"") -> Resin 7 | G26: 8 | H26: 0.008 | I26: =IF(AND(H26<>"",IFERROR(_xlfn.XLOOKUP(D26,HELPER!$B:$B,HELPER!$E:$E,""),"")=""),"Missing price",IFERROR(_xlfn.XLOOKUP(D26,HELPER!$B:$B,HELPER!$E:$E,"")," ")) -> 14.7 | J26: =IFERROR(H26*(IF(G26=8,I26*HELPER!$G$2,BOM!I26*HELPER!$G$3))," ") -> 0.02352 | L26: {=IFERROR(_xlfn.LET(_xlpm.films,Table4[Film],_xlpm.grades,Table4[Grade],_xlpm.pairs,_xlfn._xlws.FILTER(_xlfn.HSTACK(_xlpm.films,_xlpm.grades),(_xlpm.films<>"")*(TRIM(_xlpm.grades)<>"")),_xlpm.uniquePairs,_xlfn.UNIQUE(_xlpm.pairs),_xlpm.sortedPairs,_xlfn._xlws.SORT(_xlpm.uniquePairs,1,1),INDEX(_xlpm.sortedPairs,ROWS($L$2:L26),1)),"")} -> TIPA 302FG W | M26: {=IFERROR(_xlfn.LET(_xlpm.films,Table4[Film],_xlpm.grades,Table4[Grade],_xlpm.pairs,_xlfn._xlws.FILTER(_xlfn.HSTACK(_xlpm.films,_xlpm.grades),(_xlpm.films<>"")*(TRIM(_xlpm.grades)<>"")),_xlpm.uniquePairs,_xlfn.UNIQUE(_xlpm.pairs),_xlpm.sortedPairs,_xlfn._xlws.SORT(_xlpm.uniquePairs,1,1),INDEX(_xlpm.sortedPairs,ROWS($M$2:M26),2)),"")} -> LX175 | N26: {=IF(OR(Table2[[#This Row],[Film]]="",Table2[[#This Row],[Grade]]=""),"",IFERROR(INDEX(Table4[Serial Number],MATCH(1,(Table4[Film]=Table2[[#This Row],[Film]])*(Table4[Grade]=Table2[[#This Row],[Grade]]),0)),""))} -> RMLX175 | O26: =IF(OR(Table2[[#This Row],[Film]]="",Table2[[#This Row],[Grade]]=""),"",SUMIFS(Table4[Price Calculated(€) Thickness & QTY related],Table4[Film],Table2[[#This Row],[Film]],Table4[Grade],Table2[[#This Row],[Grade]])) -> 0.182592 | Q26: {=IFERROR(INDEX(Table2[Film],MATCH(0,COUNTIF($Q$1:Q25,Table2[Film])+IF(Table2[Film]="",1,0),0)),"")} | R26: =SUMIF(Table2[Film],"TIPA 312 MFG",Table2[Price Calculated(€) Thickness & QTY related])+_xlfn.XLOOKUP("MET LUX ",HELPER!$A:$A,HELPER!$E:$E,0) -> 5.380588 | S26: =IFERROR(R26*HELPER!$AK$2," ") -> 6.2414821 | U26: TIPA 302FG W | V26: PLA | W26: LX175 | X26: RMLX175 | Y26: Resin 1A | Z26: {=SUMPRODUCT((BOM!$A$2:$A$391=U26)*(BOM!$F$2:$F$391=Y26)*BOM!$H$2:$H$391*BOM!$G$2:$G$391)/SUMPRODUCT((BOM!$A$2:$A$391=U26)*BOM!$H$2:$H$391*BOM!$G$2:$G$391)} -> 0.0576 | AA26: =SUMIF(tblResinWeightedQty12[Film],tblResinWeightedQty12[[#This Row],[Film]],tblResinWeightedQty12[Weighted QTY %]) -> 1
A27: TIPA 302FG | B27: Ext. C (In) | D27: =IF(C27="","",IFERROR(_xlfn.XLOOKUP(C27,HELPER!$A$2:$A$81,HELPER!$B$2:$B$81,""),D27)) | E27: =IFERROR(_xlfn.XLOOKUP(D27,HELPER!$B:$B,HELPER!$C:$C,""),"") | F27: =IFERROR(_xlfn.XLOOKUP(D27,HELPER!$B:$B,HELPER!$D:$D,""),"") | G27: 8 | I27: =IF(AND(H27<>"",IFERROR(_xlfn.XLOOKUP(D27,HELPER!$B:$B,HELPER!$E:$E,""),"")=""),"Missing price",IFERROR(_xlfn.XLOOKUP(D27,HELPER!$B:$B,HELPER!$E:$E,"")," ")) | J27: =IFERROR(H27*(IF(G27=8,I27*HELPER!$G$2,BOM!I27*HELPER!$G$3))," ") | L27: {=IFERROR(_xlfn.LET(_xlpm.films,Table4[Film],_xlpm.grades,Table4[Grade],_xlpm.pairs,_xlfn._xlws.FILTER(_xlfn.HSTACK(_xlpm.films,_xlpm.grades),(_xlpm.films<>"")*(TRIM(_xlpm.grades)<>"")),_xlpm.uniquePairs,_xlfn.UNIQUE(_xlpm.pairs),_xlpm.sortedPairs,_xlfn._xlws.SORT(_xlpm.uniquePairs,1,1),INDEX(_xlpm.sortedPairs,ROWS($L$2:L27),1)),"")} -> TIPA 302FG W | M27: {=IFERROR(_xlfn.LET(_xlpm.films,Table4[Film],_xlpm.grades,Table4[Grade],_xlpm.pairs,_xlfn._xlws.FILTER(_xlfn.HSTACK(_xlpm.films,_xlpm.grades),(_xlpm.films<>"")*(TRIM(_xlpm.grades)<>"")),_xlpm.uniquePairs,_xlfn.UNIQUE(_xlpm.pairs),_xlpm.sortedPairs,_xlfn._xlws.SORT(_xlpm.uniquePairs,1,1),INDEX(_xlpm.sortedPairs,ROWS($M$2:M27),2)),"")} -> KAB59A | N27: {=IF(OR(Table2[[#This Row],[Film]]="",Table2[[#This Row],[Grade]]=""),"",IFERROR(INDEX(Table4[Serial Number],MATCH(1,(Table4[Film]=Table2[[#This Row],[Film]])*(Table4[Grade]=Table2[[#This Row],[Grade]]),0)),""))} -> RM A KAB59A | O27: =IF(OR(Table2[[#This Row],[Film]]="",Table2[[#This Row],[Grade]]=""),"",SUMIFS(Table4[Price Calculated(€) Thickness & QTY related],Table4[Film],Table2[[#This Row],[Film]],Table4[Grade],Table2[[#This Row],[Grade]])) -> 0.0453 | Q27: {=IFERROR(INDEX(Table2[Film],MATCH(0,COUNTIF($Q$1:Q26,Table2[Film])+IF(Table2[Film]="",1,0),0)),"")} | R27: =SUMIF(Table2[Film],"TIPA 312 MFG",Table2[Price Calculated(€) Thickness & QTY related])+_xlfn.XLOOKUP("MET LUX ",HELPER!$A:$A,HELPER!$E:$E,0) -> 5.380588 | S27: =IFERROR(R27*HELPER!$AK$2," ") -> 6.2414821 | U27: TIPA 302FG W | V27: PBAT | W27: B12 | X27: RMB12 | Y27: Resin 2A | Z27: {=SUMPRODUCT((BOM!$A$2:$A$391=U27)*(BOM!$F$2:$F$391=Y27)*BOM!$H$2:$H$391*BOM!$G$2:$G$391)/SUMPRODUCT((BOM!$A$2:$A$391=U27)*BOM!$H$2:$H$391*BOM!$G$2:$G$391)} -> 0.531 | AA27: =SUMIF(tblResinWeightedQty12[Film],tblResinWeightedQty12[[#This Row],[Film]],tblResinWeightedQty12[Weighted QTY %]) -> 1
A28: TIPA 302FG | B28: Ext. C (In) | D28: =IF(C28="","",IFERROR(_xlfn.XLOOKUP(C28,HELPER!$A$2:$A$81,HELPER!$B$2:$B$81,""),D28)) | E28: =IFERROR(_xlfn.XLOOKUP(D28,HELPER!$B:$B,HELPER!$C:$C,""),"") | F28: =IFERROR(_xlfn.XLOOKUP(D28,HELPER!$B:$B,HELPER!$D:$D,""),"") | G28: 8 | I28: =IF(AND(H28<>"",IFERROR(_xlfn.XLOOKUP(D28,HELPER!$B:$B,HELPER!$E:$E,""),"")=""),"Missing price",IFERROR(_xlfn.XLOOKUP(D28,HELPER!$B:$B,HELPER!$E:$E,"")," ")) | J28: =IFERROR(H28*(IF(G28=8,I28*HELPER!$G$2,BOM!I28*HELPER!$G$3))," ") | L28: {=IFERROR(_xlfn.LET(_xlpm.films,Table4[Film],_xlpm.grades,Table4[Grade],_xlpm.pairs,_xlfn._xlws.FILTER(_xlfn.HSTACK(_xlpm.films,_xlpm.grades),(_xlpm.films<>"")*(TRIM(_xlpm.grades)<>"")),_xlpm.uniquePairs,_xlfn.UNIQUE(_xlpm.pairs),_xlpm.sortedPairs,_xlfn._xlws.SORT(_xlpm.uniquePairs,1,1),INDEX(_xlpm.sortedPairs,ROWS($L$2:L28),1)),"")} -> TIPA 302FG W | M28: {=IFERROR(_xlfn.LET(_xlpm.films,Table4[Film],_xlpm.grades,Table4[Grade],_xlpm.pairs,_xlfn._xlws.FILTER(_xlfn.HSTACK(_xlpm.films,_xlpm.grades),(_xlpm.films<>"")*(TRIM(_xlpm.grades)<>"")),_xlpm.uniquePairs,_xlfn.UNIQUE(_xlpm.pairs),_xlpm.sortedPairs,_xlfn._xlws.SORT(_xlpm.uniquePairs,1,1),INDEX(_xlpm.sortedPairs,ROWS($M$2:M28),2)),"")} -> S723 | N28: {=IF(OR(Table2[[#This Row],[Film]]="",Table2[[#This Row],[Grade]]=""),"",IFERROR(INDEX(Table4[Serial Number],MATCH(1,(Table4[Film]=Table2[[#This Row],[Film]])*(Table4[Grade]=Table2[[#This Row],[Grade]]),0)),""))} -> RM TA45-08 S723 | O28: =IF(OR(Table2[[#This Row],[Film]]="",Table2[[#This Row],[Grade]]=""),"",SUMIFS(Table4[Price Calculated(€) Thickness & QTY related],Table4[Film],Table2[[#This Row],[Film]],Table4[Grade],Table2[[#This Row],[Grade]])) -> 0.2424 | Q28: {=IFERROR(INDEX(Table2[Film],MATCH(0,COUNTIF($Q$1:Q27,Table2[Film])+IF(Table2[Film]="",1,0),0)),"")} | R28: =SUMIF(Table2[Film],"TIPA 312 MFG",Table2[Price Calculated(€) Thickness & QTY related])+_xlfn.XLOOKUP("MET LUX ",HELPER!$A:$A,HELPER!$E:$E,0) -> 5.380588 | S28: =IFERROR(R28*HELPER!$AK$2," ") -> 6.2414821 | U28: TIPA 302FG W | V28: AO-PBS | W28: S723 | X28: RM TA45-08 S723 | Y28: Resin 6 | Z28: {=SUMPRODUCT((BOM!$A$2:$A$391=U28)*(BOM!$F$2:$F$391=Y28)*BOM!$H$2:$H$391*BOM!$G$2:$G$391)/SUMPRODUCT((BOM!$A$2:$A$391=U28)*BOM!$H$2:$H$391*BOM!$G$2:$G$391)} -> 0.015 | AA28: =SUMIF(tblResinWeightedQty12[Film],tblResinWeightedQty12[[#This Row],[Film]],tblResinWeightedQty12[Weighted QTY %]) -> 1
A29: TIPA 302FG | B29: Ext. C (In) | D29: =IF(C29="","",IFERROR(_xlfn.XLOOKUP(C29,HELPER!$A$2:$A$81,HELPER!$B$2:$B$81,""),D29)) | E29: =IFERROR(_xlfn.XLOOKUP(D29,HELPER!$B:$B,HELPER!$C:$C,""),"") | F29: =IFERROR(_xlfn.XLOOKUP(D29,HELPER!$B:$B,HELPER!$D:$D,""),"") | G29: 8 | I29: =IF(AND(H29<>"",IFERROR(_xlfn.XLOOKUP(D29,HELPER!$B:$B,HELPER!$E:$E,""),"")=""),"Missing price",IFERROR(_xlfn.XLOOKUP(D29,HELPER!$B:$B,HELPER!$E:$E,"")," ")) | J29: =IFERROR(H29*(IF(G29=8,I29*HELPER!$G$2,BOM!I29*HELPER!$G$3))," ") | L29: {=IFERROR(_xlfn.LET(_xlpm.films,Table4[Film],_xlpm.grades,Table4[Grade],_xlpm.pairs,_xlfn._xlws.FILTER(_xlfn.HSTACK(_xlpm.films,_xlpm.grades),(_xlpm.films<>"")*(TRIM(_xlpm.grades)<>"")),_xlpm.uniquePairs,_xlfn.UNIQUE(_xlpm.pairs),_xlpm.sortedPairs,_xlfn._xlws.SORT(_xlpm.uniquePairs,1,1),INDEX(_xlpm.sortedPairs,ROWS($L$2:L29),1)),"")} -> TIPA 302FG W | M29: {=IFERROR(_xlfn.LET(_xlpm.films,Table4[Film],_xlpm.grades,Table4[Grade],_xlpm.pairs,_xlfn._xlws.FILTER(_xlfn.HSTACK(_xlpm.films,_xlpm.grades),(_xlpm.films<>"")*(TRIM(_xlpm.grades)<>"")),_xlpm.uniquePairs,_xlfn.UNIQUE(_xlpm.pairs),_xlpm.sortedPairs,_xlfn._xlws.SORT(_xlpm.uniquePairs,1,1),INDEX(_xlpm.sortedPairs,ROWS($M$2:M29),2)),"")} -> S724 | N29: {=IF(OR(Table2[[#This Row],[Film]]="",Table2[[#This Row],[Grade]]=""),"",IFERROR(INDEX(Table4[Serial Number],MATCH(1,(Table4[Film]=Table2[[#This Row],[Film]])*(Table4[Grade]=Table2[[#This Row],[Grade]]),0)),""))} -> RM TA45-08 S724 | O29: =IF(OR(Table2[[#This Row],[Film]]="",Table2[[#This Row],[Grade]]=""),"",SUMIFS(Table4[Price Calculated(€) Thickness & QTY related],Table4[Film],Table2[[#This Row],[Film]],Table4[Grade],Table2[[#This Row],[Grade]])) -> 0.09408 | Q29: {=IFERROR(INDEX(Table2[Film],MATCH(0,COUNTIF($Q$1:Q28,Table2[Film])+IF(Table2[Film]="",1,0),0)),"")} | R29: =SUMIF(Table2[Film],"TIPA 312 MFG",Table2[Price Calculated(€) Thickness & QTY related])+_xlfn.XLOOKUP("MET LUX ",HELPER!$A:$A,HELPER!$E:$E,0) -> 5.380588 | S29: =IFERROR(R29*HELPER!$AK$2," ") -> 6.2414821 | U29: TIPA 302FG W | V29: SLAB-PBSA | W29: S724 | X29: RM TA45-08 S724 | Y29: Resin 7 | Z29: {=SUMPRODUCT((BOM!$A$2:$A$391=U29)*(BOM!$F$2:$F$391=Y29)*BOM!$H$2:$H$391*BOM!$G$2:$G$391)/SUMPRODUCT((BOM!$A$2:$A$391=U29)*BOM!$H$2:$H$391*BOM!$G$2:$G$391)} -> 0.0064 | AA29: =SUMIF(tblResinWeightedQty12[Film],tblResinWeightedQty12[[#This Row],[Film]],tblResinWeightedQty12[Weighted QTY %]) -> 1
A30: TIPA 302FG | B30: Ext. C (In) | D30: =IF(C30="","",IFERROR(_xlfn.XLOOKUP(C30,HELPER!$A$2:$A$81,HELPER!$B$2:$B$81,""),D30)) | E30: =IFERROR(_xlfn.XLOOKUP(D30,HELPER!$B:$B,HELPER!$C:$C,""),"") | F30: =IFERROR(_xlfn.XLOOKUP(D30,HELPER!$B:$B,HELPER!$D:$D,""),"") | G30: 8 | I30: =IF(AND(H30<>"",IFERROR(_xlfn.XLOOKUP(D30,HELPER!$B:$B,HELPER!$E:$E,""),"")=""),"Missing price",IFERROR(_xlfn.XLOOKUP(D30,HELPER!$B:$B,HELPER!$E:$E,"")," ")) | J30: =IFERROR(H30*(IF(G30=8,I30*HELPER!$G$2,BOM!I30*HELPER!$G$3))," ") | L30: {=IFERROR(_xlfn.LET(_xlpm.films,Table4[Film],_xlpm.grades,Table4[Grade],_xlpm.pairs,_xlfn._xlws.FILTER(_xlfn.HSTACK(_xlpm.films,_xlpm.grades),(_xlpm.films<>"")*(TRIM(_xlpm.grades)<>"")),_xlpm.uniquePairs,_xlfn.UNIQUE(_xlpm.pairs),_xlpm.sortedPairs,_xlfn._xlws.SORT(_xlpm.uniquePairs,1,1),INDEX(_xlpm.sortedPairs,ROWS($L$2:L30),1)),"")} -> TIPA 302FG W | M30: {=IFERROR(_xlfn.LET(_xlpm.films,Table4[Film],_xlpm.grades,Table4[Grade],_xlpm.pairs,_xlfn._xlws.FILTER(_xlfn.HSTACK(_xlpm.films,_xlpm.grades),(_xlpm.films<>"")*(TRIM(_xlpm.grades)<>"")),_xlpm.uniquePairs,_xlfn.UNIQUE(_xlpm.pairs),_xlpm.sortedPairs,_xlfn._xlws.SORT(_xlpm.uniquePairs,1,1),INDEX(_xlpm.sortedPairs,ROWS($M$2:M30),2)),"")} -> RM WHITE BIO8153 | N30: {=IF(OR(Table2[[#This Row],[Film]]="",Table2[[#This Row],[Grade]]=""),"",IFERROR(INDEX(Table4[Serial Number],MATCH(1,(Table4[Film]=Table2[[#This Row],[Film]])*(Table4[Grade]=Table2[[#This Row],[Grade]]),0)),""))} -> RM WHITE BIO8153 | O30: =IF(OR(Table2[[#This Row],[Film]]="",Table2[[#This Row],[Grade]]=""),"",SUMIFS(Table4[Price Calculated(€) Thickness & QTY related],Table4[Film],Table2[[#This Row],[Film]],Table4[Grade],Table2[[#This Row],[Grade]])) -> 0.369 | Q30: {=IFERROR(INDEX(Table2[Film],MATCH(0,COUNTIF($Q$1:Q29,Table2[Film])+IF(Table2[Film]="",1,0),0)),"")} | R30: =SUMIF(Table2[Film],"TIPA 312 MFG",Table2[Price Calculated(€) Thickness & QTY related])+_xlfn.XLOOKUP("MET LUX ",HELPER!$A:$A,HELPER!$E:$E,0) -> 5.380588 | S30: =IFERROR(R30*HELPER!$AK$2," ") -> 6.2414821 | U30: TIPA 302FG W | V30: AB-PLA | W30: KAB59A | X30: RM A KAB59A | Y30: Resin 8 | Z30: {=SUMPRODUCT((BOM!$A$2:$A$391=U30)*(BOM!$F$2:$F$391=Y30)*BOM!$H$2:$H$391*BOM!$G$2:$G$391)/SUMPRODUCT((BOM!$A$2:$A$391=U30)*BOM!$H$2:$H$391*BOM!$G$2:$G$391)} -> 0.006 | AA30: =SUMIF(tblResinWeightedQty12[Film],tblResinWeightedQty12[[#This Row],[Film]],tblResinWeightedQty12[Weighted QTY %]) -> 1
A31: TIPA 302FG | B31: Ext. C (In) | D31: =IF(C31="","",IFERROR(_xlfn.XLOOKUP(C31,HELPER!$A$2:$A$81,HELPER!$B$2:$B$81,""),D31)) | E31: =IFERROR(_xlfn.XLOOKUP(D31,HELPER!$B:$B,HELPER!$C:$C,""),"") | F31: =IFERROR(_xlfn.XLOOKUP(D31,HELPER!$B:$B,HELPER!$D:$D,""),"") | G31: 8 | I31: =IF(AND(H31<>"",IFERROR(_xlfn.XLOOKUP(D31,HELPER!$B:$B,HELPER!$E:$E,""),"")=""),"Missing price",IFERROR(_xlfn.XLOOKUP(D31,HELPER!$B:$B,HELPER!$E:$E,"")," ")) | J31: =IFERROR(H31*(IF(G31=8,I31*HELPER!$G$2,BOM!I31*HELPER!$G$3))," ") | L31: {=IFERROR(_xlfn.LET(_xlpm.films,Table4[Film],_xlpm.grades,Table4[Grade],_xlpm.pairs,_xlfn._xlws.FILTER(_xlfn.HSTACK(_xlpm.films,_xlpm.grades),(_xlpm.films<>"")*(TRIM(_xlpm.grades)<>"")),_xlpm.uniquePairs,_xlfn.UNIQUE(_xlpm.pairs),_xlpm.sortedPairs,_xlfn._xlws.SORT(_xlpm.uniquePairs,1,1),INDEX(_xlpm.sortedPairs,ROWS($L$2:L31),1)),"")} -> TIPA 302FG W | M31: {=IFERROR(_xlfn.LET(_xlpm.films,Table4[Film],_xlpm.grades,Table4[Grade],_xlpm.pairs,_xlfn._xlws.FILTER(_xlfn.HSTACK(_xlpm.films,_xlpm.grades),(_xlpm.films<>"")*(TRIM(_xlpm.grades)<>"")),_xlpm.uniquePairs,_xlfn.UNIQUE(_xlpm.pairs),_xlpm.sortedPairs,_xlfn._xlws.SORT(_xlpm.uniquePairs,1,1),INDEX(_xlpm.sortedPairs,ROWS($M$2:M31),2)),"")} -> B12 | N31: {=IF(OR(Table2[[#This Row],[Film]]="",Table2[[#This Row],[Grade]]=""),"",IFERROR(INDEX(Table4[Serial Number],MATCH(1,(Table4[Film]=Table2[[#This Row],[Film]])*(Table4[Grade]=Table2[[#This Row],[Grade]]),0)),""))} -> RMB12 | O31: =IF(OR(Table2[[#This Row],[Film]]="",Table2[[#This Row],[Grade]]=""),"",SUMIFS(Table4[Price Calculated(€) Thickness & QTY related],Table4[Film],Table2[[#This Row],[Film]],Table4[Grade],Table2[[#This Row],[Grade]])) -> 0.96111 | Q31: {=IFERROR(INDEX(Table2[Film],MATCH(0,COUNTIF($Q$1:Q30,Table2[Film])+IF(Table2[Film]="",1,0),0)),"")} | R31: =SUMIF(Table2[Film],"TIPA 312 MFG",Table2[Price Calculated(€) Thickness & QTY related])+_xlfn.XLOOKUP("MET LUX ",HELPER!$A:$A,HELPER!$E:$E,0) -> 5.380588 | S31: =IFERROR(R31*HELPER!$AK$2," ") -> 6.2414821 | U31: TIPA 302FG W | V31: PBSA | W31: FD92PM | X31: RMPM2 | Y31: Resin 9C | Z31: {=SUMPRODUCT((BOM!$A$2:$A$391=U31)*(BOM!$F$2:$F$391=Y31)*BOM!$H$2:$H$391*BOM!$G$2:$G$391)/SUMPRODUCT((BOM!$A$2:$A$391=U31)*BOM!$H$2:$H$391*BOM!$G$2:$G$391)} -> 0.324 | AA31: =SUMIF(tblResinWeightedQty12[Film],tblResinWeightedQty12[[#This Row],[Film]],tblResinWeightedQty12[Weighted QTY %]) -> 1
A32: TIPA 302FG W | B32: Ext. A (Out - Chillroll) | C32: PBSA | D32: =IF(C32="","",IFERROR(_xlfn.XLOOKUP(C32,HELPER!$A$2:$A$81,HELPER!$B$2:$B$81,""),D32)) -> FD92PM | E32: =IFERROR(_xlfn.XLOOKUP(D32,HELPER!$B:$B,HELPER!$C:$C,""),"") -> RMPM2 | F32: =IFERROR(_xlfn.XLOOKUP(D32,HELPER!$B:$B,HELPER!$D:$D,""),"") -> Resin 9C | G32: 8 | H32: 0.81 | I32: =IF(AND(H32<>"",IFERROR(_xlfn.XLOOKUP(D32,HELPER!$B:$B,HELPER!$E:$E,""),"")=""),"Missing price",IFERROR(_xlfn.XLOOKUP(D32,HELPER!$B:$B,HELPER!$E:$E,"")," ")) -> 6.75 | J32: =IFERROR(H32*(IF(G32=8,I32*HELPER!$G$2,BOM!I32*HELPER!$G$3))," ") -> 1.0935 | L32: {=IFERROR(_xlfn.LET(_xlpm.films,Table4[Film],_xlpm.grades,Table4[Grade],_xlpm.pairs,_xlfn._xlws.FILTER(_xlfn.HSTACK(_xlpm.films,_xlpm.grades),(_xlpm.films<>"")*(TRIM(_xlpm.grades)<>"")),_xlpm.uniquePairs,_xlfn.UNIQUE(_xlpm.pairs),_xlpm.sortedPairs,_xlfn._xlws.SORT(_xlpm.uniquePairs,1,1),INDEX(_xlpm.sortedPairs,ROWS($L$2:L32),1)),"")} -> TIPA 306M | M32: {=IFERROR(_xlfn.LET(_xlpm.films,Table4[Film],_xlpm.grades,Table4[Grade],_xlpm.pairs,_xlfn._xlws.FILTER(_xlfn.HSTACK(_xlpm.films,_xlpm.grades),(_xlpm.films<>"")*(TRIM(_xlpm.grades)<>"")),_xlpm.uniquePairs,_xlfn.UNIQUE(_xlpm.pairs),_xlpm.sortedPairs,_xlfn._xlws.SORT(_xlpm.uniquePairs,1,1),INDEX(_xlpm.sortedPairs,ROWS($M$2:M32),2)),"")} -> LX175 | N32: {=IF(OR(Table2[[#This Row],[Film]]="",Table2[[#This Row],[Grade]]=""),"",IFERROR(INDEX(Table4[Serial Number],MATCH(1,(Table4[Film]=Table2[[#This Row],[Film]])*(Table4[Grade]=Table2[[#This Row],[Grade]]),0)),""))} -> RMLX175 | O32: =IF(OR(Table2[[#This Row],[Film]]="",Table2[[#This Row],[Grade]]=""),"",SUMIFS(Table4[Price Calculated(€) Thickness & QTY related],Table4[Film],Table2[[#This Row],[Film]],Table4[Grade],Table2[[#This Row],[Grade]])) -> 2.106148 | Q32: {=IFERROR(INDEX(Table2[Film],MATCH(0,COUNTIF($Q$1:Q31,Table2[Film])+IF(Table2[Film]="",1,0),0)),"")} | R32: =SUMIF(Table2[Film],"TIPA 312 MFG",Table2[Price Calculated(€) Thickness & QTY related])+_xlfn.XLOOKUP("MET LUX ",HELPER!$A:$A,HELPER!$E:$E,0) -> 5.380588 | S32: =IFERROR(R32*HELPER!$AK$2," ") -> 6.2414821 | U32: TIPA 306M | V32: PLA | W32: LX175 | X32: RMLX175 | Y32: Resin 1A | Z32: {=SUMPRODUCT((BOM!$A$2:$A$391=U32)*(BOM!$F$2:$F$391=Y32)*BOM!$H$2:$H$391*BOM!$G$2:$G$391)/SUMPRODUCT((BOM!$A$2:$A$391=U32)*BOM!$H$2:$H$391*BOM!$G$2:$G$391)} -> 0.6644 | AA32: =SUMIF(tblResinWeightedQty12[Film],tblResinWeightedQty12[[#This Row],[Film]],tblResinWeightedQty12[Weighted QTY %]) -> 1
A33: TIPA 302FG W | B33: Ext. A (Out - Chillroll) | C33: PLA | D33: =IF(C33="","",IFERROR(_xlfn.XLOOKUP(C33,HELPER!$A$2:$A$81,HELPER!$B$2:$B$81,""),D33)) -> LX175 | E33: =IFERROR(_xlfn.XLOOKUP(D33,HELPER!$B:$B,HELPER!$C:$C,""),"") -> RMLX175 | F33: =IFERROR(_xlfn.XLOOKUP(D33,HELPER!$B:$B,HELPER!$D:$D,""),"") -> Resin 1A | G33: 8 | H33: 0.144 | I33: =IF(AND(H33<>"",IFERROR(_xlfn.XLOOKUP(D33,HELPER!$B:$B,HELPER!$E:$E,""),"")=""),"Missing price",IFERROR(_xlfn.XLOOKUP(D33,HELPER!$B:$B,HELPER!$E:$E,"")," ")) -> 3.17 | J33: =IFERROR(H33*(IF(G33=8,I33*HELPER!$G$2,BOM!I33*HELPER!$G$3))," ") -> 0.091296 | L33: {=IFERROR(_xlfn.LET(_xlpm.films,Table4[Film],_xlpm.grades,Table4[Grade],_xlpm.pairs,_xlfn._xlws.FILTER(_xlfn.HSTACK(_xlpm.films,_xlpm.grades),(_xlpm.films<>"")*(TRIM(_xlpm.grades)<>"")),_xlpm.uniquePairs,_xlfn.UNIQUE(_xlpm.pairs),_xlpm.sortedPairs,_xlfn._xlws.SORT(_xlpm.uniquePairs,1,1),INDEX(_xlpm.sortedPairs,ROWS($L$2:L33),1)),"")} -> TIPA 306M | M33: {=IFERROR(_xlfn.LET(_xlpm.films,Table4[Film],_xlpm.grades,Table4[Grade],_xlpm.pairs,_xlfn._xlws.FILTER(_xlfn.HSTACK(_xlpm.films,_xlpm.grades),(_xlpm.films<>"")*(TRIM(_xlpm.grades)<>"")),_xlpm.uniquePairs,_xlfn.UNIQUE(_xlpm.pairs),_xlpm.sortedPairs,_xlfn._xlws.SORT(_xlpm.uniquePairs,1,1),INDEX(_xlpm.sortedPairs,ROWS($M$2:M33),2)),"")} -> P65D | N33: {=IF(OR(Table2[[#This Row],[Film]]="",Table2[[#This Row],[Grade]]=""),"",IFERROR(INDEX(Table4[Serial Number],MATCH(1,(Table4[Film]=Table2[[#This Row],[Film]])*(Table4[Grade]=Table2[[#This Row],[Grade]]),0)),""))} -> RMP65D | O33: =IF(OR(Table2[[#This Row],[Film]]="",Table2[[#This Row],[Grade]]=""),"",SUMIFS(Table4[Price Calculated(€) Thickness & QTY related],Table4[Film],Table2[[#This Row],[Film]],Table4[Grade],Table2[[#This Row],[Grade]])) -> 1.1096 | Q33: {=IFERROR(INDEX(Table2[Film],MATCH(0,COUNTIF($Q$1:Q32,Table2[Film])+IF(Table2[Film]="",1,0),0)),"")} | R33: =SUMIF(Table2[Film],"TIPA 312 MFG",Table2[Price Calculated(€) Thickness & QTY related])+_xlfn.XLOOKUP("MET LUX ",HELPER!$A:$A,HELPER!$E:$E,0) -> 5.380588 | S33: =IFERROR(R33*HELPER!$AK$2," ") -> 6.2414821 | U33: TIPA 306M | V33: PCL | W33: P65D | X33: RMP65D | Y33: Resin 4A | Z33: {=SUMPRODUCT((BOM!$A$2:$A$391=U33)*(BOM!$F$2:$F$391=Y33)*BOM!$H$2:$H$391*BOM!$G$2:$G$391)/SUMPRODUCT((BOM!$A$2:$A$391=U33)*BOM!$H$2:$H$391*BOM!$G$2:$G$391)} -> 0.152 | AA33: =SUMIF(tblResinWeightedQty12[Film],tblResinWeightedQty12[[#This Row],[Film]],tblResinWeightedQty12[Weighted QTY %]) -> 1
A34: TIPA 302FG W | B34: Ext. A (Out - Chillroll) | C34: AB-PLA | D34: =IF(C34="","",IFERROR(_xlfn.XLOOKUP(C34,HELPER!$A$2:$A$81,HELPER!$B$2:$B$81,""),D34)) -> KAB59A | E34: =IFERROR(_xlfn.XLOOKUP(D34,HELPER!$B:$B,HELPER!$C:$C,""),"") -> RM A KAB59A | F34: =IFERROR(_xlfn.XLOOKUP(D34,HELPER!$B:$B,HELPER!$D:$D,""),"") -> Resin 8 | G34: 8 | H34: 0.015 | I34: =IF(AND(H34<>"",IFERROR(_xlfn.XLOOKUP(D34,HELPER!$B:$B,HELPER!$E:$E,""),"")=""),"Missing price",IFERROR(_xlfn.XLOOKUP(D34,HELPER!$B:$B,HELPER!$E:$E,"")," ")) -> 7.55 | J34: =IFERROR(H34*(IF(G34=8,I34*HELPER!$G$2,BOM!I34*HELPER!$G$3))," ") -> 0.02265 | L34: {=IFERROR(_xlfn.LET(_xlpm.films,Table4[Film],_xlpm.grades,Table4[Grade],_xlpm.pairs,_xlfn._xlws.FILTER(_xlfn.HSTACK(_xlpm.films,_xlpm.grades),(_xlpm.films<>"")*(TRIM(_xlpm.grades)<>"")),_xlpm.uniquePairs,_xlfn.UNIQUE(_xlpm.pairs),_xlpm.sortedPairs,_xlfn._xlws.SORT(_xlpm.uniquePairs,1,1),INDEX(_xlpm.sortedPairs,ROWS($L$2:L34),1)),"")} -> TIPA 306M | M34: {=IFERROR(_xlfn.LET(_xlpm.films,Table4[Film],_xlpm.grades,Table4[Grade],_xlpm.pairs,_xlfn._xlws.FILTER(_xlfn.HSTACK(_xlpm.films,_xlpm.grades),(_xlpm.films<>"")*(TRIM(_xlpm.grades)<>"")),_xlpm.uniquePairs,_xlfn.UNIQUE(_xlpm.pairs),_xlpm.sortedPairs,_xlfn._xlws.SORT(_xlpm.uniquePairs,1,1),INDEX(_xlpm.sortedPairs,ROWS($M$2:M34),2)),"")} -> S723 | N34: {=IF(OR(Table2[[#This Row],[Film]]="",Table2[[#This Row],[Grade]]=""),"",IFERROR(INDEX(Table4[Serial Number],MATCH(1,(Table4[Film]=Table2[[#This Row],[Film]])*(Table4[Grade]=Table2[[#This Row],[Grade]]),0)),""))} -> RM TA45-08 S723 | O34: =IF(OR(Table2[[#This Row],[Film]]="",Table2[[#This Row],[Grade]]=""),"",SUMIFS(Table4[Price Calculated(€) Thickness & QTY related],Table4[Film],Table2[[#This Row],[Film]],Table4[Grade],Table2[[#This Row],[Grade]])) -> 0.2424 | Q34: {=IFERROR(INDEX(Table2[Film],MATCH(0,COUNTIF($Q$1:Q33,Table2[Film])+IF(Table2[Film]="",1,0),0)),"")} | R34: =SUMIF(Table2[Film],"TIPA 312 MFG",Table2[Price Calculated(€) Thickness & QTY related])+_xlfn.XLOOKUP("MET LUX ",HELPER!$A:$A,HELPER!$E:$E,0) -> 5.380588 | S34: =IFERROR(R34*HELPER!$AK$2," ") -> 6.2414821 | U34: TIPA 306M | V34: AO-PBS | W34: S723 | X34: RM TA45-08 S723 | Y34: Resin 6 | Z34: {=SUMPRODUCT((BOM!$A$2:$A$391=U34)*(BOM!$F$2:$F$391=Y34)*BOM!$H$2:$H$391*BOM!$G$2:$G$391)/SUMPRODUCT((BOM!$A$2:$A$391=U34)*BOM!$H$2:$H$391*BOM!$G$2:$G$391)} -> 0.015 | AA34: =SUMIF(tblResinWeightedQty12[Film],tblResinWeightedQty12[[#This Row],[Film]],tblResinWeightedQty12[Weighted QTY %]) -> 1
A35: TIPA 302FG W | B35: Ext. A (Out - Chillroll) | C35: AO-PBS | D35: =IF(C35="","",IFERROR(_xlfn.XLOOKUP(C35,HELPER!$A$2:$A$81,HELPER!$B$2:$B$81,""),D35)) -> S723 | E35: =IFERROR(_xlfn.XLOOKUP(D35,HELPER!$B:$B,HELPER!$C:$C,""),"") -> RM TA45-08 S723 | F35: =IFERROR(_xlfn.XLOOKUP(D35,HELPER!$B:$B,HELPER!$D:$D,""),"") -> Resin 6 | G35: 8 | H35: 0.015 | I35: =IF(AND(H35<>"",IFERROR(_xlfn.XLOOKUP(D35,HELPER!$B:$B,HELPER!$E:$E,""),"")=""),"Missing price",IFERROR(_xlfn.XLOOKUP(D35,HELPER!$B:$B,HELPER!$E:$E,"")," ")) -> 16.16 | J35: =IFERROR(H35*(IF(G35=8,I35*HELPER!$G$2,BOM!I35*HELPER!$G$3))," ") -> 0.04848 | L35: {=IFERROR(_xlfn.LET(_xlpm.films,Table4[Film],_xlpm.grades,Table4[Grade],_xlpm.pairs,_xlfn._xlws.FILTER(_xlfn.HSTACK(_xlpm.films,_xlpm.grades),(_xlpm.films<>"")*(TRIM(_xlpm.grades)<>"")),_xlpm.uniquePairs,_xlfn.UNIQUE(_xlpm.pairs),_xlpm.sortedPairs,_xlfn._xlws.SORT(_xlpm.uniquePairs,1,1),INDEX(_xlpm.sortedPairs,ROWS($L$2:L35),1)),"")} -> TIPA 306M | M35: {=IFERROR(_xlfn.LET(_xlpm.films,Table4[Film],_xlpm.grades,Table4[Grade],_xlpm.pairs,_xlfn._xlws.FILTER(_xlfn.HSTACK(_xlpm.films,_xlpm.grades),(_xlpm.films<>"")*(TRIM(_xlpm.grades)<>"")),_xlpm.uniquePairs,_xlfn.UNIQUE(_xlpm.pairs),_xlpm.sortedPairs,_xlfn._xlws.SORT(_xlpm.uniquePairs,1,1),INDEX(_xlpm.sortedPairs,ROWS($M$2:M35),2)),"")} -> FD92PM | N35: {=IF(OR(Table2[[#This Row],[Film]]="",Table2[[#This Row],[Grade]]=""),"",IFERROR(INDEX(Table4[Serial Number],MATCH(1,(Table4[Film]=Table2[[#This Row],[Film]])*(Table4[Grade]=Table2[[#This Row],[Grade]]),0)),""))} -> RMPM2 | O35: =IF(OR(Table2[[#This Row],[Film]]="",Table2[[#This Row],[Grade]]=""),"",SUMIFS(Table4[Price Calculated(€) Thickness & QTY related],Table4[Film],Table2[[#This Row],[Film]],Table4[Grade],Table2[[#This Row],[Grade]])) -> 1.0908 | Q35: {=IFERROR(INDEX(Table2[Film],MATCH(0,COUNTIF($Q$1:Q34,Table2[Film])+IF(Table2[Film]="",1,0),0)),"")} | R35: =SUMIF(Table2[Film],"TIPA 312 MFG",Table2[Price Calculated(€) Thickness & QTY related])+_xlfn.XLOOKUP("MET LUX ",HELPER!$A:$A,HELPER!$E:$E,0) -> 5.380588 | S35: =IFERROR(R35*HELPER!$AK$2," ") -> 6.2414821 | U35: TIPA 306M | V35: SLAB-PBSA | W35: S724 | X35: RM TA45-08 S724 | Y35: Resin 7 | Z35: {=SUMPRODUCT((BOM!$A$2:$A$391=U35)*(BOM!$F$2:$F$391=Y35)*BOM!$H$2:$H$391*BOM!$G$2:$G$391)/SUMPRODUCT((BOM!$A$2:$A$391=U35)*BOM!$H$2:$H$391*BOM!$G$2:$G$391)} -> 0.004 | AA35: =SUMIF(tblResinWeightedQty12[Film],tblResinWeightedQty12[[#This Row],[Film]],tblResinWeightedQty12[Weighted QTY %]) -> 1
A36: TIPA 302FG W | B36: Ext. A (Out - Chillroll) | C36: SLAB-PBSA | D36: =IF(C36="","",IFERROR(_xlfn.XLOOKUP(C36,HELPER!$A$2:$A$81,HELPER!$B$2:$B$81,""),D36)) -> S724 | E36: =IFERROR(_xlfn.XLOOKUP(D36,HELPER!$B:$B,HELPER!$C:$C,""),"") -> RM TA45-08 S724 | F36: =IFERROR(_xlfn.XLOOKUP(D36,HELPER!$B:$B,HELPER!$D:$D,""),"") -> Resin 7 | G36: 8 | H36: 0.016 | I36: =IF(AND(H36<>"",IFERROR(_xlfn.XLOOKUP(D36,HELPER!$B:$B,HELPER!$E:$E,""),"")=""),"Missing price",IFERROR(_xlfn.XLOOKUP(D36,HELPER!$B:$B,HELPER!$E:$E,"")," ")) -> 14.7 | J36: =IFERROR(H36*(IF(G36=8,I36*HELPER!$G$2,BOM!I36*HELPER!$G$3))," ") -> 0.04704 | L36: {=IFERROR(_xlfn.LET(_xlpm.films,Table4[Film],_xlpm.grades,Table4[Grade],_xlpm.pairs,_xlfn._xlws.FILTER(_xlfn.HSTACK(_xlpm.films,_xlpm.grades),(_xlpm.films<>"")*(TRIM(_xlpm.grades)<>"")),_xlpm.uniquePairs,_xlfn.UNIQUE(_xlpm.pairs),_xlpm.sortedPairs,_xlfn._xlws.SORT(_xlpm.uniquePairs,1,1),INDEX(_xlpm.sortedPairs,ROWS($L$2:L36),1)),"")} -> TIPA 306M | M36: {=IFERROR(_xlfn.LET(_xlpm.films,Table4[Film],_xlpm.grades,Table4[Grade],_xlpm.pairs,_xlfn._xlws.FILTER(_xlfn.HSTACK(_xlpm.films,_xlpm.grades),(_xlpm.films<>"")*(TRIM(_xlpm.grades)<>"")),_xlpm.uniquePairs,_xlfn.UNIQUE(_xlpm.pairs),_xlpm.sortedPairs,_xlfn._xlws.SORT(_xlpm.uniquePairs,1,1),INDEX(_xlpm.sortedPairs,ROWS($M$2:M36),2)),"")} -> KAB59A | N36: {=IF(OR(Table2[[#This Row],[Film]]="",Table2[[#This Row],[Grade]]=""),"",IFERROR(INDEX(Table4[Serial Number],MATCH(1,(Table4[Film]=Table2[[#This Row],[Film]])*(Table4[Grade]=Table2[[#This Row],[Grade]]),0)),""))} -> RM A KAB59A | O36: =IF(OR(Table2[[#This Row],[Film]]="",Table2[[#This Row],[Grade]]=""),"",SUMIFS(Table4[Price Calculated(€) Thickness & QTY related],Table4[Film],Table2[[#This Row],[Film]],Table4[Grade],Table2[[#This Row],[Grade]])) -> 0.02265 | Q36: {=IFERROR(INDEX(Table2[Film],MATCH(0,COUNTIF($Q$1:Q35,Table2[Film])+IF(Table2[Film]="",1,0),0)),"")} | R36: =SUMIF(Table2[Film],"TIPA 312 MFG",Table2[Price Calculated(€) Thickness & QTY related])+_xlfn.XLOOKUP("MET LUX ",HELPER!$A:$A,HELPER!$E:$E,0) -> 5.380588 | S36: =IFERROR(R36*HELPER!$AK$2," ") -> 6.2414821 | U36: TIPA 306M | V36: AB-PLA | W36: KAB59A | X36: RM A KAB59A | Y36: Resin 8 | Z36: {=SUMPRODUCT((BOM!$A$2:$A$391=U36)*(BOM!$F$2:$F$391=Y36)*BOM!$H$2:$H$391*BOM!$G$2:$G$391)/SUMPRODUCT((BOM!$A$2:$A$391=U36)*BOM!$H$2:$H$391*BOM!$G$2:$G$391)} -> 0.003 | AA36: =SUMIF(tblResinWeightedQty12[Film],tblResinWeightedQty12[[#This Row],[Film]],tblResinWeightedQty12[Weighted QTY %]) -> 1
A37: TIPA 302FG W | B37: Ext. A (Out - Chillroll) | D37: =IF(C37="","",IFERROR(_xlfn.XLOOKUP(C37,HELPER!$A$2:$A$81,HELPER!$B$2:$B$81,""),D37)) | E37: =IFERROR(_xlfn.XLOOKUP(D37,HELPER!$B:$B,HELPER!$C:$C,""),"") | F37: =IFERROR(_xlfn.XLOOKUP(D37,HELPER!$B:$B,HELPER!$D:$D,""),"") | G37: 8 | I37: =IF(AND(H37<>"",IFERROR(_xlfn.XLOOKUP(D37,HELPER!$B:$B,HELPER!$E:$E,""),"")=""),"Missing price",IFERROR(_xlfn.XLOOKUP(D37,HELPER!$B:$B,HELPER!$E:$E,"")," ")) | J37: =IFERROR(H37*(IF(G37=8,I37*HELPER!$G$2,BOM!I37*HELPER!$G$3))," ") | L37: {=IFERROR(_xlfn.LET(_xlpm.films,Table4[Film],_xlpm.grades,Table4[Grade],_xlpm.pairs,_xlfn._xlws.FILTER(_xlfn.HSTACK(_xlpm.films,_xlpm.grades),(_xlpm.films<>"")*(TRIM(_xlpm.grades)<>"")),_xlpm.uniquePairs,_xlfn.UNIQUE(_xlpm.pairs),_xlpm.sortedPairs,_xlfn._xlws.SORT(_xlpm.uniquePairs,1,1),INDEX(_xlpm.sortedPairs,ROWS($L$2:L37),1)),"")} -> TIPA 306M | M37: {=IFERROR(_xlfn.LET(_xlpm.films,Table4[Film],_xlpm.grades,Table4[Grade],_xlpm.pairs,_xlfn._xlws.FILTER(_xlfn.HSTACK(_xlpm.films,_xlpm.grades),(_xlpm.films<>"")*(TRIM(_xlpm.grades)<>"")),_xlpm.uniquePairs,_xlfn.UNIQUE(_xlpm.pairs),_xlpm.sortedPairs,_xlfn._xlws.SORT(_xlpm.uniquePairs,1,1),INDEX(_xlpm.sortedPairs,ROWS($M$2:M37),2)),"")} -> S724 | N37: {=IF(OR(Table2[[#This Row],[Film]]="",Table2[[#This Row],[Grade]]=""),"",IFERROR(INDEX(Table4[Serial Number],MATCH(1,(Table4[Film]=Table2[[#This Row],[Film]])*(Table4[Grade]=Table2[[#This Row],[Grade]]),0)),""))} -> RM TA45-08 S724 | O37: =IF(OR(Table2[[#This Row],[Film]]="",Table2[[#This Row],[Grade]]=""),"",SUMIFS(Table4[Price Calculated(€) Thickness & QTY related],Table4[Film],Table2[[#This Row],[Film]],Table4[Grade],Table2[[#This Row],[Grade]])) -> 0.0588 | Q37: {=IFERROR(INDEX(Table2[Film],MATCH(0,COUNTIF($Q$1:Q36,Table2[Film])+IF(Table2[Film]="",1,0),0)),"")} | R37: =SUMIF(Table2[Film],"TIPA 312 MFG",Table2[Price Calculated(€) Thickness & QTY related])+_xlfn.XLOOKUP("MET LUX ",HELPER!$A:$A,HELPER!$E:$E,0) -> 5.380588 | S37: =IFERROR(R37*HELPER!$AK$2," ") -> 6.2414821 | U37: TIPA 306M | V37: PBSA | W37: FD92PM | X37: RMPM2 | Y37: Resin 9C | Z37: {=SUMPRODUCT((BOM!$A$2:$A$391=U37)*(BOM!$F$2:$F$391=Y37)*BOM!$H$2:$H$391*BOM!$G$2:$G$391)/SUMPRODUCT((BOM!$A$2:$A$391=U37)*BOM!$H$2:$H$391*BOM!$G$2:$G$391)} -> 0.1616 | AA37: =SUMIF(tblResinWeightedQty12[Film],tblResinWeightedQty12[[#This Row],[Film]],tblResinWeightedQty12[Weighted QTY %]) -> 1
A38: TIPA 302FG W | B38: Ext. A (Out - Chillroll) | D38: =IF(C38="","",IFERROR(_xlfn.XLOOKUP(C38,HELPER!$A$2:$A$81,HELPER!$B$2:$B$81,""),D38)) | E38: =IFERROR(_xlfn.XLOOKUP(D38,HELPER!$B:$B,HELPER!$C:$C,""),"") | F38: =IFERROR(_xlfn.XLOOKUP(D38,HELPER!$B:$B,HELPER!$D:$D,""),"") | G38: 8 | I38: =IF(AND(H38<>"",IFERROR(_xlfn.XLOOKUP(D38,HELPER!$B:$B,HELPER!$E:$E,""),"")=""),"Missing price",IFERROR(_xlfn.XLOOKUP(D38,HELPER!$B:$B,HELPER!$E:$E,"")," ")) | J38: =IFERROR(H38*(IF(G38=8,I38*HELPER!$G$2,BOM!I38*HELPER!$G$3))," ") | L38: {=IFERROR(_xlfn.LET(_xlpm.films,Table4[Film],_xlpm.grades,Table4[Grade],_xlpm.pairs,_xlfn._xlws.FILTER(_xlfn.HSTACK(_xlpm.films,_xlpm.grades),(_xlpm.films<>"")*(TRIM(_xlpm.grades)<>"")),_xlpm.uniquePairs,_xlfn.UNIQUE(_xlpm.pairs),_xlpm.sortedPairs,_xlfn._xlws.SORT(_xlpm.uniquePairs,1,1),INDEX(_xlpm.sortedPairs,ROWS($L$2:L38),1)),"")} -> TIPA 306W | M38: {=IFERROR(_xlfn.LET(_xlpm.films,Table4[Film],_xlpm.grades,Table4[Grade],_xlpm.pairs,_xlfn._xlws.FILTER(_xlfn.HSTACK(_xlpm.films,_xlpm.grades),(_xlpm.films<>"")*(TRIM(_xlpm.grades)<>"")),_xlpm.uniquePairs,_xlfn.UNIQUE(_xlpm.pairs),_xlpm.sortedPairs,_xlfn._xlws.SORT(_xlpm.uniquePairs,1,1),INDEX(_xlpm.sortedPairs,ROWS($M$2:M38),2)),"")} -> LX175 | N38: {=IF(OR(Table2[[#This Row],[Film]]="",Table2[[#This Row],[Grade]]=""),"",IFERROR(INDEX(Table4[Serial Number],MATCH(1,(Table4[Film]=Table2[[#This Row],[Film]])*(Table4[Grade]=Table2[[#This Row],[Grade]]),0)),""))} -> RMLX175 | O38: =IF(OR(Table2[[#This Row],[Film]]="",Table2[[#This Row],[Grade]]=""),"",SUMIFS(Table4[Price Calculated(€) Thickness & QTY related],Table4[Film],Table2[[#This Row],[Film]],Table4[Grade],Table2[[#This Row],[Grade]])) -> 1.940674 | Q38: {=IFERROR(INDEX(Table2[Film],MATCH(0,COUNTIF($Q$1:Q37,Table2[Film])+IF(Table2[Film]="",1,0),0)),"")} | R38: =SUMIF(Table2[Film],"TIPA 312 MFG",Table2[Price Calculated(€) Thickness & QTY related])+_xlfn.XLOOKUP("MET LUX ",HELPER!$A:$A,HELPER!$E:$E,0) -> 5.380588 | S38: =IFERROR(R38*HELPER!$AK$2," ") -> 6.2414821 | U38: TIPA 306W | V38: ECOMP WHITE | W38: RM WHITE BIO8153 | X38: RM WHITE BIO8153 | Y38: Resin 13B | Z38: {=SUMPRODUCT((BOM!$A$2:$A$391=U38)*(BOM!$F$2:$F$391=Y38)*BOM!$H$2:$H$391*BOM!$G$2:$G$391)/SUMPRODUCT((BOM!$A$2:$A$391=U38)*BOM!$H$2:$H$391*BOM!$G$2:$G$391)} -> 0.06 | AA38: =SUMIF(tblResinWeightedQty12[Film],tblResinWeightedQty12[[#This Row],[Film]],tblResinWeightedQty12[Weighted QTY %]) -> 1
A39: TIPA 302FG W | B39: Ext. A (Out - Chillroll) | D39: =IF(C39="","",IFERROR(_xlfn.XLOOKUP(C39,HELPER!$A$2:$A$81,HELPER!$B$2:$B$81,""),D39)) | E39: =IFERROR(_xlfn.XLOOKUP(D39,HELPER!$B:$B,HELPER!$C:$C,""),"") | F39: =IFERROR(_xlfn.XLOOKUP(D39,HELPER!$B:$B,HELPER!$D:$D,""),"") | G39: 8 | I39: =IF(AND(H39<>"",IFERROR(_xlfn.XLOOKUP(D39,HELPER!$B:$B,HELPER!$E:$E,""),"")=""),"Missing price",IFERROR(_xlfn.XLOOKUP(D39,HELPER!$B:$B,HELPER!$E:$E,"")," ")) | J39: =IFERROR(H39*(IF(G39=8,I39*HELPER!$G$2,BOM!I39*HELPER!$G$3))," ") | L39: {=IFERROR(_xlfn.LET(_xlpm.films,Table4[Film],_xlpm.grades,Table4[Grade],_xlpm.pairs,_xlfn._xlws.FILTER(_xlfn.HSTACK(_xlpm.films,_xlpm.grades),(_xlpm.films<>"")*(TRIM(_xlpm.grades)<>"")),_xlpm.uniquePairs,_xlfn.UNIQUE(_xlpm.pairs),_xlpm.sortedPairs,_xlfn._xlws.SORT(_xlpm.uniquePairs,1,1),INDEX(_xlpm.sortedPairs,ROWS($L$2:L39),1)),"")} -> TIPA 306W | M39: {=IFERROR(_xlfn.LET(_xlpm.films,Table4[Film],_xlpm.grades,Table4[Grade],_xlpm.pairs,_xlfn._xlws.FILTER(_xlfn.HSTACK(_xlpm.films,_xlpm.grades),(_xlpm.films<>"")*(TRIM(_xlpm.grades)<>"")),_xlpm.uniquePairs,_xlfn.UNIQUE(_xlpm.pairs),_xlpm.sortedPairs,_xlfn._xlws.SORT(_xlpm.uniquePairs,1,1),INDEX(_xlpm.sortedPairs,ROWS($M$2:M39),2)),"")} -> P65D | N39: {=IF(OR(Table2[[#This Row],[Film]]="",Table2[[#This Row],[Grade]]=""),"",IFERROR(INDEX(Table4[Serial Number],MATCH(1,(Table4[Film]=Table2[[#This Row],[Film]])*(Table4[Grade]=Table2[[#This Row],[Grade]]),0)),""))} -> RMP65D | O39: =IF(OR(Table2[[#This Row],[Film]]="",Table2[[#This Row],[Grade]]=""),"",SUMIFS(Table4[Price Calculated(€) Thickness & QTY related],Table4[Film],Table2[[#This Row],[Film]],Table4[Grade],Table2[[#This Row],[Grade]])) -> 1.00156 | Q39: {=IFERROR(INDEX(Table2[Film],MATCH(0,COUNTIF($Q$1:Q38,Table2[Film])+IF(Table2[Film]="",1,0),0)),"")} | R39: =SUMIF(Table2[Film],"TIPA 312 MFG",Table2[Price Calculated(€) Thickness & QTY related])+_xlfn.XLOOKUP("MET LUX ",HELPER!$A:$A,HELPER!$E:$E,0) -> 5.380588 | S39: =IFERROR(R39*HELPER!$AK$2," ") -> 6.2414821 | U39: TIPA 306W | V39: PLA | W39: LX175 | X39: RMLX175 | Y39: Resin 1A | Z39: {=SUMPRODUCT((BOM!$A$2:$A$391=U39)*(BOM!$F$2:$F$391=Y39)*BOM!$H$2:$H$391*BOM!$G$2:$G$391)/SUMPRODUCT((BOM!$A$2:$A$391=U39)*BOM!$H$2:$H$391*BOM!$G$2:$G$391)} -> 0.6122 | AA39: =SUMIF(tblResinWeightedQty12[Film],tblResinWeightedQty12[[#This Row],[Film]],tblResinWeightedQty12[Weighted QTY %]) -> 1
A40: TIPA 302FG W | B40: Ext. A (Out - Chillroll) | D40: =IF(C40="","",IFERROR(_xlfn.XLOOKUP(C40,HELPER!$A$2:$A$81,HELPER!$B$2:$B$81,""),D40)) | E40: =IFERROR(_xlfn.XLOOKUP(D40,HELPER!$B:$B,HELPER!$C:$C,""),"") | F40: =IFERROR(_xlfn.XLOOKUP(D40,HELPER!$B:$B,HELPER!$D:$D,""),"") | G40: 8 | I40: =IF(AND(H40<>"",IFERROR(_xlfn.XLOOKUP(D40,HELPER!$B:$B,HELPER!$E:$E,""),"")=""),"Missing price",IFERROR(_xlfn.XLOOKUP(D40,HELPER!$B:$B,HELPER!$E:$E,"")," ")) | J40: =IFERROR(H40*(IF(G40=8,I40*HELPER!$G$2,BOM!I40*HELPER!$G$3))," ") | L40: {=IFERROR(_xlfn.LET(_xlpm.films,Table4[Film],_xlpm.grades,Table4[Grade],_xlpm.pairs,_xlfn._xlws.FILTER(_xlfn.HSTACK(_xlpm.films,_xlpm.grades),(_xlpm.films<>"")*(TRIM(_xlpm.grades)<>"")),_xlpm.uniquePairs,_xlfn.UNIQUE(_xlpm.pairs),_xlpm.sortedPairs,_xlfn._xlws.SORT(_xlpm.uniquePairs,1,1),INDEX(_xlpm.sortedPairs,ROWS($L$2:L40),1)),"")} -> TIPA 306W | M40: {=IFERROR(_xlfn.LET(_xlpm.films,Table4[Film],_xlpm.grades,Table4[Grade],_xlpm.pairs,_xlfn._xlws.FILTER(_xlfn.HSTACK(_xlpm.films,_xlpm.grades),(_xlpm.films<>"")*(TRIM(_xlpm.grades)<>"")),_xlpm.uniquePairs,_xlfn.UNIQUE(_xlpm.pairs),_xlpm.sortedPairs,_xlfn._xlws.SORT(_xlpm.uniquePairs,1,1),INDEX(_xlpm.sortedPairs,ROWS($M$2:M40),2)),"")} -> S723 | N40: {=IF(OR(Table2[[#This Row],[Film]]="",Table2[[#This Row],[Grade]]=""),"",IFERROR(INDEX(Table4[Serial Number],MATCH(1,(Table4[Film]=Table2[[#This Row],[Film]])*(Table4[Grade]=Table2[[#This Row],[Grade]]),0)),""))} -> RM TA45-08 S723 | O40: =IF(OR(Table2[[#This Row],[Film]]="",Table2[[#This Row],[Grade]]=""),"",SUMIFS(Table4[Price Calculated(€) Thickness & QTY related],Table4[Film],Table2[[#This Row],[Film]],Table4[Grade],Table2[[#This Row],[Grade]])) -> 0.2424 | Q40: {=IFERROR(INDEX(Table2[Film],MATCH(0,COUNTIF($Q$1:Q39,Table2[Film])+IF(Table2[Film]="",1,0),0)),"")} | R40: =SUMIF(Table2[Film],"TIPA 312 MFG",Table2[Price Calculated(€) Thickness & QTY related])+_xlfn.XLOOKUP("MET LUX ",HELPER!$A:$A,HELPER!$E:$E,0) -> 5.380588 | S40: =IFERROR(R40*HELPER!$AK$2," ") -> 6.2414821 | U40: TIPA 306W | V40: PCL | W40: P65D | X40: RMP65D | Y40: Resin 4A | Z40: {=SUMPRODUCT((BOM!$A$2:$A$391=U40)*(BOM!$F$2:$F$391=Y40)*BOM!$H$2:$H$391*BOM!$G$2:$G$391)/SUMPRODUCT((BOM!$A$2:$A$391=U40)*BOM!$H$2:$H$391*BOM!$G$2:$G$391)} -> 0.1372 | AA40: =SUMIF(tblResinWeightedQty12[Film],tblResinWeightedQty12[[#This Row],[Film]],tblResinWeightedQty12[Weighted QTY %]) -> 1
A41: TIPA 302FG W | B41: Ext. A (Out - Chillroll) | D41: =IF(C41="","",IFERROR(_xlfn.XLOOKUP(C41,HELPER!$A$2:$A$81,HELPER!$B$2:$B$81,""),D41)) | E41: =IFERROR(_xlfn.XLOOKUP(D41,HELPER!$B:$B,HELPER!$C:$C,""),"") | F41: =IFERROR(_xlfn.XLOOKUP(D41,HELPER!$B:$B,HELPER!$D:$D,""),"") | G41: 8 | I41: =IF(AND(H41<>"",IFERROR(_xlfn.XLOOKUP(D41,HELPER!$B:$B,HELPER!$E:$E,""),"")=""),"Missing price",IFERROR(_xlfn.XLOOKUP(D41,HELPER!$B:$B,HELPER!$E:$E,"")," ")) | J41: =IFERROR(H41*(IF(G41=8,I41*HELPER!$G$2,BOM!I41*HELPER!$G$3))," ") | L41: {=IFERROR(_xlfn.LET(_xlpm.films,Table4[Film],_xlpm.grades,Table4[Grade],_xlpm.pairs,_xlfn._xlws.FILTER(_xlfn.HSTACK(_xlpm.films,_xlpm.grades),(_xlpm.films<>"")*(TRIM(_xlpm.grades)<>"")),_xlpm.uniquePairs,_xlfn.UNIQUE(_xlpm.pairs),_xlpm.sortedPairs,_xlfn._xlws.SORT(_xlpm.uniquePairs,1,1),INDEX(_xlpm.sortedPairs,ROWS($L$2:L41),1)),"")} -> TIPA 306W | M41: {=IFERROR(_xlfn.LET(_xlpm.films,Table4[Film],_xlpm.grades,Table4[Grade],_xlpm.pairs,_xlfn._xlws.FILTER(_xlfn.HSTACK(_xlpm.films,_xlpm.grades),(_xlpm.films<>"")*(TRIM(_xlpm.grades)<>"")),_xlpm.uniquePairs,_xlfn.UNIQUE(_xlpm.pairs),_xlpm.sortedPairs,_xlfn._xlws.SORT(_xlpm.uniquePairs,1,1),INDEX(_xlpm.sortedPairs,ROWS($M$2:M41),2)),"")} -> KAB59A | N41: {=IF(OR(Table2[[#This Row],[Film]]="",Table2[[#This Row],[Grade]]=""),"",IFERROR(INDEX(Table4[Serial Number],MATCH(1,(Table4[Film]=Table2[[#This Row],[Film]])*(Table4[Grade]=Table2[[#This Row],[Grade]]),0)),""))} -> RM A KAB59A | O41: =IF(OR(Table2[[#This Row],[Film]]="",Table2[[#This Row],[Grade]]=""),"",SUMIFS(Table4[Price Calculated(€) Thickness & QTY related],Table4[Film],Table2[[#This Row],[Film]],Table4[Grade],Table2[[#This Row],[Grade]])) -> 0.0453 | Q41: {=IFERROR(INDEX(Table2[Film],MATCH(0,COUNTIF($Q$1:Q40,Table2[Film])+IF(Table2[Film]="",1,0),0)),"")} | R41: =SUMIF(Table2[Film],"TIPA 312 MFG",Table2[Price Calculated(€) Thickness & QTY related])+_xlfn.XLOOKUP("MET LUX ",HELPER!$A:$A,HELPER!$E:$E,0) -> 5.380588 | S41: =IFERROR(R41*HELPER!$AK$2," ") -> 6.2414821 | U41: TIPA 306W | V41: AO-PBS | W41: S723 | X41: RM TA45-08 S723 | Y41: Resin 6 | Z41: {=SUMPRODUCT((BOM!$A$2:$A$391=U41)*(BOM!$F$2:$F$391=Y41)*BOM!$H$2:$H$391*BOM!$G$2:$G$391)/SUMPRODUCT((BOM!$A$2:$A$391=U41)*BOM!$H$2:$H$391*BOM!$G$2:$G$391)} -> 0.015 | AA41: =SUMIF(tblResinWeightedQty12[Film],tblResinWeightedQty12[[#This Row],[Film]],tblResinWeightedQty12[Weighted QTY %]) -> 1
A42: TIPA 302FG W | B42: Ext. B | D42: =IF(C42="","",IFERROR(_xlfn.XLOOKUP(C42,HELPER!$A$2:$A$81,HELPER!$B$2:$B$81,""),D42)) | E42: =IFERROR(_xlfn.XLOOKUP(D42,HELPER!$B:$B,HELPER!$C:$C,""),"") | F42: =IFERROR(_xlfn.XLOOKUP(D42,HELPER!$B:$B,HELPER!$D:$D,""),"") | G42: 24 | I42: =IF(AND(H42<>"",IFERROR(_xlfn.XLOOKUP(D42,HELPER!$B:$B,HELPER!$E:$E,""),"")=""),"Missing price",IFERROR(_xlfn.XLOOKUP(D42,HELPER!$B:$B,HELPER!$E:$E,"")," ")) | J42: =IFERROR(H42*(IF(G42=8,I42*HELPER!$G$2,BOM!I42*HELPER!$G$3))," ") | L42: {=IFERROR(_xlfn.LET(_xlpm.films,Table4[Film],_xlpm.grades,Table4[Grade],_xlpm.pairs,_xlfn._xlws.FILTER(_xlfn.HSTACK(_xlpm.films,_xlpm.grades),(_xlpm.films<>"")*(TRIM(_xlpm.grades)<>"")),_xlpm.uniquePairs,_xlfn.UNIQUE(_xlpm.pairs),_xlpm.sortedPairs,_xlfn._xlws.SORT(_xlpm.uniquePairs,1,1),INDEX(_xlpm.sortedPairs,ROWS($L$2:L42),1)),"")} -> TIPA 306W | M42: {=IFERROR(_xlfn.LET(_xlpm.films,Table4[Film],_xlpm.grades,Table4[Grade],_xlpm.pairs,_xlfn._xlws.FILTER(_xlfn.HSTACK(_xlpm.films,_xlpm.grades),(_xlpm.films<>"")*(TRIM(_xlpm.grades)<>"")),_xlpm.uniquePairs,_xlfn.UNIQUE(_xlpm.pairs),_xlpm.sortedPairs,_xlfn._xlws.SORT(_xlpm.uniquePairs,1,1),INDEX(_xlpm.sortedPairs,ROWS($M$2:M42),2)),"")} -> S724 | N42: {=IF(OR(Table2[[#This Row],[Film]]="",Table2[[#This Row],[Grade]]=""),"",IFERROR(INDEX(Table4[Serial Number],MATCH(1,(Table4[Film]=Table2[[#This Row],[Film]])*(Table4[Grade]=Table2[[#This Row],[Grade]]),0)),""))} -> RM TA45-08 S724 | O42: =IF(OR(Table2[[#This Row],[Film]]="",Table2[[#This Row],[Grade]]=""),"",SUMIFS(Table4[Price Calculated(€) Thickness & QTY related],Table4[Film],Table2[[#This Row],[Film]],Table4[Grade],Table2[[#This Row],[Grade]])) -> 0.1176 | Q42: {=IFERROR(INDEX(Table2[Film],MATCH(0,COUNTIF($Q$1:Q41,Table2[Film])+IF(Table2[Film]="",1,0),0)),"")} | R42: =SUMIF(Table2[Film],"TIPA 312 MFG",Table2[Price Calculated(€) Thickness & QTY related])+_xlfn.XLOOKUP("MET LUX ",HELPER!$A:$A,HELPER!$E:$E,0) -> 5.380588 | S42: =IFERROR(R42*HELPER!$AK$2," ") -> 6.2414821 | U42: TIPA 306W | V42: SLAB-PBSA | W42: S724 | X42: RM TA45-08 S724 | Y42: Resin 7 | Z42: {=SUMPRODUCT((BOM!$A$2:$A$391=U42)*(BOM!$F$2:$F$391=Y42)*BOM!$H$2:$H$391*BOM!$G$2:$G$391)/SUMPRODUCT((BOM!$A$2:$A$391=U42)*BOM!$H$2:$H$391*BOM!$G$2:$G$391)} -> 0.008 | AA42: =SUMIF(tblResinWeightedQty12[Film],tblResinWeightedQty12[[#This Row],[Film]],tblResinWeightedQty12[Weighted QTY %]) -> 1
A43: TIPA 302FG W | B43: Ext. B | D43: =IF(C43="","",IFERROR(_xlfn.XLOOKUP(C43,HELPER!$A$2:$A$81,HELPER!$B$2:$B$81,""),D43)) | E43: =IFERROR(_xlfn.XLOOKUP(D43,HELPER!$B:$B,HELPER!$C:$C,""),"") | F43: =IFERROR(_xlfn.XLOOKUP(D43,HELPER!$B:$B,HELPER!$D:$D,""),"") | G43: 24 | I43: =IF(AND(H43<>"",IFERROR(_xlfn.XLOOKUP(D43,HELPER!$B:$B,HELPER!$E:$E,""),"")=""),"Missing price",IFERROR(_xlfn.XLOOKUP(D43,HELPER!$B:$B,HELPER!$E:$E,"")," ")) | J43: =IFERROR(H43*(IF(G43=8,I43*HELPER!$G$2,BOM!I43*HELPER!$G$3))," ") | L43: {=IFERROR(_xlfn.LET(_xlpm.films,Table4[Film],_xlpm.grades,Table4[Grade],_xlpm.pairs,_xlfn._xlws.FILTER(_xlfn.HSTACK(_xlpm.films,_xlpm.grades),(_xlpm.films<>"")*(TRIM(_xlpm.grades)<>"")),_xlpm.uniquePairs,_xlfn.UNIQUE(_xlpm.pairs),_xlpm.sortedPairs,_xlfn._xlws.SORT(_xlpm.uniquePairs,1,1),INDEX(_xlpm.sortedPairs,ROWS($L$2:L43),1)),"")} -> TIPA 306W | M43: {=IFERROR(_xlfn.LET(_xlpm.films,Table4[Film],_xlpm.grades,Table4[Grade],_xlpm.pairs,_xlfn._xlws.FILTER(_xlfn.HSTACK(_xlpm.films,_xlpm.grades),(_xlpm.films<>"")*(TRIM(_xlpm.grades)<>"")),_xlpm.uniquePairs,_xlfn.UNIQUE(_xlpm.pairs),_xlpm.sortedPairs,_xlfn._xlws.SORT(_xlpm.uniquePairs,1,1),INDEX(_xlpm.sortedPairs,ROWS($M$2:M43),2)),"")} -> RM WHITE BIO8153 | N43: {=IF(OR(Table2[[#This Row],[Film]]="",Table2[[#This Row],[Grade]]=""),"",IFERROR(INDEX(Table4[Serial Number],MATCH(1,(Table4[Film]=Table2[[#This Row],[Film]])*(Table4[Grade]=Table2[[#This Row],[Grade]]),0)),""))} -> RM WHITE BIO8153 | O43: =IF(OR(Table2[[#This Row],[Film]]="",Table2[[#This Row],[Grade]]=""),"",SUMIFS(Table4[Price Calculated(€) Thickness & QTY related],Table4[Film],Table2[[#This Row],[Film]],Table4[Grade],Table2[[#This Row],[Grade]])) -> 0.369 | Q43: {=IFERROR(INDEX(Table2[Film],MATCH(0,COUNTIF($Q$1:Q42,Table2[Film])+IF(Table2[Film]="",1,0),0)),"")} | R43: =SUMIF(Table2[Film],"TIPA 312 MFG",Table2[Price Calculated(€) Thickness & QTY related])+_xlfn.XLOOKUP("MET LUX ",HELPER!$A:$A,HELPER!$E:$E,0) -> 5.380588 | S43: =IFERROR(R43*HELPER!$AK$2," ") -> 6.2414821 | U43: TIPA 306W | V43: AB-PLA | W43: KAB59A | X43: RM A KAB59A | Y43: Resin 8 | Z43: {=SUMPRODUCT((BOM!$A$2:$A$391=U43)*(BOM!$F$2:$F$391=Y43)*BOM!$H$2:$H$391*BOM!$G$2:$G$391)/SUMPRODUCT((BOM!$A$2:$A$391=U43)*BOM!$H$2:$H$391*BOM!$G$2:$G$391)} -> 0.006 | AA43: =SUMIF(tblResinWeightedQty12[Film],tblResinWeightedQty12[[#This Row],[Film]],tblResinWeightedQty12[Weighted QTY %]) -> 1
A44: TIPA 302FG W | B44: Ext. B | D44: =IF(C44="","",IFERROR(_xlfn.XLOOKUP(C44,HELPER!$A$2:$A$81,HELPER!$B$2:$B$81,""),D44)) | E44: =IFERROR(_xlfn.XLOOKUP(D44,HELPER!$B:$B,HELPER!$C:$C,""),"") | F44: =IFERROR(_xlfn.XLOOKUP(D44,HELPER!$B:$B,HELPER!$D:$D,""),"") | G44: 24 | I44: =IF(AND(H44<>"",IFERROR(_xlfn.XLOOKUP(D44,HELPER!$B:$B,HELPER!$E:$E,""),"")=""),"Missing price",IFERROR(_xlfn.XLOOKUP(D44,HELPER!$B:$B,HELPER!$E:$E,"")," ")) | J44: =IFERROR(H44*(IF(G44=8,I44*HELPER!$G$2,BOM!I44*HELPER!$G$3))," ") | L44: {=IFERROR(_xlfn.LET(_xlpm.films,Table4[Film],_xlpm.grades,Table4[Grade],_xlpm.pairs,_xlfn._xlws.FILTER(_xlfn.HSTACK(_xlpm.films,_xlpm.grades),(_xlpm.films<>"")*(TRIM(_xlpm.grades)<>"")),_xlpm.uniquePairs,_xlfn.UNIQUE(_xlpm.pairs),_xlpm.sortedPairs,_xlfn._xlws.SORT(_xlpm.uniquePairs,1,1),INDEX(_xlpm.sortedPairs,ROWS($L$2:L44),1)),"")} -> TIPA 306W | M44: {=IFERROR(_xlfn.LET(_xlpm.films,Table4[Film],_xlpm.grades,Table4[Grade],_xlpm.pairs,_xlfn._xlws.FILTER(_xlfn.HSTACK(_xlpm.films,_xlpm.grades),(_xlpm.films<>"")*(TRIM(_xlpm.grades)<>"")),_xlpm.uniquePairs,_xlfn.UNIQUE(_xlpm.pairs),_xlpm.sortedPairs,_xlfn._xlws.SORT(_xlpm.uniquePairs,1,1),INDEX(_xlpm.sortedPairs,ROWS($M$2:M44),2)),"")} -> FD92PM | N44: {=IF(OR(Table2[[#This Row],[Film]]="",Table2[[#This Row],[Grade]]=""),"",IFERROR(INDEX(Table4[Serial Number],MATCH(1,(Table4[Film]=Table2[[#This Row],[Film]])*(Table4[Grade]=Table2[[#This Row],[Grade]]),0)),""))} -> RMPM2 | O44: =IF(OR(Table2[[#This Row],[Film]]="",Table2[[#This Row],[Grade]]=""),"",SUMIFS(Table4[Price Calculated(€) Thickness & QTY related],Table4[Film],Table2[[#This Row],[Film]],Table4[Grade],Table2[[#This Row],[Grade]])) -> 1.0908 | Q44: {=IFERROR(INDEX(Table2[Film],MATCH(0,COUNTIF($Q$1:Q43,Table2[Film])+IF(Table2[Film]="",1,0),0)),"")} | R44: =SUMIF(Table2[Film],"TIPA 312 MFG",Table2[Price Calculated(€) Thickness & QTY related])+_xlfn.XLOOKUP("MET LUX ",HELPER!$A:$A,HELPER!$E:$E,0) -> 5.380588 | S44: =IFERROR(R44*HELPER!$AK$2," ") -> 6.2414821 | U44: TIPA 306W | V44: PBSA | W44: FD92PM | X44: RMPM2 | Y44: Resin 9C | Z44: {=SUMPRODUCT((BOM!$A$2:$A$391=U44)*(BOM!$F$2:$F$391=Y44)*BOM!$H$2:$H$391*BOM!$G$2:$G$391)/SUMPRODUCT((BOM!$A$2:$A$391=U44)*BOM!$H$2:$H$391*BOM!$G$2:$G$391)} -> 0.1616 | AA44: =SUMIF(tblResinWeightedQty12[Film],tblResinWeightedQty12[[#This Row],[Film]],tblResinWeightedQty12[Weighted QTY %]) -> 1
A45: TIPA 302FG W | B45: Ext. B | C45: AO-PBS | D45: =IF(C45="","",IFERROR(_xlfn.XLOOKUP(C45,HELPER!$A$2:$A$81,HELPER!$B$2:$B$81,""),D45)) -> S723 | E45: =IFERROR(_xlfn.XLOOKUP(D45,HELPER!$B:$B,HELPER!$C:$C,""),"") -> RM TA45-08 S723 | F45: =IFERROR(_xlfn.XLOOKUP(D45,HELPER!$B:$B,HELPER!$D:$D,""),"") -> Resin 6 | G45: 24 | H45: 0.015 | I45: =IF(AND(H45<>"",IFERROR(_xlfn.XLOOKUP(D45,HELPER!$B:$B,HELPER!$E:$E,""),"")=""),"Missing price",IFERROR(_xlfn.XLOOKUP(D45,HELPER!$B:$B,HELPER!$E:$E,"")," ")) -> 16.16 | J45: =IFERROR(H45*(IF(G45=8,I45*HELPER!$G$2,BOM!I45*HELPER!$G$3))," ") -> 0.14544 | L45: {=IFERROR(_xlfn.LET(_xlpm.films,Table4[Film],_xlpm.grades,Table4[Grade],_xlpm.pairs,_xlfn._xlws.FILTER(_xlfn.HSTACK(_xlpm.films,_xlpm.grades),(_xlpm.films<>"")*(TRIM(_xlpm.grades)<>"")),_xlpm.uniquePairs,_xlfn.UNIQUE(_xlpm.pairs),_xlpm.sortedPairs,_xlfn._xlws.SORT(_xlpm.uniquePairs,1,1),INDEX(_xlpm.sortedPairs,ROWS($L$2:L45),1)),"")} -> TIPA 312 MFG | M45: {=IFERROR(_xlfn.LET(_xlpm.films,Table4[Film],_xlpm.grades,Table4[Grade],_xlpm.pairs,_xlfn._xlws.FILTER(_xlfn.HSTACK(_xlpm.films,_xlpm.grades),(_xlpm.films<>"")*(TRIM(_xlpm.grades)<>"")),_xlpm.uniquePairs,_xlfn.UNIQUE(_xlpm.pairs),_xlpm.sortedPairs,_xlfn._xlws.SORT(_xlpm.uniquePairs,1,1),INDEX(_xlpm.sortedPairs,ROWS($M$2:M45),2)),"")} -> LX175 | N45: {=IF(OR(Table2[[#This Row],[Film]]="",Table2[[#This Row],[Grade]]=""),"",IFERROR(INDEX(Table4[Serial Number],MATCH(1,(Table4[Film]=Table2[[#This Row],[Film]])*(Table4[Grade]=Table2[[#This Row],[Grade]]),0)),""))} -> RMLX175 | O45: =IF(OR(Table2[[#This Row],[Film]]="",Table2[[#This Row],[Grade]]=""),"",SUMIFS(Table4[Price Calculated(€) Thickness & QTY related],Table4[Film],Table2[[#This Row],[Film]],Table4[Grade],Table2[[#This Row],[Grade]])) -> 0.594058 | Q45: {=IFERROR(INDEX(Table2[Film],MATCH(0,COUNTIF($Q$1:Q44,Table2[Film])+IF(Table2[Film]="",1,0),0)),"")} | R45: =SUMIF(Table2[Film],"TIPA 312 MFG",Table2[Price Calculated(€) Thickness & QTY related])+_xlfn.XLOOKUP("MET LUX ",HELPER!$A:$A,HELPER!$E:$E,0) -> 5.380588 | S45: =IFERROR(R45*HELPER!$AK$2," ") -> 6.2414821 | U45: TIPA 312 MFG | V45: PLA | W45: LX175 | X45: RMLX175 | Y45: Resin 1A | Z45: {=SUMPRODUCT((BOM!$A$2:$A$391=U45)*(BOM!$F$2:$F$391=Y45)*BOM!$H$2:$H$391*BOM!$G$2:$G$391)/SUMPRODUCT((BOM!$A$2:$A$391=U45)*BOM!$H$2:$H$391*BOM!$G$2:$G$391)} -> 0.1874 | AA45: =SUMIF(tblResinWeightedQty12[Film],tblResinWeightedQty12[[#This Row],[Film]],tblResinWeightedQty12[Weighted QTY %]) -> 1
A46: TIPA 302FG W | B46: Ext. B | C46: ECOMP WHITE | D46: =IF(C46="","",IFERROR(_xlfn.XLOOKUP(C46,HELPER!$A$2:$A$81,HELPER!$B$2:$B$81,""),D46)) -> RM WHITE BIO8153 | E46: =IFERROR(_xlfn.XLOOKUP(D46,HELPER!$B:$B,HELPER!$C:$C,""),"") -> RM WHITE BIO8153 | F46: =IFERROR(_xlfn.XLOOKUP(D46,HELPER!$B:$B,HELPER!$D:$D,""),"") -> Resin 13B | G46: 24 | H46: 0.1 | I46: =IF(AND(H46<>"",IFERROR(_xlfn.XLOOKUP(D46,HELPER!$B:$B,HELPER!$E:$E,""),"")=""),"Missing price",IFERROR(_xlfn.XLOOKUP(D46,HELPER!$B:$B,HELPER!$E:$E,"")," ")) -> 6.15 | J46: =IFERROR(H46*(IF(G46=8,I46*HELPER!$G$2,BOM!I46*HELPER!$G$3))," ") -> 0.369 | L46: {=IFERROR(_xlfn.LET(_xlpm.films,Table4[Film],_xlpm.grades,Table4[Grade],_xlpm.pairs,_xlfn._xlws.FILTER(_xlfn.HSTACK(_xlpm.films,_xlpm.grades),(_xlpm.films<>"")*(TRIM(_xlpm.grades)<>"")),_xlpm.uniquePairs,_xlfn.UNIQUE(_xlpm.pairs),_xlpm.sortedPairs,_xlfn._xlws.SORT(_xlpm.uniquePairs,1,1),INDEX(_xlpm.sortedPairs,ROWS($L$2:L46),1)),"")} -> TIPA 312 MFG | M46: {=IFERROR(_xlfn.LET(_xlpm.films,Table4[Film],_xlpm.grades,Table4[Grade],_xlpm.pairs,_xlfn._xlws.FILTER(_xlfn.HSTACK(_xlpm.films,_xlpm.grades),(_xlpm.films<>"")*(TRIM(_xlpm.grades)<>"")),_xlpm.uniquePairs,_xlfn.UNIQUE(_xlpm.pairs),_xlpm.sortedPairs,_xlfn._xlws.SORT(_xlpm.uniquePairs,1,1),INDEX(_xlpm.sortedPairs,ROWS($M$2:M46),2)),"")} -> P65D | N46: {=IF(OR(Table2[[#This Row],[Film]]="",Table2[[#This Row],[Grade]]=""),"",IFERROR(INDEX(Table4[Serial Number],MATCH(1,(Table4[Film]=Table2[[#This Row],[Film]])*(Table4[Grade]=Table2[[#This Row],[Grade]]),0)),""))} -> RMP65D | O46: =IF(OR(Table2[[#This Row],[Film]]="",Table2[[#This Row],[Grade]]=""),"",SUMIFS(Table4[Price Calculated(€) Thickness & QTY related],Table4[Film],Table2[[#This Row],[Film]],Table4[Grade],Table2[[#This Row],[Grade]])) -> 0.2774 | Q46: {=IFERROR(INDEX(Table2[Film],MATCH(0,COUNTIF($Q$1:Q45,Table2[Film])+IF(Table2[Film]="",1,0),0)),"")} | R46: =SUMIF(Table2[Film],"TIPA 312 MFG",Table2[Price Calculated(€) Thickness & QTY related])+_xlfn.XLOOKUP("MET LUX ",HELPER!$A:$A,HELPER!$E:$E,0) -> 5.380588 | S46: =IFERROR(R46*HELPER!$AK$2," ") -> 6.2414821 | U46: TIPA 312 MFG | V46: PBAT | W46: B12 | X46: RMB12 | Y46: Resin 2A | Z46: {=SUMPRODUCT((BOM!$A$2:$A$391=U46)*(BOM!$F$2:$F$391=Y46)*BOM!$H$2:$H$391*BOM!$G$2:$G$391)/SUMPRODUCT((BOM!$A$2:$A$391=U46)*BOM!$H$2:$H$391*BOM!$G$2:$G$391)} -> 0.591 | AA46: =SUMIF(tblResinWeightedQty12[Film],tblResinWeightedQty12[[#This Row],[Film]],tblResinWeightedQty12[Weighted QTY %]) -> 1
A47: TIPA 302FG W | B47: Ext. B | C47: SLAB-PBSA | D47: =IF(C47="","",IFERROR(_xlfn.XLOOKUP(C47,HELPER!$A$2:$A$81,HELPER!$B$2:$B$81,""),D47)) -> S724 | E47: =IFERROR(_xlfn.XLOOKUP(D47,HELPER!$B:$B,HELPER!$C:$C,""),"") -> RM TA45-08 S724 | F47: =IFERROR(_xlfn.XLOOKUP(D47,HELPER!$B:$B,HELPER!$D:$D,""),"") -> Resin 7 | G47: 24 | I47: =IF(AND(H47<>"",IFERROR(_xlfn.XLOOKUP(D47,HELPER!$B:$B,HELPER!$E:$E,""),"")=""),"Missing price",IFERROR(_xlfn.XLOOKUP(D47,HELPER!$B:$B,HELPER!$E:$E,"")," ")) -> 14.7 | J47: =IFERROR(H47*(IF(G47=8,I47*HELPER!$G$2,BOM!I47*HELPER!$G$3))," ") -> 0 | L47: {=IFERROR(_xlfn.LET(_xlpm.films,Table4[Film],_xlpm.grades,Table4[Grade],_xlpm.pairs,_xlfn._xlws.FILTER(_xlfn.HSTACK(_xlpm.films,_xlpm.grades),(_xlpm.films<>"")*(TRIM(_xlpm.grades)<>"")),_xlpm.uniquePairs,_xlfn.UNIQUE(_xlpm.pairs),_xlpm.sortedPairs,_xlfn._xlws.SORT(_xlpm.uniquePairs,1,1),INDEX(_xlpm.sortedPairs,ROWS($L$2:L47),1)),"")} -> TIPA 312 MFG | M47: {=IFERROR(_xlfn.LET(_xlpm.films,Table4[Film],_xlpm.grades,Table4[Grade],_xlpm.pairs,_xlfn._xlws.FILTER(_xlfn.HSTACK(_xlpm.films,_xlpm.grades),(_xlpm.films<>"")*(TRIM(_xlpm.grades)<>"")),_xlpm.uniquePairs,_xlfn.UNIQUE(_xlpm.pairs),_xlpm.sortedPairs,_xlfn._xlws.SORT(_xlpm.uniquePairs,1,1),INDEX(_xlpm.sortedPairs,ROWS($M$2:M47),2)),"")} -> S723 | N47: {=IF(OR(Table2[[#This Row],[Film]]="",Table2[[#This Row],[Grade]]=""),"",IFERROR(INDEX(Table4[Serial Number],MATCH(1,(Table4[Film]=Table2[[#This Row],[Film]])*(Table4[Grade]=Table2[[#This Row],[Grade]]),0)),""))} -> RM TA45-08 S723 | O47: =IF(OR(Table2[[#This Row],[Film]]="",Table2[[#This Row],[Grade]]=""),"",SUMIFS(Table4[Price Calculated(€) Thickness & QTY related],Table4[Film],Table2[[#This Row],[Film]],Table4[Grade],Table2[[#This Row],[Grade]])) -> 0.2424 | Q47: {=IFERROR(INDEX(Table2[Film],MATCH(0,COUNTIF($Q$1:Q46,Table2[Film])+IF(Table2[Film]="",1,0),0)),"")} | R47: =SUMIF(Table2[Film],"TIPA 312 MFG",Table2[Price Calculated(€) Thickness & QTY related])+_xlfn.XLOOKUP("MET LUX ",HELPER!$A:$A,HELPER!$E:$E,0) -> 5.380588 | S47: =IFERROR(R47*HELPER!$AK$2," ") -> 6.2414821 | U47: TIPA 312 MFG | V47: PCL | W47: P65D | X47: RMP65D | Y47: Resin 4A | Z47: {=SUMPRODUCT((BOM!$A$2:$A$391=U47)*(BOM!$F$2:$F$391=Y47)*BOM!$H$2:$H$391*BOM!$G$2:$G$391)/SUMPRODUCT((BOM!$A$2:$A$391=U47)*BOM!$H$2:$H$391*BOM!$G$2:$G$391)} -> 0.038 | AA47: =SUMIF(tblResinWeightedQty12[Film],tblResinWeightedQty12[[#This Row],[Film]],tblResinWeightedQty12[Weighted QTY %]) -> 1
A48: TIPA 302FG W | B48: Ext. B | C48: PBAT | D48: =IF(C48="","",IFERROR(_xlfn.XLOOKUP(C48,HELPER!$A$2:$A$81,HELPER!$B$2:$B$81,""),D48)) -> B12 | E48: =IFERROR(_xlfn.XLOOKUP(D48,HELPER!$B:$B,HELPER!$C:$C,""),"") -> RMB12 | F48: =IFERROR(_xlfn.XLOOKUP(D48,HELPER!$B:$B,HELPER!$D:$D,""),"") -> Resin 2A | G48: 24 | H48: 0.885 | I48: =IF(AND(H48<>"",IFERROR(_xlfn.XLOOKUP(D48,HELPER!$B:$B,HELPER!$E:$E,""),"")=""),"Missing price",IFERROR(_xlfn.XLOOKUP(D48,HELPER!$B:$B,HELPER!$E:$E,"")," ")) -> 1.81 | J48: =IFERROR(H48*(IF(G48=8,I48*HELPER!$G$2,BOM!I48*HELPER!$G$3))," ") -> 0.96111 | L48: {=IFERROR(_xlfn.LET(_xlpm.films,Table4[Film],_xlpm.grades,Table4[Grade],_xlpm.pairs,_xlfn._xlws.FILTER(_xlfn.HSTACK(_xlpm.films,_xlpm.grades),(_xlpm.films<>"")*(TRIM(_xlpm.grades)<>"")),_xlpm.uniquePairs,_xlfn.UNIQUE(_xlpm.pairs),_xlpm.sortedPairs,_xlfn._xlws.SORT(_xlpm.uniquePairs,1,1),INDEX(_xlpm.sortedPairs,ROWS($L$2:L48),1)),"")} -> TIPA 312 MFG | M48: {=IFERROR(_xlfn.LET(_xlpm.films,Table4[Film],_xlpm.grades,Table4[Grade],_xlpm.pairs,_xlfn._xlws.FILTER(_xlfn.HSTACK(_xlpm.films,_xlpm.grades),(_xlpm.films<>"")*(TRIM(_xlpm.grades)<>"")),_xlpm.uniquePairs,_xlfn.UNIQUE(_xlpm.pairs),_xlpm.sortedPairs,_xlfn._xlws.SORT(_xlpm.uniquePairs,1,1),INDEX(_xlpm.sortedPairs,ROWS($M$2:M48),2)),"")} -> B12 | N48: {=IF(OR(Table2[[#This Row],[Film]]="",Table2[[#This Row],[Grade]]=""),"",IFERROR(INDEX(Table4[Serial Number],MATCH(1,(Table4[Film]=Table2[[#This Row],[Film]])*(Table4[Grade]=Table2[[#This Row],[Grade]]),0)),""))} -> RMB12 | O48: =IF(OR(Table2[[#This Row],[Film]]="",Table2[[#This Row],[Grade]]=""),"",SUMIFS(Table4[Price Calculated(€) Thickness & QTY related],Table4[Film],Table2[[#This Row],[Film]],Table4[Grade],Table2[[#This Row],[Grade]])) -> 1.06971 | Q48: {=IFERROR(INDEX(Table2[Film],MATCH(0,COUNTIF($Q$1:Q47,Table2[Film])+IF(Table2[Film]="",1,0),0)),"")} | R48: =SUMIF(Table2[Film],"TIPA 312 MFG",Table2[Price Calculated(€) Thickness & QTY related])+_xlfn.XLOOKUP("MET LUX ",HELPER!$A:$A,HELPER!$E:$E,0) -> 5.380588 | S48: =IFERROR(R48*HELPER!$AK$2," ") -> 6.2414821 | U48: TIPA 312 MFG | V48: AO-PBS | W48: S723 | X48: RM TA45-08 S723 | Y48: Resin 6 | Z48: {=SUMPRODUCT((BOM!$A$2:$A$391=U48)*(BOM!$F$2:$F$391=Y48)*BOM!$H$2:$H$391*BOM!$G$2:$G$391)/SUMPRODUCT((BOM!$A$2:$A$391=U48)*BOM!$H$2:$H$391*BOM!$G$2:$G$391)} -> 0.015 | AA48: =SUMIF(tblResinWeightedQty12[Film],tblResinWeightedQty12[[#This Row],[Film]],tblResinWeightedQty12[Weighted QTY %]) -> 1
A49: TIPA 302FG W | B49: Ext. B | D49: =IF(C49="","",IFERROR(_xlfn.XLOOKUP(C49,HELPER!$A$2:$A$81,HELPER!$B$2:$B$81,""),D49)) | E49: =IFERROR(_xlfn.XLOOKUP(D49,HELPER!$B:$B,HELPER!$C:$C,""),"") | F49: =IFERROR(_xlfn.XLOOKUP(D49,HELPER!$B:$B,HELPER!$D:$D,""),"") | G49: 24 | I49: =IF(AND(H49<>"",IFERROR(_xlfn.XLOOKUP(D49,HELPER!$B:$B,HELPER!$E:$E,""),"")=""),"Missing price",IFERROR(_xlfn.XLOOKUP(D49,HELPER!$B:$B,HELPER!$E:$E,"")," ")) | J49: =IFERROR(H49*(IF(G49=8,I49*HELPER!$G$2,BOM!I49*HELPER!$G$3))," ") | L49: {=IFERROR(_xlfn.LET(_xlpm.films,Table4[Film],_xlpm.grades,Table4[Grade],_xlpm.pairs,_xlfn._xlws.FILTER(_xlfn.HSTACK(_xlpm.films,_xlpm.grades),(_xlpm.films<>"")*(TRIM(_xlpm.grades)<>"")),_xlpm.uniquePairs,_xlfn.UNIQUE(_xlpm.pairs),_xlpm.sortedPairs,_xlfn._xlws.SORT(_xlpm.uniquePairs,1,1),INDEX(_xlpm.sortedPairs,ROWS($L$2:L49),1)),"")} -> TIPA 312 MFG | M49: {=IFERROR(_xlfn.LET(_xlpm.films,Table4[Film],_xlpm.grades,Table4[Grade],_xlpm.pairs,_xlfn._xlws.FILTER(_xlfn.HSTACK(_xlpm.films,_xlpm.grades),(_xlpm.films<>"")*(TRIM(_xlpm.grades)<>"")),_xlpm.uniquePairs,_xlfn.UNIQUE(_xlpm.pairs),_xlpm.sortedPairs,_xlfn._xlws.SORT(_xlpm.uniquePairs,1,1),INDEX(_xlpm.sortedPairs,ROWS($M$2:M49),2)),"")} -> FD92PM | N49: {=IF(OR(Table2[[#This Row],[Film]]="",Table2[[#This Row],[Grade]]=""),"",IFERROR(INDEX(Table4[Serial Number],MATCH(1,(Table4[Film]=Table2[[#This Row],[Film]])*(Table4[Grade]=Table2[[#This Row],[Grade]]),0)),""))} -> RMPM2 | O49: =IF(OR(Table2[[#This Row],[Film]]="",Table2[[#This Row],[Grade]]=""),"",SUMIFS(Table4[Price Calculated(€) Thickness & QTY related],Table4[Film],Table2[[#This Row],[Film]],Table4[Grade],Table2[[#This Row],[Grade]])) -> 1.08675 | Q49: {=IFERROR(INDEX(Table2[Film],MATCH(0,COUNTIF($Q$1:Q48,Table2[Film])+IF(Table2[Film]="",1,0),0)),"")} | R49: =SUMIF(Table2[Film],"TIPA 312 MFG",Table2[Price Calculated(€) Thickness & QTY related])+_xlfn.XLOOKUP("MET LUX ",HELPER!$A:$A,HELPER!$E:$E,0) -> 5.380588 | S49: =IFERROR(R49*HELPER!$AK$2," ") -> 6.2414821 | U49: TIPA 312 MFG | V49: SLAB-PBSA | W49: S724 | X49: RM TA45-08 S724 | Y49: Resin 7 | Z49: {=SUMPRODUCT((BOM!$A$2:$A$391=U49)*(BOM!$F$2:$F$391=Y49)*BOM!$H$2:$H$391*BOM!$G$2:$G$391)/SUMPRODUCT((BOM!$A$2:$A$391=U49)*BOM!$H$2:$H$391*BOM!$G$2:$G$391)} -> 0.0046 | AA49: =SUMIF(tblResinWeightedQty12[Film],tblResinWeightedQty12[[#This Row],[Film]],tblResinWeightedQty12[Weighted QTY %]) -> 1
A50: TIPA 302FG W | B50: Ext. B | D50: =IF(C50="","",IFERROR(_xlfn.XLOOKUP(C50,HELPER!$A$2:$A$81,HELPER!$B$2:$B$81,""),D50)) | E50: =IFERROR(_xlfn.XLOOKUP(D50,HELPER!$B:$B,HELPER!$C:$C,""),"") | F50: =IFERROR(_xlfn.XLOOKUP(D50,HELPER!$B:$B,HELPER!$D:$D,""),"") | G50: 24 | I50: =IF(AND(H50<>"",IFERROR(_xlfn.XLOOKUP(D50,HELPER!$B:$B,HELPER!$E:$E,""),"")=""),"Missing price",IFERROR(_xlfn.XLOOKUP(D50,HELPER!$B:$B,HELPER!$E:$E,"")," ")) | J50: =IFERROR(H50*(IF(G50=8,I50*HELPER!$G$2,BOM!I50*HELPER!$G$3))," ") | L50: {=IFERROR(_xlfn.LET(_xlpm.films,Table4[Film],_xlpm.grades,Table4[Grade],_xlpm.pairs,_xlfn._xlws.FILTER(_xlfn.HSTACK(_xlpm.films,_xlpm.grades),(_xlpm.films<>"")*(TRIM(_xlpm.grades)<>"")),_xlpm.uniquePairs,_xlfn.UNIQUE(_xlpm.pairs),_xlpm.sortedPairs,_xlfn._xlws.SORT(_xlpm.uniquePairs,1,1),INDEX(_xlpm.sortedPairs,ROWS($L$2:L50),1)),"")} -> TIPA 312 MFG | M50: {=IFERROR(_xlfn.LET(_xlpm.films,Table4[Film],_xlpm.grades,Table4[Grade],_xlpm.pairs,_xlfn._xlws.FILTER(_xlfn.HSTACK(_xlpm.films,_xlpm.grades),(_xlpm.films<>"")*(TRIM(_xlpm.grades)<>"")),_xlpm.uniquePairs,_xlfn.UNIQUE(_xlpm.pairs),_xlpm.sortedPairs,_xlfn._xlws.SORT(_xlpm.uniquePairs,1,1),INDEX(_xlpm.sortedPairs,ROWS($M$2:M50),2)),"")} -> KAB59A | N50: {=IF(OR(Table2[[#This Row],[Film]]="",Table2[[#This Row],[Grade]]=""),"",IFERROR(INDEX(Table4[Serial Number],MATCH(1,(Table4[Film]=Table2[[#This Row],[Film]])*(Table4[Grade]=Table2[[#This Row],[Grade]]),0)),""))} -> RM A KAB59A | O50: =IF(OR(Table2[[#This Row],[Film]]="",Table2[[#This Row],[Grade]]=""),"",SUMIFS(Table4[Price Calculated(€) Thickness & QTY related],Table4[Film],Table2[[#This Row],[Film]],Table4[Grade],Table2[[#This Row],[Grade]])) -> 0.02265 | Q50: {=IFERROR(INDEX(Table2[Film],MATCH(0,COUNTIF($Q$1:Q49,Table2[Film])+IF(Table2[Film]="",1,0),0)),"")} | R50: =SUMIF(Table2[Film],"TIPA 312 MFG",Table2[Price Calculated(€) Thickness & QTY related])+_xlfn.XLOOKUP("MET LUX ",HELPER!$A:$A,HELPER!$E:$E,0) -> 5.380588 | S50: =IFERROR(R50*HELPER!$AK$2," ") -> 6.2414821 | U50: TIPA 312 MFG | V50: AB-PLA | W50: KAB59A | X50: RM A KAB59A | Y50: Resin 8 | Z50: {=SUMPRODUCT((BOM!$A$2:$A$391=U50)*(BOM!$F$2:$F$391=Y50)*BOM!$H$2:$H$391*BOM!$G$2:$G$391)/SUMPRODUCT((BOM!$A$2:$A$391=U50)*BOM!$H$2:$H$391*BOM!$G$2:$G$391)} -> 0.003 | AA50: =SUMIF(tblResinWeightedQty12[Film],tblResinWeightedQty12[[#This Row],[Film]],tblResinWeightedQty12[Weighted QTY %]) -> 1
A51: TIPA 302FG W | B51: Ext. B | D51: =IF(C51="","",IFERROR(_xlfn.XLOOKUP(C51,HELPER!$A$2:$A$81,HELPER!$B$2:$B$81,""),D51)) | E51: =IFERROR(_xlfn.XLOOKUP(D51,HELPER!$B:$B,HELPER!$C:$C,""),"") | F51: =IFERROR(_xlfn.XLOOKUP(D51,HELPER!$B:$B,HELPER!$D:$D,""),"") | G51: 24 | I51: =IF(AND(H51<>"",IFERROR(_xlfn.XLOOKUP(D51,HELPER!$B:$B,HELPER!$E:$E,""),"")=""),"Missing price",IFERROR(_xlfn.XLOOKUP(D51,HELPER!$B:$B,HELPER!$E:$E,"")," ")) | J51: =IFERROR(H51*(IF(G51=8,I51*HELPER!$G$2,BOM!I51*HELPER!$G$3))," ") | L51: {=IFERROR(_xlfn.LET(_xlpm.films,Table4[Film],_xlpm.grades,Table4[Grade],_xlpm.pairs,_xlfn._xlws.FILTER(_xlfn.HSTACK(_xlpm.films,_xlpm.grades),(_xlpm.films<>"")*(TRIM(_xlpm.grades)<>"")),_xlpm.uniquePairs,_xlfn.UNIQUE(_xlpm.pairs),_xlpm.sortedPairs,_xlfn._xlws.SORT(_xlpm.uniquePairs,1,1),INDEX(_xlpm.sortedPairs,ROWS($L$2:L51),1)),"")} -> TIPA 312 MFG | M51: {=IFERROR(_xlfn.LET(_xlpm.films,Table4[Film],_xlpm.grades,Table4[Grade],_xlpm.pairs,_xlfn._xlws.FILTER(_xlfn.HSTACK(_xlpm.films,_xlpm.grades),(_xlpm.films<>"")*(TRIM(_xlpm.grades)<>"")),_xlpm.uniquePairs,_xlfn.UNIQUE(_xlpm.pairs),_xlpm.sortedPairs,_xlfn._xlws.SORT(_xlpm.uniquePairs,1,1),INDEX(_xlpm.sortedPairs,ROWS($M$2:M51),2)),"")} -> S724 | N51: {=IF(OR(Table2[[#This Row],[Film]]="",Table2[[#This Row],[Grade]]=""),"",IFERROR(INDEX(Table4[Serial Number],MATCH(1,(Table4[Film]=Table2[[#This Row],[Film]])*(Table4[Grade]=Table2[[#This Row],[Grade]]),0)),""))} -> RM TA45-08 S724 | O51: =IF(OR(Table2[[#This Row],[Film]]="",Table2[[#This Row],[Grade]]=""),"",SUMIFS(Table4[Price Calculated(€) Thickness & QTY related],Table4[Film],Table2[[#This Row],[Film]],Table4[Grade],Table2[[#This Row],[Grade]])) -> 0.06762 | U51: TIPA 312 MFG | V51: PBSA | W51: FD92PM | X51: RMPM2 | Y51: Resin 9C | Z51: {=SUMPRODUCT((BOM!$A$2:$A$391=U51)*(BOM!$F$2:$F$391=Y51)*BOM!$H$2:$H$391*BOM!$G$2:$G$391)/SUMPRODUCT((BOM!$A$2:$A$391=U51)*BOM!$H$2:$H$391*BOM!$G$2:$G$391)} -> 0.161 | AA51: =SUMIF(tblResinWeightedQty12[Film],tblResinWeightedQty12[[#This Row],[Film]],tblResinWeightedQty12[Weighted QTY %]) -> 1
A52: TIPA 302FG W | B52: Ext. C (In) | C52: PBSA | D52: =IF(C52="","",IFERROR(_xlfn.XLOOKUP(C52,HELPER!$A$2:$A$81,HELPER!$B$2:$B$81,""),D52)) -> FD92PM | E52: =IFERROR(_xlfn.XLOOKUP(D52,HELPER!$B:$B,HELPER!$C:$C,""),"") -> RMPM2 | F52: =IFERROR(_xlfn.XLOOKUP(D52,HELPER!$B:$B,HELPER!$D:$D,""),"") -> Resin 9C | G52: 8 | H52: 0.81 | I52: =IF(AND(H52<>"",IFERROR(_xlfn.XLOOKUP(D52,HELPER!$B:$B,HELPER!$E:$E,""),"")=""),"Missing price",IFERROR(_xlfn.XLOOKUP(D52,HELPER!$B:$B,HELPER!$E:$E,"")," ")) -> 6.75 | J52: =IFERROR(H52*(IF(G52=8,I52*HELPER!$G$2,BOM!I52*HELPER!$G$3))," ") -> 1.0935 | L52: {=IFERROR(_xlfn.LET(_xlpm.films,Table4[Film],_xlpm.grades,Table4[Grade],_xlpm.pairs,_xlfn._xlws.FILTER(_xlfn.HSTACK(_xlpm.films,_xlpm.grades),(_xlpm.films<>"")*(TRIM(_xlpm.grades)<>"")),_xlpm.uniquePairs,_xlfn.UNIQUE(_xlpm.pairs),_xlpm.sortedPairs,_xlfn._xlws.SORT(_xlpm.uniquePairs,1,1),INDEX(_xlpm.sortedPairs,ROWS($L$2:L52),1)),"")} -> TIPA 312MFGW | M52: {=IFERROR(_xlfn.LET(_xlpm.films,Table4[Film],_xlpm.grades,Table4[Grade],_xlpm.pairs,_xlfn._xlws.FILTER(_xlfn.HSTACK(_xlpm.films,_xlpm.grades),(_xlpm.films<>"")*(TRIM(_xlpm.grades)<>"")),_xlpm.uniquePairs,_xlfn.UNIQUE(_xlpm.pairs),_xlpm.sortedPairs,_xlfn._xlws.SORT(_xlpm.uniquePairs,1,1),INDEX(_xlpm.sortedPairs,ROWS($M$2:M52),2)),"")} -> LX175 | N52: {=IF(OR(Table2[[#This Row],[Film]]="",Table2[[#This Row],[Grade]]=""),"",IFERROR(INDEX(Table4[Serial Number],MATCH(1,(Table4[Film]=Table2[[#This Row],[Film]])*(Table4[Grade]=Table2[[#This Row],[Grade]]),0)),""))} -> RMLX175 | O52: =IF(OR(Table2[[#This Row],[Film]]="",Table2[[#This Row],[Grade]]=""),"",SUMIFS(Table4[Price Calculated(€) Thickness & QTY related],Table4[Film],Table2[[#This Row],[Film]],Table4[Grade],Table2[[#This Row],[Grade]])) -> 0.594058 | U52: TIPA 312MFGW | V52: ECOMP WHITE | W52: RM WHITE BIO8153 | X52: RM WHITE BIO8153 | Y52: Resin 13B | Z52: {=SUMPRODUCT((BOM!$A$2:$A$391=U52)*(BOM!$F$2:$F$391=Y52)*BOM!$H$2:$H$391*BOM!$G$2:$G$391)/SUMPRODUCT((BOM!$A$2:$A$391=U52)*BOM!$H$2:$H$391*BOM!$G$2:$G$391)} -> 0.06 | AA52: =SUMIF(tblResinWeightedQty12[Film],tblResinWeightedQty12[[#This Row],[Film]],tblResinWeightedQty12[Weighted QTY %]) -> 1
A53: TIPA 302FG W | B53: Ext. C (In) | C53: PLA | D53: =IF(C53="","",IFERROR(_xlfn.XLOOKUP(C53,HELPER!$A$2:$A$81,HELPER!$B$2:$B$81,""),D53)) -> LX175 | E53: =IFERROR(_xlfn.XLOOKUP(D53,HELPER!$B:$B,HELPER!$C:$C,""),"") -> RMLX175 | F53: =IFERROR(_xlfn.XLOOKUP(D53,HELPER!$B:$B,HELPER!$D:$D,""),"") -> Resin 1A | G53: 8 | H53: 0.144 | I53: =IF(AND(H53<>"",IFERROR(_xlfn.XLOOKUP(D53,HELPER!$B:$B,HELPER!$E:$E,""),"")=""),"Missing price",IFERROR(_xlfn.XLOOKUP(D53,HELPER!$B:$B,HELPER!$E:$E,"")," ")) -> 3.17 | J53: =IFERROR(H53*(IF(G53=8,I53*HELPER!$G$2,BOM!I53*HELPER!$G$3))," ") -> 0.091296 | L53: {=IFERROR(_xlfn.LET(_xlpm.films,Table4[Film],_xlpm.grades,Table4[Grade],_xlpm.pairs,_xlfn._xlws.FILTER(_xlfn.HSTACK(_xlpm.films,_xlpm.grades),(_xlpm.films<>"")*(TRIM(_xlpm.grades)<>"")),_xlpm.uniquePairs,_xlfn.UNIQUE(_xlpm.pairs),_xlpm.sortedPairs,_xlfn._xlws.SORT(_xlpm.uniquePairs,1,1),INDEX(_xlpm.sortedPairs,ROWS($L$2:L53),1)),"")} -> TIPA 312MFGW | M53: {=IFERROR(_xlfn.LET(_xlpm.films,Table4[Film],_xlpm.grades,Table4[Grade],_xlpm.pairs,_xlfn._xlws.FILTER(_xlfn.HSTACK(_xlpm.films,_xlpm.grades),(_xlpm.films<>"")*(TRIM(_xlpm.grades)<>"")),_xlpm.uniquePairs,_xlfn.UNIQUE(_xlpm.pairs),_xlpm.sortedPairs,_xlfn._xlws.SORT(_xlpm.uniquePairs,1,1),INDEX(_xlpm.sortedPairs,ROWS($M$2:M53),2)),"")} -> P65D | N53: {=IF(OR(Table2[[#This Row],[Film]]="",Table2[[#This Row],[Grade]]=""),"",IFERROR(INDEX(Table4[Serial Number],MATCH(1,(Table4[Film]=Table2[[#This Row],[Film]])*(Table4[Grade]=Table2[[#This Row],[Grade]]),0)),""))} -> RMP65D | O53: =IF(OR(Table2[[#This Row],[Film]]="",Table2[[#This Row],[Grade]]=""),"",SUMIFS(Table4[Price Calculated(€) Thickness & QTY related],Table4[Film],Table2[[#This Row],[Film]],Table4[Grade],Table2[[#This Row],[Grade]])) -> 0.2774 | U53: TIPA 312MFGW | V53: PLA | W53: LX175 | X53: RMLX175 | Y53: Resin 1A | Z53: {=SUMPRODUCT((BOM!$A$2:$A$391=U53)*(BOM!$F$2:$F$391=Y53)*BOM!$H$2:$H$391*BOM!$G$2:$G$391)/SUMPRODUCT((BOM!$A$2:$A$391=U53)*BOM!$H$2:$H$391*BOM!$G$2:$G$391)} -> 0.1874 | AA53: =SUMIF(tblResinWeightedQty12[Film],tblResinWeightedQty12[[#This Row],[Film]],tblResinWeightedQty12[Weighted QTY %]) -> 1
A54: TIPA 302FG W | B54: Ext. C (In) | C54: AB-PLA | D54: =IF(C54="","",IFERROR(_xlfn.XLOOKUP(C54,HELPER!$A$2:$A$81,HELPER!$B$2:$B$81,""),D54)) -> KAB59A | E54: =IFERROR(_xlfn.XLOOKUP(D54,HELPER!$B:$B,HELPER!$C:$C,""),"") -> RM A KAB59A | F54: =IFERROR(_xlfn.XLOOKUP(D54,HELPER!$B:$B,HELPER!$D:$D,""),"") -> Resin 8 | G54: 8 | H54: 0.015 | I54: =IF(AND(H54<>"",IFERROR(_xlfn.XLOOKUP(D54,HELPER!$B:$B,HELPER!$E:$E,""),"")=""),"Missing price",IFERROR(_xlfn.XLOOKUP(D54,HELPER!$B:$B,HELPER!$E:$E,"")," ")) -> 7.55 | J54: =IFERROR(H54*(IF(G54=8,I54*HELPER!$G$2,BOM!I54*HELPER!$G$3))," ") -> 0.02265 | L54: {=IFERROR(_xlfn.LET(_xlpm.films,Table4[Film],_xlpm.grades,Table4[Grade],_xlpm.pairs,_xlfn._xlws.FILTER(_xlfn.HSTACK(_xlpm.films,_xlpm.grades),(_xlpm.films<>"")*(TRIM(_xlpm.grades)<>"")),_xlpm.uniquePairs,_xlfn.UNIQUE(_xlpm.pairs),_xlpm.sortedPairs,_xlfn._xlws.SORT(_xlpm.uniquePairs,1,1),INDEX(_xlpm.sortedPairs,ROWS($L$2:L54),1)),"")} -> TIPA 312MFGW | M54: {=IFERROR(_xlfn.LET(_xlpm.films,Table4[Film],_xlpm.grades,Table4[Grade],_xlpm.pairs,_xlfn._xlws.FILTER(_xlfn.HSTACK(_xlpm.films,_xlpm.grades),(_xlpm.films<>"")*(TRIM(_xlpm.grades)<>"")),_xlpm.uniquePairs,_xlfn.UNIQUE(_xlpm.pairs),_xlpm.sortedPairs,_xlfn._xlws.SORT(_xlpm.uniquePairs,1,1),INDEX(_xlpm.sortedPairs,ROWS($M$2:M54),2)),"")} -> S723 | N54: {=IF(OR(Table2[[#This Row],[Film]]="",Table2[[#This Row],[Grade]]=""),"",IFERROR(INDEX(Table4[Serial Number],MATCH(1,(Table4[Film]=Table2[[#This Row],[Film]])*(Table4[Grade]=Table2[[#This Row],[Grade]]),0)),""))} -> RM TA45-08 S723 | O54: =IF(OR(Table2[[#This Row],[Film]]="",Table2[[#This Row],[Grade]]=""),"",SUMIFS(Table4[Price Calculated(€) Thickness & QTY related],Table4[Film],Table2[[#This Row],[Film]],Table4[Grade],Table2[[#This Row],[Grade]])) -> 0.2424 | U54: TIPA 312MFGW | V54: PBAT | W54: B12 | X54: RMB12 | Y54: Resin 2A | Z54: {=SUMPRODUCT((BOM!$A$2:$A$391=U54)*(BOM!$F$2:$F$391=Y54)*BOM!$H$2:$H$391*BOM!$G$2:$G$391)/SUMPRODUCT((BOM!$A$2:$A$391=U54)*BOM!$H$2:$H$391*BOM!$G$2:$G$391)} -> 0.531 | AA54: =SUMIF(tblResinWeightedQty12[Film],tblResinWeightedQty12[[#This Row],[Film]],tblResinWeightedQty12[Weighted QTY %]) -> 1
A55: TIPA 302FG W | B55: Ext. C (In) | C55: AO-PBS | D55: =IF(C55="","",IFERROR(_xlfn.XLOOKUP(C55,HELPER!$A$2:$A$81,HELPER!$B$2:$B$81,""),D55)) -> S723 | E55: =IFERROR(_xlfn.XLOOKUP(D55,HELPER!$B:$B,HELPER!$C:$C,""),"") -> RM TA45-08 S723 | F55: =IFERROR(_xlfn.XLOOKUP(D55,HELPER!$B:$B,HELPER!$D:$D,""),"") -> Resin 6 | G55: 8 | H55: 0.015 | I55: =IF(AND(H55<>"",IFERROR(_xlfn.XLOOKUP(D55,HELPER!$B:$B,HELPER!$E:$E,""),"")=""),"Missing price",IFERROR(_xlfn.XLOOKUP(D55,HELPER!$B:$B,HELPER!$E:$E,"")," ")) -> 16.16 | J55: =IFERROR(H55*(IF(G55=8,I55*HELPER!$G$2,BOM!I55*HELPER!$G$3))," ") -> 0.04848 | L55: {=IFERROR(_xlfn.LET(_xlpm.films,Table4[Film],_xlpm.grades,Table4[Grade],_xlpm.pairs,_xlfn._xlws.FILTER(_xlfn.HSTACK(_xlpm.films,_xlpm.grades),(_xlpm.films<>"")*(TRIM(_xlpm.grades)<>"")),_xlpm.uniquePairs,_xlfn.UNIQUE(_xlpm.pairs),_xlpm.sortedPairs,_xlfn._xlws.SORT(_xlpm.uniquePairs,1,1),INDEX(_xlpm.sortedPairs,ROWS($L$2:L55),1)),"")} -> TIPA 312MFGW | M55: {=IFERROR(_xlfn.LET(_xlpm.films,Table4[Film],_xlpm.grades,Table4[Grade],_xlpm.pairs,_xlfn._xlws.FILTER(_xlfn.HSTACK(_xlpm.films,_xlpm.grades),(_xlpm.films<>"")*(TRIM(_xlpm.grades)<>"")),_xlpm.uniquePairs,_xlfn.UNIQUE(_xlpm.pairs),_xlpm.sortedPairs,_xlfn._xlws.SORT(_xlpm.uniquePairs,1,1),INDEX(_xlpm.sortedPairs,ROWS($M$2:M55),2)),"")} -> RM WHITE BIO8153 | N55: {=IF(OR(Table2[[#This Row],[Film]]="",Table2[[#This Row],[Grade]]=""),"",IFERROR(INDEX(Table4[Serial Number],MATCH(1,(Table4[Film]=Table2[[#This Row],[Film]])*(Table4[Grade]=Table2[[#This Row],[Grade]]),0)),""))} -> RM WHITE BIO8153 | O55: =IF(OR(Table2[[#This Row],[Film]]="",Table2[[#This Row],[Grade]]=""),"",SUMIFS(Table4[Price Calculated(€) Thickness & QTY related],Table4[Film],Table2[[#This Row],[Film]],Table4[Grade],Table2[[#This Row],[Grade]])) -> 0.369 | U55: TIPA 312MFGW | V55: PCL | W55: P65D | X55: RMP65D | Y55: Resin 4A | Z55: {=SUMPRODUCT((BOM!$A$2:$A$391=U55)*(BOM!$F$2:$F$391=Y55)*BOM!$H$2:$H$391*BOM!$G$2:$G$391)/SUMPRODUCT((BOM!$A$2:$A$391=U55)*BOM!$H$2:$H$391*BOM!$G$2:$G$391)} -> 0.038 | AA55: =SUMIF(tblResinWeightedQty12[Film],tblResinWeightedQty12[[#This Row],[Film]],tblResinWeightedQty12[Weighted QTY %]) -> 1
A56: TIPA 302FG W | B56: Ext. C (In) | C56: SLAB-PBSA | D56: =IF(C56="","",IFERROR(_xlfn.XLOOKUP(C56,HELPER!$A$2:$A$81,HELPER!$B$2:$B$81,""),D56)) -> S724 | E56: =IFERROR(_xlfn.XLOOKUP(D56,HELPER!$B:$B,HELPER!$C:$C,""),"") -> RM TA45-08 S724 | F56: =IFERROR(_xlfn.XLOOKUP(D56,HELPER!$B:$B,HELPER!$D:$D,""),"") -> Resin 7 | G56: 8 | H56: 0.016 | I56: =IF(AND(H56<>"",IFERROR(_xlfn.XLOOKUP(D56,HELPER!$B:$B,HELPER!$E:$E,""),"")=""),"Missing price",IFERROR(_xlfn.XLOOKUP(D56,HELPER!$B:$B,HELPER!$E:$E,"")," ")) -> 14.7 | J56: =IFERROR(H56*(IF(G56=8,I56*HELPER!$G$2,BOM!I56*HELPER!$G$3))," ") -> 0.04704 | L56: {=IFERROR(_xlfn.LET(_xlpm.films,Table4[Film],_xlpm.grades,Table4[Grade],_xlpm.pairs,_xlfn._xlws.FILTER(_xlfn.HSTACK(_xlpm.films,_xlpm.grades),(_xlpm.films<>"")*(TRIM(_xlpm.grades)<>"")),_xlpm.uniquePairs,_xlfn.UNIQUE(_xlpm.pairs),_xlpm.sortedPairs,_xlfn._xlws.SORT(_xlpm.uniquePairs,1,1),INDEX(_xlpm.sortedPairs,ROWS($L$2:L56),1)),"")} -> TIPA 312MFGW | M56: {=IFERROR(_xlfn.LET(_xlpm.films,Table4[Film],_xlpm.grades,Table4[Grade],_xlpm.pairs,_xlfn._xlws.FILTER(_xlfn.HSTACK(_xlpm.films,_xlpm.grades),(_xlpm.films<>"")*(TRIM(_xlpm.grades)<>"")),_xlpm.uniquePairs,_xlfn.UNIQUE(_xlpm.pairs),_xlpm.sortedPairs,_xlfn._xlws.SORT(_xlpm.uniquePairs,1,1),INDEX(_xlpm.sortedPairs,ROWS($M$2:M56),2)),"")} -> B12 | N56: {=IF(OR(Table2[[#This Row],[Film]]="",Table2[[#This Row],[Grade]]=""),"",IFERROR(INDEX(Table4[Serial Number],MATCH(1,(Table4[Film]=Table2[[#This Row],[Film]])*(Table4[Grade]=Table2[[#This Row],[Grade]]),0)),""))} -> RMB12 | O56: =IF(OR(Table2[[#This Row],[Film]]="",Table2[[#This Row],[Grade]]=""),"",SUMIFS(Table4[Price Calculated(€) Thickness & QTY related],Table4[Film],Table2[[#This Row],[Film]],Table4[Grade],Table2[[#This Row],[Grade]])) -> 0.96111 | U56: TIPA 312MFGW | V56: AO-PBS | W56: S723 | X56: RM TA45-08 S723 | Y56: Resin 6 | Z56: {=SUMPRODUCT((BOM!$A$2:$A$391=U56)*(BOM!$F$2:$F$391=Y56)*BOM!$H$2:$H$391*BOM!$G$2:$G$391)/SUMPRODUCT((BOM!$A$2:$A$391=U56)*BOM!$H$2:$H$391*BOM!$G$2:$G$391)} -> 0.015 | AA56: =SUMIF(tblResinWeightedQty12[Film],tblResinWeightedQty12[[#This Row],[Film]],tblResinWeightedQty12[Weighted QTY %]) -> 1
A57: TIPA 302FG W | B57: Ext. C (In) | D57: =IF(C57="","",IFERROR(_xlfn.XLOOKUP(C57,HELPER!$A$2:$A$81,HELPER!$B$2:$B$81,""),D57)) | E57: =IFERROR(_xlfn.XLOOKUP(D57,HELPER!$B:$B,HELPER!$C:$C,""),"") | F57: =IFERROR(_xlfn.XLOOKUP(D57,HELPER!$B:$B,HELPER!$D:$D,""),"") | G57: 8 | I57: =IF(AND(H57<>"",IFERROR(_xlfn.XLOOKUP(D57,HELPER!$B:$B,HELPER!$E:$E,""),"")=""),"Missing price",IFERROR(_xlfn.XLOOKUP(D57,HELPER!$B:$B,HELPER!$E:$E,"")," ")) | J57: =IFERROR(H57*(IF(G57=8,I57*HELPER!$G$2,BOM!I57*HELPER!$G$3))," ") | L57: {=IFERROR(_xlfn.LET(_xlpm.films,Table4[Film],_xlpm.grades,Table4[Grade],_xlpm.pairs,_xlfn._xlws.FILTER(_xlfn.HSTACK(_xlpm.films,_xlpm.grades),(_xlpm.films<>"")*(TRIM(_xlpm.grades)<>"")),_xlpm.uniquePairs,_xlfn.UNIQUE(_xlpm.pairs),_xlpm.sortedPairs,_xlfn._xlws.SORT(_xlpm.uniquePairs,1,1),INDEX(_xlpm.sortedPairs,ROWS($L$2:L57),1)),"")} -> TIPA 312MFGW | M57: {=IFERROR(_xlfn.LET(_xlpm.films,Table4[Film],_xlpm.grades,Table4[Grade],_xlpm.pairs,_xlfn._xlws.FILTER(_xlfn.HSTACK(_xlpm.films,_xlpm.grades),(_xlpm.films<>"")*(TRIM(_xlpm.grades)<>"")),_xlpm.uniquePairs,_xlfn.UNIQUE(_xlpm.pairs),_xlpm.sortedPairs,_xlfn._xlws.SORT(_xlpm.uniquePairs,1,1),INDEX(_xlpm.sortedPairs,ROWS($M$2:M57),2)),"")} -> FD92PM | N57: {=IF(OR(Table2[[#This Row],[Film]]="",Table2[[#This Row],[Grade]]=""),"",IFERROR(INDEX(Table4[Serial Number],MATCH(1,(Table4[Film]=Table2[[#This Row],[Film]])*(Table4[Grade]=Table2[[#This Row],[Grade]]),0)),""))} -> RMPM2 | O57: =IF(OR(Table2[[#This Row],[Film]]="",Table2[[#This Row],[Grade]]=""),"",SUMIFS(Table4[Price Calculated(€) Thickness & QTY related],Table4[Film],Table2[[#This Row],[Film]],Table4[Grade],Table2[[#This Row],[Grade]])) -> 1.08675 | U57: TIPA 312MFGW | V57: SLAB-PBSA | W57: S724 | X57: RM TA45-08 S724 | Y57: Resin 7 | Z57: {=SUMPRODUCT((BOM!$A$2:$A$391=U57)*(BOM!$F$2:$F$391=Y57)*BOM!$H$2:$H$391*BOM!$G$2:$G$391)/SUMPRODUCT((BOM!$A$2:$A$391=U57)*BOM!$H$2:$H$391*BOM!$G$2:$G$391)} -> 0.0046 | AA57: =SUMIF(tblResinWeightedQty12[Film],tblResinWeightedQty12[[#This Row],[Film]],tblResinWeightedQty12[Weighted QTY %]) -> 1
A58: TIPA 302FG W | B58: Ext. C (In) | D58: =IF(C58="","",IFERROR(_xlfn.XLOOKUP(C58,HELPER!$A$2:$A$81,HELPER!$B$2:$B$81,""),D58)) | E58: =IFERROR(_xlfn.XLOOKUP(D58,HELPER!$B:$B,HELPER!$C:$C,""),"") | F58: =IFERROR(_xlfn.XLOOKUP(D58,HELPER!$B:$B,HELPER!$D:$D,""),"") | G58: 8 | I58: =IF(AND(H58<>"",IFERROR(_xlfn.XLOOKUP(D58,HELPER!$B:$B,HELPER!$E:$E,""),"")=""),"Missing price",IFERROR(_xlfn.XLOOKUP(D58,HELPER!$B:$B,HELPER!$E:$E,"")," ")) | J58: =IFERROR(H58*(IF(G58=8,I58*HELPER!$G$2,BOM!I58*HELPER!$G$3))," ") | L58: {=IFERROR(_xlfn.LET(_xlpm.films,Table4[Film],_xlpm.grades,Table4[Grade],_xlpm.pairs,_xlfn._xlws.FILTER(_xlfn.HSTACK(_xlpm.films,_xlpm.grades),(_xlpm.films<>"")*(TRIM(_xlpm.grades)<>"")),_xlpm.uniquePairs,_xlfn.UNIQUE(_xlpm.pairs),_xlpm.sortedPairs,_xlfn._xlws.SORT(_xlpm.uniquePairs,1,1),INDEX(_xlpm.sortedPairs,ROWS($L$2:L58),1)),"")} -> TIPA 312MFGW | M58: {=IFERROR(_xlfn.LET(_xlpm.films,Table4[Film],_xlpm.grades,Table4[Grade],_xlpm.pairs,_xlfn._xlws.FILTER(_xlfn.HSTACK(_xlpm.films,_xlpm.grades),(_xlpm.films<>"")*(TRIM(_xlpm.grades)<>"")),_xlpm.uniquePairs,_xlfn.UNIQUE(_xlpm.pairs),_xlpm.sortedPairs,_xlfn._xlws.SORT(_xlpm.uniquePairs,1,1),INDEX(_xlpm.sortedPairs,ROWS($M$2:M58),2)),"")} -> KAB59A | N58: {=IF(OR(Table2[[#This Row],[Film]]="",Table2[[#This Row],[Grade]]=""),"",IFERROR(INDEX(Table4[Serial Number],MATCH(1,(Table4[Film]=Table2[[#This Row],[Film]])*(Table4[Grade]=Table2[[#This Row],[Grade]]),0)),""))} -> RM A KAB59A | O58: =IF(OR(Table2[[#This Row],[Film]]="",Table2[[#This Row],[Grade]]=""),"",SUMIFS(Table4[Price Calculated(€) Thickness & QTY related],Table4[Film],Table2[[#This Row],[Film]],Table4[Grade],Table2[[#This Row],[Grade]])) -> 0.02265 | U58: TIPA 312MFGW | V58: AB-PLA | W58: KAB59A | X58: RM A KAB59A | Y58: Resin 8 | Z58: {=SUMPRODUCT((BOM!$A$2:$A$391=U58)*(BOM!$F$2:$F$391=Y58)*BOM!$H$2:$H$391*BOM!$G$2:$G$391)/SUMPRODUCT((BOM!$A$2:$A$391=U58)*BOM!$H$2:$H$391*BOM!$G$2:$G$391)} -> 0.003 | AA58: =SUMIF(tblResinWeightedQty12[Film],tblResinWeightedQty12[[#This Row],[Film]],tblResinWeightedQty12[Weighted QTY %]) -> 1
A59: TIPA 302FG W | B59: Ext. C (In) | D59: =IF(C59="","",IFERROR(_xlfn.XLOOKUP(C59,HELPER!$A$2:$A$81,HELPER!$B$2:$B$81,""),D59)) | E59: =IFERROR(_xlfn.XLOOKUP(D59,HELPER!$B:$B,HELPER!$C:$C,""),"") | F59: =IFERROR(_xlfn.XLOOKUP(D59,HELPER!$B:$B,HELPER!$D:$D,""),"") | G59: 8 | I59: =IF(AND(H59<>"",IFERROR(_xlfn.XLOOKUP(D59,HELPER!$B:$B,HELPER!$E:$E,""),"")=""),"Missing price",IFERROR(_xlfn.XLOOKUP(D59,HELPER!$B:$B,HELPER!$E:$E,"")," ")) | J59: =IFERROR(H59*(IF(G59=8,I59*HELPER!$G$2,BOM!I59*HELPER!$G$3))," ") | L59: {=IFERROR(_xlfn.LET(_xlpm.films,Table4[Film],_xlpm.grades,Table4[Grade],_xlpm.pairs,_xlfn._xlws.FILTER(_xlfn.HSTACK(_xlpm.films,_xlpm.grades),(_xlpm.films<>"")*(TRIM(_xlpm.grades)<>"")),_xlpm.uniquePairs,_xlfn.UNIQUE(_xlpm.pairs),_xlpm.sortedPairs,_xlfn._xlws.SORT(_xlpm.uniquePairs,1,1),INDEX(_xlpm.sortedPairs,ROWS($L$2:L59),1)),"")} -> TIPA 312MFGW | M59: {=IFERROR(_xlfn.LET(_xlpm.films,Table4[Film],_xlpm.grades,Table4[Grade],_xlpm.pairs,_xlfn._xlws.FILTER(_xlfn.HSTACK(_xlpm.films,_xlpm.grades),(_xlpm.films<>"")*(TRIM(_xlpm.grades)<>"")),_xlpm.uniquePairs,_xlfn.UNIQUE(_xlpm.pairs),_xlpm.sortedPairs,_xlfn._xlws.SORT(_xlpm.uniquePairs,1,1),INDEX(_xlpm.sortedPairs,ROWS($M$2:M59),2)),"")} -> S724 | N59: {=IF(OR(Table2[[#This Row],[Film]]="",Table2[[#This Row],[Grade]]=""),"",IFERROR(INDEX(Table4[Serial Number],MATCH(1,(Table4[Film]=Table2[[#This Row],[Film]])*(Table4[Grade]=Table2[[#This Row],[Grade]]),0)),""))} -> RM TA45-08 S724 | O59: =IF(OR(Table2[[#This Row],[Film]]="",Table2[[#This Row],[Grade]]=""),"",SUMIFS(Table4[Price Calculated(€) Thickness & QTY related],Table4[Film],Table2[[#This Row],[Film]],Table4[Grade],Table2[[#This Row],[Grade]])) -> 0.06762 | U59: TIPA 312MFGW | V59: PBSA | W59: FD92PM | X59: RMPM2 | Y59: Resin 9C | Z59: {=SUMPRODUCT((BOM!$A$2:$A$391=U59)*(BOM!$F$2:$F$391=Y59)*BOM!$H$2:$H$391*BOM!$G$2:$G$391)/SUMPRODUCT((BOM!$A$2:$A$391=U59)*BOM!$H$2:$H$391*BOM!$G$2:$G$391)} -> 0.161 | AA59: =SUMIF(tblResinWeightedQty12[Film],tblResinWeightedQty12[[#This Row],[Film]],tblResinWeightedQty12[Weighted QTY %]) -> 1
A60: TIPA 302FG W | B60: Ext. C (In) | D60: =IF(C60="","",IFERROR(_xlfn.XLOOKUP(C60,HELPER!$A$2:$A$81,HELPER!$B$2:$B$81,""),D60)) | E60: =IFERROR(_xlfn.XLOOKUP(D60,HELPER!$B:$B,HELPER!$C:$C,""),"") | F60: =IFERROR(_xlfn.XLOOKUP(D60,HELPER!$B:$B,HELPER!$D:$D,""),"") | G60: 8 | I60: =IF(AND(H60<>"",IFERROR(_xlfn.XLOOKUP(D60,HELPER!$B:$B,HELPER!$E:$E,""),"")=""),"Missing price",IFERROR(_xlfn.XLOOKUP(D60,HELPER!$B:$B,HELPER!$E:$E,"")," ")) | J60: =IFERROR(H60*(IF(G60=8,I60*HELPER!$G$2,BOM!I60*HELPER!$G$3))," ") | L60: {=IFERROR(_xlfn.LET(_xlpm.films,Table4[Film],_xlpm.grades,Table4[Grade],_xlpm.pairs,_xlfn._xlws.FILTER(_xlfn.HSTACK(_xlpm.films,_xlpm.grades),(_xlpm.films<>"")*(TRIM(_xlpm.grades)<>"")),_xlpm.uniquePairs,_xlfn.UNIQUE(_xlpm.pairs),_xlpm.sortedPairs,_xlfn._xlws.SORT(_xlpm.uniquePairs,1,1),INDEX(_xlpm.sortedPairs,ROWS($L$2:L60),1)),"")} | M60: {=IFERROR(_xlfn.LET(_xlpm.films,Table4[Film],_xlpm.grades,Table4[Grade],_xlpm.pairs,_xlfn._xlws.FILTER(_xlfn.HSTACK(_xlpm.films,_xlpm.grades),(_xlpm.films<>"")*(TRIM(_xlpm.grades)<>"")),_xlpm.uniquePairs,_xlfn.UNIQUE(_xlpm.pairs),_xlpm.sortedPairs,_xlfn._xlws.SORT(_xlpm.uniquePairs,1,1),INDEX(_xlpm.sortedPairs,ROWS($M$2:M60),2)),"")} | N60: {=IF(OR(Table2[[#This Row],[Film]]="",Table2[[#This Row],[Grade]]=""),"",IFERROR(INDEX(Table4[Serial Number],MATCH(1,(Table4[Film]=Table2[[#This Row],[Film]])*(Table4[Grade]=Table2[[#This Row],[Grade]]),0)),""))} | O60: =IF(OR(Table2[[#This Row],[Film]]="",Table2[[#This Row],[Grade]]=""),"",SUMIFS(Table4[Price Calculated(€) Thickness & QTY related],Table4[Film],Table2[[#This Row],[Film]],Table4[Grade],Table2[[#This Row],[Grade]]))
A61: TIPA 302FG W | B61: Ext. C (In) | D61: =IF(C61="","",IFERROR(_xlfn.XLOOKUP(C61,HELPER!$A$2:$A$81,HELPER!$B$2:$B$81,""),D61)) | E61: =IFERROR(_xlfn.XLOOKUP(D61,HELPER!$B:$B,HELPER!$C:$C,""),"") | F61: =IFERROR(_xlfn.XLOOKUP(D61,HELPER!$B:$B,HELPER!$D:$D,""),"") | G61: 8 | I61: =IF(AND(H61<>"",IFERROR(_xlfn.XLOOKUP(D61,HELPER!$B:$B,HELPER!$E:$E,""),"")=""),"Missing price",IFERROR(_xlfn.XLOOKUP(D61,HELPER!$B:$B,HELPER!$E:$E,"")," ")) | J61: =IFERROR(H61*(IF(G61=8,I61*HELPER!$G$2,BOM!I61*HELPER!$G$3))," ") | L61: {=IFERROR(_xlfn.LET(_xlpm.films,Table4[Film],_xlpm.grades,Table4[Grade],_xlpm.pairs,_xlfn._xlws.FILTER(_xlfn.HSTACK(_xlpm.films,_xlpm.grades),(_xlpm.films<>"")*(TRIM(_xlpm.grades)<>"")),_xlpm.uniquePairs,_xlfn.UNIQUE(_xlpm.pairs),_xlpm.sortedPairs,_xlfn._xlws.SORT(_xlpm.uniquePairs,1,1),INDEX(_xlpm.sortedPairs,ROWS($L$2:L61),1)),"")} | M61: {=IFERROR(_xlfn.LET(_xlpm.films,Table4[Film],_xlpm.grades,Table4[Grade],_xlpm.pairs,_xlfn._xlws.FILTER(_xlfn.HSTACK(_xlpm.films,_xlpm.grades),(_xlpm.films<>"")*(TRIM(_xlpm.grades)<>"")),_xlpm.uniquePairs,_xlfn.UNIQUE(_xlpm.pairs),_xlpm.sortedPairs,_xlfn._xlws.SORT(_xlpm.uniquePairs,1,1),INDEX(_xlpm.sortedPairs,ROWS($M$2:M61),2)),"")} | N61: {=IF(OR(Table2[[#This Row],[Film]]="",Table2[[#This Row],[Grade]]=""),"",IFERROR(INDEX(Table4[Serial Number],MATCH(1,(Table4[Film]=Table2[[#This Row],[Film]])*(Table4[Grade]=Table2[[#This Row],[Grade]]),0)),""))} | O61: =IF(OR(Table2[[#This Row],[Film]]="",Table2[[#This Row],[Grade]]=""),"",SUMIFS(Table4[Price Calculated(€) Thickness & QTY related],Table4[Film],Table2[[#This Row],[Film]],Table4[Grade],Table2[[#This Row],[Grade]]))
A62: TIPA 312 MFG | B62: Ext. A (Out - Chillroll) | C62: PLA | D62: =IF(C62="","",IFERROR(_xlfn.XLOOKUP(C62,HELPER!$A$2:$A$81,HELPER!$B$2:$B$81,""),D62)) -> LX175 | E62: =IFERROR(_xlfn.XLOOKUP(D62,HELPER!$B:$B,HELPER!$C:$C,""),"") -> RMLX175 | F62: =IFERROR(_xlfn.XLOOKUP(D62,HELPER!$B:$B,HELPER!$D:$D,""),"") -> Resin 1A | G62: 8 | H62: 0.795 | I62: =IF(AND(H62<>"",IFERROR(_xlfn.XLOOKUP(D62,HELPER!$B:$B,HELPER!$E:$E,""),"")=""),"Missing price",IFERROR(_xlfn.XLOOKUP(D62,HELPER!$B:$B,HELPER!$E:$E,"")," ")) -> 3.17 | J62: =IFERROR(H62*(IF(G62=8,I62*HELPER!$G$2,BOM!I62*HELPER!$G$3))," ") -> 0.50403 | L62: {=IFERROR(_xlfn.LET(_xlpm.films,Table4[Film],_xlpm.grades,Table4[Grade],_xlpm.pairs,_xlfn._xlws.FILTER(_xlfn.HSTACK(_xlpm.films,_xlpm.grades),(_xlpm.films<>"")*(TRIM(_xlpm.grades)<>"")),_xlpm.uniquePairs,_xlfn.UNIQUE(_xlpm.pairs),_xlpm.sortedPairs,_xlfn._xlws.SORT(_xlpm.uniquePairs,1,1),INDEX(_xlpm.sortedPairs,ROWS($L$2:L62),1)),"")} | M62: {=IFERROR(_xlfn.LET(_xlpm.films,Table4[Film],_xlpm.grades,Table4[Grade],_xlpm.pairs,_xlfn._xlws.FILTER(_xlfn.HSTACK(_xlpm.films,_xlpm.grades),(_xlpm.films<>"")*(TRIM(_xlpm.grades)<>"")),_xlpm.uniquePairs,_xlfn.UNIQUE(_xlpm.pairs),_xlpm.sortedPairs,_xlfn._xlws.SORT(_xlpm.uniquePairs,1,1),INDEX(_xlpm.sortedPairs,ROWS($M$2:M62),2)),"")} | N62: {=IF(OR(Table2[[#This Row],[Film]]="",Table2[[#This Row],[Grade]]=""),"",IFERROR(INDEX(Table4[Serial Number],MATCH(1,(Table4[Film]=Table2[[#This Row],[Film]])*(Table4[Grade]=Table2[[#This Row],[Grade]]),0)),""))} | O62: =IF(OR(Table2[[#This Row],[Film]]="",Table2[[#This Row],[Grade]]=""),"",SUMIFS(Table4[Price Calculated(€) Thickness & QTY related],Table4[Film],Table2[[#This Row],[Film]],Table4[Grade],Table2[[#This Row],[Grade]]))
A63: TIPA 312 MFG | B63: Ext. A (Out - Chillroll) | C63: PCL | D63: =IF(C63="","",IFERROR(_xlfn.XLOOKUP(C63,HELPER!$A$2:$A$81,HELPER!$B$2:$B$81,""),D63)) -> P65D | E63: =IFERROR(_xlfn.XLOOKUP(D63,HELPER!$B:$B,HELPER!$C:$C,""),"") -> RMP65D | F63: =IFERROR(_xlfn.XLOOKUP(D63,HELPER!$B:$B,HELPER!$D:$D,""),"") -> Resin 4A | G63: 8 | H63: 0.19 | I63: =IF(AND(H63<>"",IFERROR(_xlfn.XLOOKUP(D63,HELPER!$B:$B,HELPER!$E:$E,""),"")=""),"Missing price",IFERROR(_xlfn.XLOOKUP(D63,HELPER!$B:$B,HELPER!$E:$E,"")," ")) -> 7.3 | J63: =IFERROR(H63*(IF(G63=8,I63*HELPER!$G$2,BOM!I63*HELPER!$G$3))," ") -> 0.2774 | L63: {=IFERROR(_xlfn.LET(_xlpm.films,Table4[Film],_xlpm.grades,Table4[Grade],_xlpm.pairs,_xlfn._xlws.FILTER(_xlfn.HSTACK(_xlpm.films,_xlpm.grades),(_xlpm.films<>"")*(TRIM(_xlpm.grades)<>"")),_xlpm.uniquePairs,_xlfn.UNIQUE(_xlpm.pairs),_xlpm.sortedPairs,_xlfn._xlws.SORT(_xlpm.uniquePairs,1,1),INDEX(_xlpm.sortedPairs,ROWS($L$2:L63),1)),"")} | M63: {=IFERROR(_xlfn.LET(_xlpm.films,Table4[Film],_xlpm.grades,Table4[Grade],_xlpm.pairs,_xlfn._xlws.FILTER(_xlfn.HSTACK(_xlpm.films,_xlpm.grades),(_xlpm.films<>"")*(TRIM(_xlpm.grades)<>"")),_xlpm.uniquePairs,_xlfn.UNIQUE(_xlpm.pairs),_xlpm.sortedPairs,_xlfn._xlws.SORT(_xlpm.uniquePairs,1,1),INDEX(_xlpm.sortedPairs,ROWS($M$2:M63),2)),"")} | N63: {=IF(OR(Table2[[#This Row],[Film]]="",Table2[[#This Row],[Grade]]=""),"",IFERROR(INDEX(Table4[Serial Number],MATCH(1,(Table4[Film]=Table2[[#This Row],[Film]])*(Table4[Grade]=Table2[[#This Row],[Grade]]),0)),""))} | O63: =IF(OR(Table2[[#This Row],[Film]]="",Table2[[#This Row],[Grade]]=""),"",SUMIFS(Table4[Price Calculated(€) Thickness & QTY related],Table4[Film],Table2[[#This Row],[Film]],Table4[Grade],Table2[[#This Row],[Grade]]))
A64: TIPA 312 MFG | B64: Ext. A (Out - Chillroll) | C64: AO-PBS | D64: =IF(C64="","",IFERROR(_xlfn.XLOOKUP(C64,HELPER!$A$2:$A$81,HELPER!$B$2:$B$81,""),D64)) -> S723 | E64: =IFERROR(_xlfn.XLOOKUP(D64,HELPER!$B:$B,HELPER!$C:$C,""),"") -> RM TA45-08 S723 | F64: =IFERROR(_xlfn.XLOOKUP(D64,HELPER!$B:$B,HELPER!$D:$D,""),"") -> Resin 6 | G64: 8 | H64: 0.015 | I64: =IF(AND(H64<>"",IFERROR(_xlfn.XLOOKUP(D64,HELPER!$B:$B,HELPER!$E:$E,""),"")=""),"Missing price",IFERROR(_xlfn.XLOOKUP(D64,HELPER!$B:$B,HELPER!$E:$E,"")," ")) -> 16.16 | J64: =IFERROR(H64*(IF(G64=8,I64*HELPER!$G$2,BOM!I64*HELPER!$G$3))," ") -> 0.04848 | L64: {=IFERROR(_xlfn.LET(_xlpm.films,Table4[Film],_xlpm.grades,Table4[Grade],_xlpm.pairs,_xlfn._xlws.FILTER(_xlfn.HSTACK(_xlpm.films,_xlpm.grades),(_xlpm.films<>"")*(TRIM(_xlpm.grades)<>"")),_xlpm.uniquePairs,_xlfn.UNIQUE(_xlpm.pairs),_xlpm.sortedPairs,_xlfn._xlws.SORT(_xlpm.uniquePairs,1,1),INDEX(_xlpm.sortedPairs,ROWS($L$2:L64),1)),"")} | M64: {=IFERROR(_xlfn.LET(_xlpm.films,Table4[Film],_xlpm.grades,Table4[Grade],_xlpm.pairs,_xlfn._xlws.FILTER(_xlfn.HSTACK(_xlpm.films,_xlpm.grades),(_xlpm.films<>"")*(TRIM(_xlpm.grades)<>"")),_xlpm.uniquePairs,_xlfn.UNIQUE(_xlpm.pairs),_xlpm.sortedPairs,_xlfn._xlws.SORT(_xlpm.uniquePairs,1,1),INDEX(_xlpm.sortedPairs,ROWS($M$2:M64),2)),"")} | N64: {=IF(OR(Table2[[#This Row],[Film]]="",Table2[[#This Row],[Grade]]=""),"",IFERROR(INDEX(Table4[Serial Number],MATCH(1,(Table4[Film]=Table2[[#This Row],[Film]])*(Table4[Grade]=Table2[[#This Row],[Grade]]),0)),""))} | O64: =IF(OR(Table2[[#This Row],[Film]]="",Table2[[#This Row],[Grade]]=""),"",SUMIFS(Table4[Price Calculated(€) Thickness & QTY related],Table4[Film],Table2[[#This Row],[Film]],Table4[Grade],Table2[[#This Row],[Grade]]))
A65: TIPA 312 MFG | B65: Ext. A (Out - Chillroll) | D65: =IF(C65="","",IFERROR(_xlfn.XLOOKUP(C65,HELPER!$A$2:$A$81,HELPER!$B$2:$B$81,""),D65)) | E65: =IFERROR(_xlfn.XLOOKUP(D65,HELPER!$B:$B,HELPER!$C:$C,""),"") | F65: =IFERROR(_xlfn.XLOOKUP(D65,HELPER!$B:$B,HELPER!$D:$D,""),"") | G65: 8 | I65: =IF(AND(H65<>"",IFERROR(_xlfn.XLOOKUP(D65,HELPER!$B:$B,HELPER!$E:$E,""),"")=""),"Missing price",IFERROR(_xlfn.XLOOKUP(D65,HELPER!$B:$B,HELPER!$E:$E,"")," ")) | J65: =IFERROR(H65*(IF(G65=8,I65*HELPER!$G$2,BOM!I65*HELPER!$G$3))," ") | L65: {=IFERROR(_xlfn.LET(_xlpm.films,Table4[Film],_xlpm.grades,Table4[Grade],_xlpm.pairs,_xlfn._xlws.FILTER(_xlfn.HSTACK(_xlpm.films,_xlpm.grades),(_xlpm.films<>"")*(TRIM(_xlpm.grades)<>"")),_xlpm.uniquePairs,_xlfn.UNIQUE(_xlpm.pairs),_xlpm.sortedPairs,_xlfn._xlws.SORT(_xlpm.uniquePairs,1,1),INDEX(_xlpm.sortedPairs,ROWS($L$2:L65),1)),"")} | M65: {=IFERROR(_xlfn.LET(_xlpm.films,Table4[Film],_xlpm.grades,Table4[Grade],_xlpm.pairs,_xlfn._xlws.FILTER(_xlfn.HSTACK(_xlpm.films,_xlpm.grades),(_xlpm.films<>"")*(TRIM(_xlpm.grades)<>"")),_xlpm.uniquePairs,_xlfn.UNIQUE(_xlpm.pairs),_xlpm.sortedPairs,_xlfn._xlws.SORT(_xlpm.uniquePairs,1,1),INDEX(_xlpm.sortedPairs,ROWS($M$2:M65),2)),"")} | N65: {=IF(OR(Table2[[#This Row],[Film]]="",Table2[[#This Row],[Grade]]=""),"",IFERROR(INDEX(Table4[Serial Number],MATCH(1,(Table4[Film]=Table2[[#This Row],[Film]])*(Table4[Grade]=Table2[[#This Row],[Grade]]),0)),""))} | O65: =IF(OR(Table2[[#This Row],[Film]]="",Table2[[#This Row],[Grade]]=""),"",SUMIFS(Table4[Price Calculated(€) Thickness & QTY related],Table4[Film],Table2[[#This Row],[Film]],Table4[Grade],Table2[[#This Row],[Grade]]))
A66: TIPA 312 MFG | B66: Ext. A (Out - Chillroll) | D66: =IF(C66="","",IFERROR(_xlfn.XLOOKUP(C66,HELPER!$A$2:$A$81,HELPER!$B$2:$B$81,""),D66)) | E66: =IFERROR(_xlfn.XLOOKUP(D66,HELPER!$B:$B,HELPER!$C:$C,""),"") | F66: =IFERROR(_xlfn.XLOOKUP(D66,HELPER!$B:$B,HELPER!$D:$D,""),"") | G66: 8 | I66: =IF(AND(H66<>"",IFERROR(_xlfn.XLOOKUP(D66,HELPER!$B:$B,HELPER!$E:$E,""),"")=""),"Missing price",IFERROR(_xlfn.XLOOKUP(D66,HELPER!$B:$B,HELPER!$E:$E,"")," ")) | J66: =IFERROR(H66*(IF(G66=8,I66*HELPER!$G$2,BOM!I66*HELPER!$G$3))," ") | L66: {=IFERROR(_xlfn.LET(_xlpm.films,Table4[Film],_xlpm.grades,Table4[Grade],_xlpm.pairs,_xlfn._xlws.FILTER(_xlfn.HSTACK(_xlpm.films,_xlpm.grades),(_xlpm.films<>"")*(TRIM(_xlpm.grades)<>"")),_xlpm.uniquePairs,_xlfn.UNIQUE(_xlpm.pairs),_xlpm.sortedPairs,_xlfn._xlws.SORT(_xlpm.uniquePairs,1,1),INDEX(_xlpm.sortedPairs,ROWS($L$2:L66),1)),"")} | M66: {=IFERROR(_xlfn.LET(_xlpm.films,Table4[Film],_xlpm.grades,Table4[Grade],_xlpm.pairs,_xlfn._xlws.FILTER(_xlfn.HSTACK(_xlpm.films,_xlpm.grades),(_xlpm.films<>"")*(TRIM(_xlpm.grades)<>"")),_xlpm.uniquePairs,_xlfn.UNIQUE(_xlpm.pairs),_xlpm.sortedPairs,_xlfn._xlws.SORT(_xlpm.uniquePairs,1,1),INDEX(_xlpm.sortedPairs,ROWS($M$2:M66),2)),"")} | N66: {=IF(OR(Table2[[#This Row],[Film]]="",Table2[[#This Row],[Grade]]=""),"",IFERROR(INDEX(Table4[Serial Number],MATCH(1,(Table4[Film]=Table2[[#This Row],[Film]])*(Table4[Grade]=Table2[[#This Row],[Grade]]),0)),""))} | O66: =IF(OR(Table2[[#This Row],[Film]]="",Table2[[#This Row],[Grade]]=""),"",SUMIFS(Table4[Price Calculated(€) Thickness & QTY related],Table4[Film],Table2[[#This Row],[Film]],Table4[Grade],Table2[[#This Row],[Grade]]))
A67: TIPA 312 MFG | B67: Ext. A (Out - Chillroll) | D67: =IF(C67="","",IFERROR(_xlfn.XLOOKUP(C67,HELPER!$A$2:$A$81,HELPER!$B$2:$B$81,""),D67)) | E67: =IFERROR(_xlfn.XLOOKUP(D67,HELPER!$B:$B,HELPER!$C:$C,""),"") | F67: =IFERROR(_xlfn.XLOOKUP(D67,HELPER!$B:$B,HELPER!$D:$D,""),"") | G67: 8 | I67: =IF(AND(H67<>"",IFERROR(_xlfn.XLOOKUP(D67,HELPER!$B:$B,HELPER!$E:$E,""),"")=""),"Missing price",IFERROR(_xlfn.XLOOKUP(D67,HELPER!$B:$B,HELPER!$E:$E,"")," ")) | J67: =IFERROR(H67*(IF(G67=8,I67*HELPER!$G$2,BOM!I67*HELPER!$G$3))," ") | L67: {=IFERROR(_xlfn.LET(_xlpm.films,Table4[Film],_xlpm.grades,Table4[Grade],_xlpm.pairs,_xlfn._xlws.FILTER(_xlfn.HSTACK(_xlpm.films,_xlpm.grades),(_xlpm.films<>"")*(TRIM(_xlpm.grades)<>"")),_xlpm.uniquePairs,_xlfn.UNIQUE(_xlpm.pairs),_xlpm.sortedPairs,_xlfn._xlws.SORT(_xlpm.uniquePairs,1,1),INDEX(_xlpm.sortedPairs,ROWS($L$2:L67),1)),"")} | M67: {=IFERROR(_xlfn.LET(_xlpm.films,Table4[Film],_xlpm.grades,Table4[Grade],_xlpm.pairs,_xlfn._xlws.FILTER(_xlfn.HSTACK(_xlpm.films,_xlpm.grades),(_xlpm.films<>"")*(TRIM(_xlpm.grades)<>"")),_xlpm.uniquePairs,_xlfn.UNIQUE(_xlpm.pairs),_xlpm.sortedPairs,_xlfn._xlws.SORT(_xlpm.uniquePairs,1,1),INDEX(_xlpm.sortedPairs,ROWS($M$2:M67),2)),"")} | N67: {=IF(OR(Table2[[#This Row],[Film]]="",Table2[[#This Row],[Grade]]=""),"",IFERROR(INDEX(Table4[Serial Number],MATCH(1,(Table4[Film]=Table2[[#This Row],[Film]])*(Table4[Grade]=Table2[[#This Row],[Grade]]),0)),""))} | O67: =IF(OR(Table2[[#This Row],[Film]]="",Table2[[#This Row],[Grade]]=""),"",SUMIFS(Table4[Price Calculated(€) Thickness & QTY related],Table4[Film],Table2[[#This Row],[Film]],Table4[Grade],Table2[[#This Row],[Grade]]))
A68: TIPA 312 MFG | B68: Ext. A (Out - Chillroll) | D68: =IF(C68="","",IFERROR(_xlfn.XLOOKUP(C68,HELPER!$A$2:$A$81,HELPER!$B$2:$B$81,""),D68)) | E68: =IFERROR(_xlfn.XLOOKUP(D68,HELPER!$B:$B,HELPER!$C:$C,""),"") | F68: =IFERROR(_xlfn.XLOOKUP(D68,HELPER!$B:$B,HELPER!$D:$D,""),"") | G68: 8 | I68: =IF(AND(H68<>"",IFERROR(_xlfn.XLOOKUP(D68,HELPER!$B:$B,HELPER!$E:$E,""),"")=""),"Missing price",IFERROR(_xlfn.XLOOKUP(D68,HELPER!$B:$B,HELPER!$E:$E,"")," ")) | J68: =IFERROR(H68*(IF(G68=8,I68*HELPER!$G$2,BOM!I68*HELPER!$G$3))," ") | L68: {=IFERROR(_xlfn.LET(_xlpm.films,Table4[Film],_xlpm.grades,Table4[Grade],_xlpm.pairs,_xlfn._xlws.FILTER(_xlfn.HSTACK(_xlpm.films,_xlpm.grades),(_xlpm.films<>"")*(TRIM(_xlpm.grades)<>"")),_xlpm.uniquePairs,_xlfn.UNIQUE(_xlpm.pairs),_xlpm.sortedPairs,_xlfn._xlws.SORT(_xlpm.uniquePairs,1,1),INDEX(_xlpm.sortedPairs,ROWS($L$2:L68),1)),"")} | M68: {=IFERROR(_xlfn.LET(_xlpm.films,Table4[Film],_xlpm.grades,Table4[Grade],_xlpm.pairs,_xlfn._xlws.FILTER(_xlfn.HSTACK(_xlpm.films,_xlpm.grades),(_xlpm.films<>"")*(TRIM(_xlpm.grades)<>"")),_xlpm.uniquePairs,_xlfn.UNIQUE(_xlpm.pairs),_xlpm.sortedPairs,_xlfn._xlws.SORT(_xlpm.uniquePairs,1,1),INDEX(_xlpm.sortedPairs,ROWS($M$2:M68),2)),"")} | N68: {=IF(OR(Table2[[#This Row],[Film]]="",Table2[[#This Row],[Grade]]=""),"",IFERROR(INDEX(Table4[Serial Number],MATCH(1,(Table4[Film]=Table2[[#This Row],[Film]])*(Table4[Grade]=Table2[[#This Row],[Grade]]),0)),""))} | O68: =IF(OR(Table2[[#This Row],[Film]]="",Table2[[#This Row],[Grade]]=""),"",SUMIFS(Table4[Price Calculated(€) Thickness & QTY related],Table4[Film],Table2[[#This Row],[Film]],Table4[Grade],Table2[[#This Row],[Grade]]))
A69: TIPA 312 MFG | B69: Ext. A (Out - Chillroll) | D69: =IF(C69="","",IFERROR(_xlfn.XLOOKUP(C69,HELPER!$A$2:$A$81,HELPER!$B$2:$B$81,""),D69)) | E69: =IFERROR(_xlfn.XLOOKUP(D69,HELPER!$B:$B,HELPER!$C:$C,""),"") | F69: =IFERROR(_xlfn.XLOOKUP(D69,HELPER!$B:$B,HELPER!$D:$D,""),"") | G69: 8 | I69: =IF(AND(H69<>"",IFERROR(_xlfn.XLOOKUP(D69,HELPER!$B:$B,HELPER!$E:$E,""),"")=""),"Missing price",IFERROR(_xlfn.XLOOKUP(D69,HELPER!$B:$B,HELPER!$E:$E,"")," ")) | J69: =IFERROR(H69*(IF(G69=8,I69*HELPER!$G$2,BOM!I69*HELPER!$G$3))," ") | L69: {=IFERROR(_xlfn.LET(_xlpm.films,Table4[Film],_xlpm.grades,Table4[Grade],_xlpm.pairs,_xlfn._xlws.FILTER(_xlfn.HSTACK(_xlpm.films,_xlpm.grades),(_xlpm.films<>"")*(TRIM(_xlpm.grades)<>"")),_xlpm.uniquePairs,_xlfn.UNIQUE(_xlpm.pairs),_xlpm.sortedPairs,_xlfn._xlws.SORT(_xlpm.uniquePairs,1,1),INDEX(_xlpm.sortedPairs,ROWS($L$2:L69),1)),"")} | M69: {=IFERROR(_xlfn.LET(_xlpm.films,Table4[Film],_xlpm.grades,Table4[Grade],_xlpm.pairs,_xlfn._xlws.FILTER(_xlfn.HSTACK(_xlpm.films,_xlpm.grades),(_xlpm.films<>"")*(TRIM(_xlpm.grades)<>"")),_xlpm.uniquePairs,_xlfn.UNIQUE(_xlpm.pairs),_xlpm.sortedPairs,_xlfn._xlws.SORT(_xlpm.uniquePairs,1,1),INDEX(_xlpm.sortedPairs,ROWS($M$2:M69),2)),"")} | N69: {=IF(OR(Table2[[#This Row],[Film]]="",Table2[[#This Row],[Grade]]=""),"",IFERROR(INDEX(Table4[Serial Number],MATCH(1,(Table4[Film]=Table2[[#This Row],[Film]])*(Table4[Grade]=Table2[[#This Row],[Grade]]),0)),""))} | O69: =IF(OR(Table2[[#This Row],[Film]]="",Table2[[#This Row],[Grade]]=""),"",SUMIFS(Table4[Price Calculated(€) Thickness & QTY related],Table4[Film],Table2[[#This Row],[Film]],Table4[Grade],Table2[[#This Row],[Grade]]))
A70: TIPA 312 MFG | B70: Ext. A (Out - Chillroll) | D70: =IF(C70="","",IFERROR(_xlfn.XLOOKUP(C70,HELPER!$A$2:$A$81,HELPER!$B$2:$B$81,""),D70)) | E70: =IFERROR(_xlfn.XLOOKUP(D70,HELPER!$B:$B,HELPER!$C:$C,""),"") | F70: =IFERROR(_xlfn.XLOOKUP(D70,HELPER!$B:$B,HELPER!$D:$D,""),"") | G70: 8 | I70: =IF(AND(H70<>"",IFERROR(_xlfn.XLOOKUP(D70,HELPER!$B:$B,HELPER!$E:$E,""),"")=""),"Missing price",IFERROR(_xlfn.XLOOKUP(D70,HELPER!$B:$B,HELPER!$E:$E,"")," ")) | J70: =IFERROR(H70*(IF(G70=8,I70*HELPER!$G$2,BOM!I70*HELPER!$G$3))," ") | L70: {=IFERROR(_xlfn.LET(_xlpm.films,Table4[Film],_xlpm.grades,Table4[Grade],_xlpm.pairs,_xlfn._xlws.FILTER(_xlfn.HSTACK(_xlpm.films,_xlpm.grades),(_xlpm.films<>"")*(TRIM(_xlpm.grades)<>"")),_xlpm.uniquePairs,_xlfn.UNIQUE(_xlpm.pairs),_xlpm.sortedPairs,_xlfn._xlws.SORT(_xlpm.uniquePairs,1,1),INDEX(_xlpm.sortedPairs,ROWS($L$2:L70),1)),"")} | M70: {=IFERROR(_xlfn.LET(_xlpm.films,Table4[Film],_xlpm.grades,Table4[Grade],_xlpm.pairs,_xlfn._xlws.FILTER(_xlfn.HSTACK(_xlpm.films,_xlpm.grades),(_xlpm.films<>"")*(TRIM(_xlpm.grades)<>"")),_xlpm.uniquePairs,_xlfn.UNIQUE(_xlpm.pairs),_xlpm.sortedPairs,_xlfn._xlws.SORT(_xlpm.uniquePairs,1,1),INDEX(_xlpm.sortedPairs,ROWS($M$2:M70),2)),"")} | N70: {=IF(OR(Table2[[#This Row],[Film]]="",Table2[[#This Row],[Grade]]=""),"",IFERROR(INDEX(Table4[Serial Number],MATCH(1,(Table4[Film]=Table2[[#This Row],[Film]])*(Table4[Grade]=Table2[[#This Row],[Grade]]),0)),""))} | O70: =IF(OR(Table2[[#This Row],[Film]]="",Table2[[#This Row],[Grade]]=""),"",SUMIFS(Table4[Price Calculated(€) Thickness & QTY related],Table4[Film],Table2[[#This Row],[Film]],Table4[Grade],Table2[[#This Row],[Grade]]))
A71: TIPA 312 MFG | B71: Ext. A (Out - Chillroll) | D71: =IF(C71="","",IFERROR(_xlfn.XLOOKUP(C71,HELPER!$A$2:$A$81,HELPER!$B$2:$B$81,""),D71)) | E71: =IFERROR(_xlfn.XLOOKUP(D71,HELPER!$B:$B,HELPER!$C:$C,""),"") | F71: =IFERROR(_xlfn.XLOOKUP(D71,HELPER!$B:$B,HELPER!$D:$D,""),"") | G71: 8 | I71: =IF(AND(H71<>"",IFERROR(_xlfn.XLOOKUP(D71,HELPER!$B:$B,HELPER!$E:$E,""),"")=""),"Missing price",IFERROR(_xlfn.XLOOKUP(D71,HELPER!$B:$B,HELPER!$E:$E,"")," ")) | J71: =IFERROR(H71*(IF(G71=8,I71*HELPER!$G$2,BOM!I71*HELPER!$G$3))," ") | L71: {=IFERROR(_xlfn.LET(_xlpm.films,Table4[Film],_xlpm.grades,Table4[Grade],_xlpm.pairs,_xlfn._xlws.FILTER(_xlfn.HSTACK(_xlpm.films,_xlpm.grades),(_xlpm.films<>"")*(TRIM(_xlpm.grades)<>"")),_xlpm.uniquePairs,_xlfn.UNIQUE(_xlpm.pairs),_xlpm.sortedPairs,_xlfn._xlws.SORT(_xlpm.uniquePairs,1,1),INDEX(_xlpm.sortedPairs,ROWS($L$2:L71),1)),"")} | M71: {=IFERROR(_xlfn.LET(_xlpm.films,Table4[Film],_xlpm.grades,Table4[Grade],_xlpm.pairs,_xlfn._xlws.FILTER(_xlfn.HSTACK(_xlpm.films,_xlpm.grades),(_xlpm.films<>"")*(TRIM(_xlpm.grades)<>"")),_xlpm.uniquePairs,_xlfn.UNIQUE(_xlpm.pairs),_xlpm.sortedPairs,_xlfn._xlws.SORT(_xlpm.uniquePairs,1,1),INDEX(_xlpm.sortedPairs,ROWS($M$2:M71),2)),"")} | N71: {=IF(OR(Table2[[#This Row],[Film]]="",Table2[[#This Row],[Grade]]=""),"",IFERROR(INDEX(Table4[Serial Number],MATCH(1,(Table4[Film]=Table2[[#This Row],[Film]])*(Table4[Grade]=Table2[[#This Row],[Grade]]),0)),""))} | O71: =IF(OR(Table2[[#This Row],[Film]]="",Table2[[#This Row],[Grade]]=""),"",SUMIFS(Table4[Price Calculated(€) Thickness & QTY related],Table4[Film],Table2[[#This Row],[Film]],Table4[Grade],Table2[[#This Row],[Grade]]))
A72: TIPA 312 MFG | B72: Ext. B | D72: =IF(C72="","",IFERROR(_xlfn.XLOOKUP(C72,HELPER!$A$2:$A$81,HELPER!$B$2:$B$81,""),D72)) | E72: =IFERROR(_xlfn.XLOOKUP(D72,HELPER!$B:$B,HELPER!$C:$C,""),"") | F72: =IFERROR(_xlfn.XLOOKUP(D72,HELPER!$B:$B,HELPER!$D:$D,""),"") | G72: 24 | I72: =IF(AND(H72<>"",IFERROR(_xlfn.XLOOKUP(D72,HELPER!$B:$B,HELPER!$E:$E,""),"")=""),"Missing price",IFERROR(_xlfn.XLOOKUP(D72,HELPER!$B:$B,HELPER!$E:$E,"")," ")) | J72: =IFERROR(H72*(IF(G72=8,I72*HELPER!$G$2,BOM!I72*HELPER!$G$3))," ") | L72: {=IFERROR(_xlfn.LET(_xlpm.films,Table4[Film],_xlpm.grades,Table4[Grade],_xlpm.pairs,_xlfn._xlws.FILTER(_xlfn.HSTACK(_xlpm.films,_xlpm.grades),(_xlpm.films<>"")*(TRIM(_xlpm.grades)<>"")),_xlpm.uniquePairs,_xlfn.UNIQUE(_xlpm.pairs),_xlpm.sortedPairs,_xlfn._xlws.SORT(_xlpm.uniquePairs,1,1),INDEX(_xlpm.sortedPairs,ROWS($L$2:L72),1)),"")} | M72: {=IFERROR(_xlfn.LET(_xlpm.films,Table4[Film],_xlpm.grades,Table4[Grade],_xlpm.pairs,_xlfn._xlws.FILTER(_xlfn.HSTACK(_xlpm.films,_xlpm.grades),(_xlpm.films<>"")*(TRIM(_xlpm.grades)<>"")),_xlpm.uniquePairs,_xlfn.UNIQUE(_xlpm.pairs),_xlpm.sortedPairs,_xlfn._xlws.SORT(_xlpm.uniquePairs,1,1),INDEX(_xlpm.sortedPairs,ROWS($M$2:M72),2)),"")} | N72: {=IF(OR(Table2[[#This Row],[Film]]="",Table2[[#This Row],[Grade]]=""),"",IFERROR(INDEX(Table4[Serial Number],MATCH(1,(Table4[Film]=Table2[[#This Row],[Film]])*(Table4[Grade]=Table2[[#This Row],[Grade]]),0)),""))} | O72: =IF(OR(Table2[[#This Row],[Film]]="",Table2[[#This Row],[Grade]]=""),"",SUMIFS(Table4[Price Calculated(€) Thickness & QTY related],Table4[Film],Table2[[#This Row],[Film]],Table4[Grade],Table2[[#This Row],[Grade]]))
A73: TIPA 312 MFG | B73: Ext. B | D73: =IF(C73="","",IFERROR(_xlfn.XLOOKUP(C73,HELPER!$A$2:$A$81,HELPER!$B$2:$B$81,""),D73)) | E73: =IFERROR(_xlfn.XLOOKUP(D73,HELPER!$B:$B,HELPER!$C:$C,""),"") | F73: =IFERROR(_xlfn.XLOOKUP(D73,HELPER!$B:$B,HELPER!$D:$D,""),"") | G73: 24 | I73: =IF(AND(H73<>"",IFERROR(_xlfn.XLOOKUP(D73,HELPER!$B:$B,HELPER!$E:$E,""),"")=""),"Missing price",IFERROR(_xlfn.XLOOKUP(D73,HELPER!$B:$B,HELPER!$E:$E,"")," ")) | J73: =IFERROR(H73*(IF(G73=8,I73*HELPER!$G$2,BOM!I73*HELPER!$G$3))," ") | L73: {=IFERROR(_xlfn.LET(_xlpm.films,Table4[Film],_xlpm.grades,Table4[Grade],_xlpm.pairs,_xlfn._xlws.FILTER(_xlfn.HSTACK(_xlpm.films,_xlpm.grades),(_xlpm.films<>"")*(TRIM(_xlpm.grades)<>"")),_xlpm.uniquePairs,_xlfn.UNIQUE(_xlpm.pairs),_xlpm.sortedPairs,_xlfn._xlws.SORT(_xlpm.uniquePairs,1,1),INDEX(_xlpm.sortedPairs,ROWS($L$2:L73),1)),"")} | M73: {=IFERROR(_xlfn.LET(_xlpm.films,Table4[Film],_xlpm.grades,Table4[Grade],_xlpm.pairs,_xlfn._xlws.FILTER(_xlfn.HSTACK(_xlpm.films,_xlpm.grades),(_xlpm.films<>"")*(TRIM(_xlpm.grades)<>"")),_xlpm.uniquePairs,_xlfn.UNIQUE(_xlpm.pairs),_xlpm.sortedPairs,_xlfn._xlws.SORT(_xlpm.uniquePairs,1,1),INDEX(_xlpm.sortedPairs,ROWS($M$2:M73),2)),"")} | N73: {=IF(OR(Table2[[#This Row],[Film]]="",Table2[[#This Row],[Grade]]=""),"",IFERROR(INDEX(Table4[Serial Number],MATCH(1,(Table4[Film]=Table2[[#This Row],[Film]])*(Table4[Grade]=Table2[[#This Row],[Grade]]),0)),""))} | O73: =IF(OR(Table2[[#This Row],[Film]]="",Table2[[#This Row],[Grade]]=""),"",SUMIFS(Table4[Price Calculated(€) Thickness & QTY related],Table4[Film],Table2[[#This Row],[Film]],Table4[Grade],Table2[[#This Row],[Grade]]))
A74: TIPA 312 MFG | B74: Ext. B | D74: =IF(C74="","",IFERROR(_xlfn.XLOOKUP(C74,HELPER!$A$2:$A$81,HELPER!$B$2:$B$81,""),D74)) | E74: =IFERROR(_xlfn.XLOOKUP(D74,HELPER!$B:$B,HELPER!$C:$C,""),"") | F74: =IFERROR(_xlfn.XLOOKUP(D74,HELPER!$B:$B,HELPER!$D:$D,""),"") | G74: 24 | I74: =IF(AND(H74<>"",IFERROR(_xlfn.XLOOKUP(D74,HELPER!$B:$B,HELPER!$E:$E,""),"")=""),"Missing price",IFERROR(_xlfn.XLOOKUP(D74,HELPER!$B:$B,HELPER!$E:$E,"")," ")) | J74: =IFERROR(H74*(IF(G74=8,I74*HELPER!$G$2,BOM!I74*HELPER!$G$3))," ") | L74: {=IFERROR(_xlfn.LET(_xlpm.films,Table4[Film],_xlpm.grades,Table4[Grade],_xlpm.pairs,_xlfn._xlws.FILTER(_xlfn.HSTACK(_xlpm.films,_xlpm.grades),(_xlpm.films<>"")*(TRIM(_xlpm.grades)<>"")),_xlpm.uniquePairs,_xlfn.UNIQUE(_xlpm.pairs),_xlpm.sortedPairs,_xlfn._xlws.SORT(_xlpm.uniquePairs,1,1),INDEX(_xlpm.sortedPairs,ROWS($L$2:L74),1)),"")} | M74: {=IFERROR(_xlfn.LET(_xlpm.films,Table4[Film],_xlpm.grades,Table4[Grade],_xlpm.pairs,_xlfn._xlws.FILTER(_xlfn.HSTACK(_xlpm.films,_xlpm.grades),(_xlpm.films<>"")*(TRIM(_xlpm.grades)<>"")),_xlpm.uniquePairs,_xlfn.UNIQUE(_xlpm.pairs),_xlpm.sortedPairs,_xlfn._xlws.SORT(_xlpm.uniquePairs,1,1),INDEX(_xlpm.sortedPairs,ROWS($M$2:M74),2)),"")} | N74: {=IF(OR(Table2[[#This Row],[Film]]="",Table2[[#This Row],[Grade]]=""),"",IFERROR(INDEX(Table4[Serial Number],MATCH(1,(Table4[Film]=Table2[[#This Row],[Film]])*(Table4[Grade]=Table2[[#This Row],[Grade]]),0)),""))} | O74: =IF(OR(Table2[[#This Row],[Film]]="",Table2[[#This Row],[Grade]]=""),"",SUMIFS(Table4[Price Calculated(€) Thickness & QTY related],Table4[Film],Table2[[#This Row],[Film]],Table4[Grade],Table2[[#This Row],[Grade]]))
A75: TIPA 312 MFG | B75: Ext. B | D75: =IF(C75="","",IFERROR(_xlfn.XLOOKUP(C75,HELPER!$A$2:$A$81,HELPER!$B$2:$B$81,""),D75)) | E75: =IFERROR(_xlfn.XLOOKUP(D75,HELPER!$B:$B,HELPER!$C:$C,""),"") | F75: =IFERROR(_xlfn.XLOOKUP(D75,HELPER!$B:$B,HELPER!$D:$D,""),"") | G75: 24 | I75: =IF(AND(H75<>"",IFERROR(_xlfn.XLOOKUP(D75,HELPER!$B:$B,HELPER!$E:$E,""),"")=""),"Missing price",IFERROR(_xlfn.XLOOKUP(D75,HELPER!$B:$B,HELPER!$E:$E,"")," ")) | J75: =IFERROR(H75*(IF(G75=8,I75*HELPER!$G$2,BOM!I75*HELPER!$G$3))," ") | L75: {=IFERROR(_xlfn.LET(_xlpm.films,Table4[Film],_xlpm.grades,Table4[Grade],_xlpm.pairs,_xlfn._xlws.FILTER(_xlfn.HSTACK(_xlpm.films,_xlpm.grades),(_xlpm.films<>"")*(TRIM(_xlpm.grades)<>"")),_xlpm.uniquePairs,_xlfn.UNIQUE(_xlpm.pairs),_xlpm.sortedPairs,_xlfn._xlws.SORT(_xlpm.uniquePairs,1,1),INDEX(_xlpm.sortedPairs,ROWS($L$2:L75),1)),"")} | M75: {=IFERROR(_xlfn.LET(_xlpm.films,Table4[Film],_xlpm.grades,Table4[Grade],_xlpm.pairs,_xlfn._xlws.FILTER(_xlfn.HSTACK(_xlpm.films,_xlpm.grades),(_xlpm.films<>"")*(TRIM(_xlpm.grades)<>"")),_xlpm.uniquePairs,_xlfn.UNIQUE(_xlpm.pairs),_xlpm.sortedPairs,_xlfn._xlws.SORT(_xlpm.uniquePairs,1,1),INDEX(_xlpm.sortedPairs,ROWS($M$2:M75),2)),"")} | N75: {=IF(OR(Table2[[#This Row],[Film]]="",Table2[[#This Row],[Grade]]=""),"",IFERROR(INDEX(Table4[Serial Number],MATCH(1,(Table4[Film]=Table2[[#This Row],[Film]])*(Table4[Grade]=Table2[[#This Row],[Grade]]),0)),""))} | O75: =IF(OR(Table2[[#This Row],[Film]]="",Table2[[#This Row],[Grade]]=""),"",SUMIFS(Table4[Price Calculated(€) Thickness & QTY related],Table4[Film],Table2[[#This Row],[Film]],Table4[Grade],Table2[[#This Row],[Grade]]))
A76: TIPA 312 MFG | B76: Ext. B | C76: AO-PBS | D76: =IF(C76="","",IFERROR(_xlfn.XLOOKUP(C76,HELPER!$A$2:$A$81,HELPER!$B$2:$B$81,""),D76)) -> S723 | E76: =IFERROR(_xlfn.XLOOKUP(D76,HELPER!$B:$B,HELPER!$C:$C,""),"") -> RM TA45-08 S723 | F76: =IFERROR(_xlfn.XLOOKUP(D76,HELPER!$B:$B,HELPER!$D:$D,""),"") -> Resin 6 | G76: 24 | H76: 0.015 | I76: =IF(AND(H76<>"",IFERROR(_xlfn.XLOOKUP(D76,HELPER!$B:$B,HELPER!$E:$E,""),"")=""),"Missing price",IFERROR(_xlfn.XLOOKUP(D76,HELPER!$B:$B,HELPER!$E:$E,"")," ")) -> 16.16 | J76: =IFERROR(H76*(IF(G76=8,I76*HELPER!$G$2,BOM!I76*HELPER!$G$3))," ") -> 0.14544 | L76: {=IFERROR(_xlfn.LET(_xlpm.films,Table4[Film],_xlpm.grades,Table4[Grade],_xlpm.pairs,_xlfn._xlws.FILTER(_xlfn.HSTACK(_xlpm.films,_xlpm.grades),(_xlpm.films<>"")*(TRIM(_xlpm.grades)<>"")),_xlpm.uniquePairs,_xlfn.UNIQUE(_xlpm.pairs),_xlpm.sortedPairs,_xlfn._xlws.SORT(_xlpm.uniquePairs,1,1),INDEX(_xlpm.sortedPairs,ROWS($L$2:L76),1)),"")} | M76: {=IFERROR(_xlfn.LET(_xlpm.films,Table4[Film],_xlpm.grades,Table4[Grade],_xlpm.pairs,_xlfn._xlws.FILTER(_xlfn.HSTACK(_xlpm.films,_xlpm.grades),(_xlpm.films<>"")*(TRIM(_xlpm.grades)<>"")),_xlpm.uniquePairs,_xlfn.UNIQUE(_xlpm.pairs),_xlpm.sortedPairs,_xlfn._xlws.SORT(_xlpm.uniquePairs,1,1),INDEX(_xlpm.sortedPairs,ROWS($M$2:M76),2)),"")} | N76: {=IF(OR(Table2[[#This Row],[Film]]="",Table2[[#This Row],[Grade]]=""),"",IFERROR(INDEX(Table4[Serial Number],MATCH(1,(Table4[Film]=Table2[[#This Row],[Film]])*(Table4[Grade]=Table2[[#This Row],[Grade]]),0)),""))} | O76: =IF(OR(Table2[[#This Row],[Film]]="",Table2[[#This Row],[Grade]]=""),"",SUMIFS(Table4[Price Calculated(€) Thickness & QTY related],Table4[Film],Table2[[#This Row],[Film]],Table4[Grade],Table2[[#This Row],[Grade]]))
A77: TIPA 312 MFG | B77: Ext. B | D77: =IF(C77="","",IFERROR(_xlfn.XLOOKUP(C77,HELPER!$A$2:$A$81,HELPER!$B$2:$B$81,""),D77)) | E77: =IFERROR(_xlfn.XLOOKUP(D77,HELPER!$B:$B,HELPER!$C:$C,""),"") | F77: =IFERROR(_xlfn.XLOOKUP(D77,HELPER!$B:$B,HELPER!$D:$D,""),"") | G77: 24 | I77: =IF(AND(H77<>"",IFERROR(_xlfn.XLOOKUP(D77,HELPER!$B:$B,HELPER!$E:$E,""),"")=""),"Missing price",IFERROR(_xlfn.XLOOKUP(D77,HELPER!$B:$B,HELPER!$E:$E,"")," ")) | J77: =IFERROR(H77*(IF(G77=8,I77*HELPER!$G$2,BOM!I77*HELPER!$G$3))," ") | L77: {=IFERROR(_xlfn.LET(_xlpm.films,Table4[Film],_xlpm.grades,Table4[Grade],_xlpm.pairs,_xlfn._xlws.FILTER(_xlfn.HSTACK(_xlpm.films,_xlpm.grades),(_xlpm.films<>"")*(TRIM(_xlpm.grades)<>"")),_xlpm.uniquePairs,_xlfn.UNIQUE(_xlpm.pairs),_xlpm.sortedPairs,_xlfn._xlws.SORT(_xlpm.uniquePairs,1,1),INDEX(_xlpm.sortedPairs,ROWS($L$2:L77),1)),"")} | M77: {=IFERROR(_xlfn.LET(_xlpm.films,Table4[Film],_xlpm.grades,Table4[Grade],_xlpm.pairs,_xlfn._xlws.FILTER(_xlfn.HSTACK(_xlpm.films,_xlpm.grades),(_xlpm.films<>"")*(TRIM(_xlpm.grades)<>"")),_xlpm.uniquePairs,_xlfn.UNIQUE(_xlpm.pairs),_xlpm.sortedPairs,_xlfn._xlws.SORT(_xlpm.uniquePairs,1,1),INDEX(_xlpm.sortedPairs,ROWS($M$2:M77),2)),"")} | N77: {=IF(OR(Table2[[#This Row],[Film]]="",Table2[[#This Row],[Grade]]=""),"",IFERROR(INDEX(Table4[Serial Number],MATCH(1,(Table4[Film]=Table2[[#This Row],[Film]])*(Table4[Grade]=Table2[[#This Row],[Grade]]),0)),""))} | O77: =IF(OR(Table2[[#This Row],[Film]]="",Table2[[#This Row],[Grade]]=""),"",SUMIFS(Table4[Price Calculated(€) Thickness & QTY related],Table4[Film],Table2[[#This Row],[Film]],Table4[Grade],Table2[[#This Row],[Grade]]))
A78: TIPA 312 MFG | B78: Ext. B | D78: =IF(C78="","",IFERROR(_xlfn.XLOOKUP(C78,HELPER!$A$2:$A$81,HELPER!$B$2:$B$81,""),D78)) | E78: =IFERROR(_xlfn.XLOOKUP(D78,HELPER!$B:$B,HELPER!$C:$C,""),"") | F78: =IFERROR(_xlfn.XLOOKUP(D78,HELPER!$B:$B,HELPER!$D:$D,""),"") | G78: 24 | I78: =IF(AND(H78<>"",IFERROR(_xlfn.XLOOKUP(D78,HELPER!$B:$B,HELPER!$E:$E,""),"")=""),"Missing price",IFERROR(_xlfn.XLOOKUP(D78,HELPER!$B:$B,HELPER!$E:$E,"")," ")) | J78: =IFERROR(H78*(IF(G78=8,I78*HELPER!$G$2,BOM!I78*HELPER!$G$3))," ") | L78: {=IFERROR(_xlfn.LET(_xlpm.films,Table4[Film],_xlpm.grades,Table4[Grade],_xlpm.pairs,_xlfn._xlws.FILTER(_xlfn.HSTACK(_xlpm.films,_xlpm.grades),(_xlpm.films<>"")*(TRIM(_xlpm.grades)<>"")),_xlpm.uniquePairs,_xlfn.UNIQUE(_xlpm.pairs),_xlpm.sortedPairs,_xlfn._xlws.SORT(_xlpm.uniquePairs,1,1),INDEX(_xlpm.sortedPairs,ROWS($L$2:L78),1)),"")} | M78: {=IFERROR(_xlfn.LET(_xlpm.films,Table4[Film],_xlpm.grades,Table4[Grade],_xlpm.pairs,_xlfn._xlws.FILTER(_xlfn.HSTACK(_xlpm.films,_xlpm.grades),(_xlpm.films<>"")*(TRIM(_xlpm.grades)<>"")),_xlpm.uniquePairs,_xlfn.UNIQUE(_xlpm.pairs),_xlpm.sortedPairs,_xlfn._xlws.SORT(_xlpm.uniquePairs,1,1),INDEX(_xlpm.sortedPairs,ROWS($M$2:M78),2)),"")} | N78: {=IF(OR(Table2[[#This Row],[Film]]="",Table2[[#This Row],[Grade]]=""),"",IFERROR(INDEX(Table4[Serial Number],MATCH(1,(Table4[Film]=Table2[[#This Row],[Film]])*(Table4[Grade]=Table2[[#This Row],[Grade]]),0)),""))} | O78: =IF(OR(Table2[[#This Row],[Film]]="",Table2[[#This Row],[Grade]]=""),"",SUMIFS(Table4[Price Calculated(€) Thickness & QTY related],Table4[Film],Table2[[#This Row],[Film]],Table4[Grade],Table2[[#This Row],[Grade]]))
